Workbook

Sheet Dashboard
A1: Tablero 4DX — GBM Nicaragua
A2: WIG de la compañía: Construir la utilidad neta (NAT) de Nicaragua — $1M en 2027, $2M (7%) en 2028, $2.4M (8%) en 2029
A4: Metas de Utilidad Neta (NAT) 2027 → 2029 (base 2026)
A5: Año | B5: Ingreso | C5: GP % | D5: Meta NAT | E5: NAT % | F5: NAT real | G5: Estado | H5: Ir a pestaña
A6: 2026 (estimado) | B6: 18656000 | C6: 0.144 | D6: 375000 | E6: =D6/B6 -> 0.020100772 | G6: =IF(F6="","—",IF(F6>=D6*0.95,"En meta",IF(F6>=D6*0.8,"Riesgo","Atrasado"))) -> —
A7: 2027 (meta) | B7: 21000000 | C7: 0.16 | D7: 1000000 | E7: =D7/B7 -> 0.047619048 | G7: =IF(F7="","—",IF(F7>=D7*0.95,"En meta",IF(F7>=D7*0.8,"Riesgo","Atrasado"))) -> — | H7: Ver 2027
A8: 2028 (meta) | B8: 28571000 | C8: 0.164 | D8: 2000000 | E8: =D8/B8 -> 0.07000105 | G8: =IF(F8="","—",IF(F8>=D8*0.95,"En meta",IF(F8>=D8*0.8,"Riesgo","Atrasado"))) -> — | H8: Ver 2028
A9: 2029 (meta) | B9: 30571000 | C9: 0.165 | D9: 2445680 | E9: =D9/B9 -> 0.08 | G9: =IF(F9="","—",IF(F9>=D9*0.95,"En meta",IF(F9>=D9*0.8,"Riesgo","Atrasado"))) -> — | H9: Ver 2029
A10: El tope de impuesto mínimo (3% sobre ventas) fija el piso de impuestos; por eso la meta se gana en GP% y en mantener el costo local plano, no solo en crecer ventas.
A12: Cobertura de backlog — GP comprometido vs meta del año
A13: Año | B13: GP meta | C13: GP comprometido | D13: Brecha (falta vender) | E13: % cobertura
A14: 2027 | B14: ='2027'!$B$5 -> 3360000 | C14: ='2027'!$B$6 -> 0 | D14: ='2027'!$B$7 -> 3360000 | E14: ='2027'!$E$6 -> 0
A15: 2028 | B15: ='2028'!$B$5 -> 4685644 | C15: ='2028'!$B$6 -> 0 | D15: ='2028'!$B$7 -> 4685644 | E15: ='2028'!$E$6 -> 0
A16: 2029 | B16: ='2029'!$B$5 -> 5044215 | C16: ='2029'!$B$6 -> 0 | D16: ='2029'!$B$7 -> 5044215 | E16: ='2029'!$E$6 -> 0
A18: Seguimiento mensual NAT — año en curso
A19: Meta anual NAT: | C19: 1000000
A21: Mes | B21: Meta mensual | C21: NAT real | D21: Meta acum. | E21: Real acum. | F21: % avance | G21: Estado
A22: 46388 | B22: =$C$19/12 -> 83333.333 | D22: =SUM($B$22:B22) -> 83333.333 | E22: =SUM($C$22:C22) -> 0 | F22: =IF(COUNT($C$22:C22)=0,"",E22/D22) | G22: =IF(F22="","",IF(F22>=0.95,"En meta",IF(F22>=0.8,"Riesgo","Atrasado")))
A23: 46419 | B23: =$C$19/12 -> 83333.333 | D23: =SUM($B$22:B23) -> 166666.67 | E23: =SUM($C$22:C23) -> 0 | F23: =IF(COUNT($C$22:C23)=0,"",E23/D23) | G23: =IF(F23="","",IF(F23>=0.95,"En meta",IF(F23>=0.8,"Riesgo","Atrasado")))
A24: 46447 | B24: =$C$19/12 -> 83333.333 | D24: =SUM($B$22:B24) -> 250000 | E24: =SUM($C$22:C24) -> 0 | F24: =IF(COUNT($C$22:C24)=0,"",E24/D24) | G24: =IF(F24="","",IF(F24>=0.95,"En meta",IF(F24>=0.8,"Riesgo","Atrasado")))
A25: 46478 | B25: =$C$19/12 -> 83333.333 | D25: =SUM($B$22:B25) -> 333333.33 | E25: =SUM($C$22:C25) -> 0 | F25: =IF(COUNT($C$22:C25)=0,"",E25/D25) | G25: =IF(F25="","",IF(F25>=0.95,"En meta",IF(F25>=0.8,"Riesgo","Atrasado")))
A26: 46508 | B26: =$C$19/12 -> 83333.333 | D26: =SUM($B$22:B26) -> 416666.67 | E26: =SUM($C$22:C26) -> 0 | F26: =IF(COUNT($C$22:C26)=0,"",E26/D26) | G26: =IF(F26="","",IF(F26>=0.95,"En meta",IF(F26>=0.8,"Riesgo","Atrasado")))
A27: 46539 | B27: =$C$19/12 -> 83333.333 | D27: =SUM($B$22:B27) -> 500000 | E27: =SUM($C$22:C27) -> 0 | F27: =IF(COUNT($C$22:C27)=0,"",E27/D27) | G27: =IF(F27="","",IF(F27>=0.95,"En meta",IF(F27>=0.8,"Riesgo","Atrasado")))
A28: 46569 | B28: =$C$19/12 -> 83333.333 | D28: =SUM($B$22:B28) -> 583333.33 | E28: =SUM($C$22:C28) -> 0 | F28: =IF(COUNT($C$22:C28)=0,"",E28/D28) | G28: =IF(F28="","",IF(F28>=0.95,"En meta",IF(F28>=0.8,"Riesgo","Atrasado")))
A29: 46600 | B29: =$C$19/12 -> 83333.333 | D29: =SUM($B$22:B29) -> 666666.67 | E29: =SUM($C$22:C29) -> 0 | F29: =IF(COUNT($C$22:C29)=0,"",E29/D29) | G29: =IF(F29="","",IF(F29>=0.95,"En meta",IF(F29>=0.8,"Riesgo","Atrasado")))
A30: 46631 | B30: =$C$19/12 -> 83333.333 | D30: =SUM($B$22:B30) -> 750000 | E30: =SUM($C$22:C30) -> 0 | F30: =IF(COUNT($C$22:C30)=0,"",E30/D30) | G30: =IF(F30="","",IF(F30>=0.95,"En meta",IF(F30>=0.8,"Riesgo","Atrasado")))
A31: 46661 | B31: =$C$19/12 -> 83333.333 | D31: =SUM($B$22:B31) -> 833333.33 | E31: =SUM($C$22:C31) -> 0 | F31: =IF(COUNT($C$22:C31)=0,"",E31/D31) | G31: =IF(F31="","",IF(F31>=0.95,"En meta",IF(F31>=0.8,"Riesgo","Atrasado")))
A32: 46692 | B32: =$C$19/12 -> 83333.333 | D32: =SUM($B$22:B32) -> 916666.67 | E32: =SUM($C$22:C32) -> 0 | F32: =IF(COUNT($C$22:C32)=0,"",E32/D32) | G32: =IF(F32="","",IF(F32>=0.95,"En meta",IF(F32>=0.8,"Riesgo","Atrasado")))
A33: 46722 | B33: =$C$19/12 -> 83333.333 | D33: =SUM($B$22:B33) -> 1000000 | E33: =SUM($C$22:C33) -> 0 | F33: =IF(COUNT($C$22:C33)=0,"",E33/D33) | G33: =IF(F33="","",IF(F33>=0.95,"En meta",IF(F33>=0.8,"Riesgo","Atrasado")))
A35: WIGs de soporte — estado al último dato ingresado
A36: # | B36: WIG de soporte | C36: Dueño | D36: Equipo | E36: Meta | F36: Último real | G36: Estado | H36: Ir a pestaña
A37: 1 | B37: Incrementar el Parque de Smart User en 500 equipos en el 2026 | C37: ='1. Smart User 500'!$B$4 -> Por asignar | D37: Pre-Sales, Del - DEX | E37: ='1. Smart User 500'!$B$5 -> 500 | F37: =IFERROR(LOOKUP(2,1/('1. Smart User 500'!$D$11:$D$39<>""),'1. Smart User 500'!$D$11:$D$39),"Sin datos") -> Sin datos | G37: =IFERROR(LOOKUP(2,1/('1. Smart User 500'!$D$11:$D$39<>""),'1. Smart User 500'!$H$11:$H$39),"Sin datos") -> Sin datos | H37: 1. Smart User 500
A38: 2 | B38: Lograr un Monthly Value de $X en advisory en el primer trimestre de 2027 | C38: ='2. MV Advisory'!$B$4 -> Por asignar | D38: Ventas, Customer Success, Pre-Sales, Del - TSS | E38: ='2. MV Advisory'!$B$5 -> 10000 | F38: =IFERROR(LOOKUP(2,1/('2. MV Advisory'!$D$11:$D$52<>""),'2. MV Advisory'!$D$11:$D$52),"Sin datos") -> Sin datos | G38: =IFERROR(LOOKUP(2,1/('2. MV Advisory'!$D$11:$D$52<>""),'2. MV Advisory'!$H$11:$H$52),"Sin datos") -> Sin datos | H38: 2. MV Advisory
A39: 3 | B39: Reconocer 10 negocios mayores a $30K de GP en el 2027 | C39: ='3. Negocios +30K GP'!$B$4 -> Por asignar | D39: Ventas, Pre-Sales | E39: ='3. Negocios +30K GP'!$B$5 -> 10 | F39: =IFERROR(LOOKUP(2,1/('3. Negocios +30K GP'!$D$11:$D$91<>""),'3. Negocios +30K GP'!$D$11:$D$91),"Sin datos") -> Sin datos | G39: =IFERROR(LOOKUP(2,1/('3. Negocios +30K GP'!$D$11:$D$91<>""),'3. Negocios +30K GP'!$H$11:$H$91),"Sin datos") -> Sin datos | H39: 3. Negocios +30K GP
A40: 4 | B40: Cumplir el 100% de entregas y colocaciones en tiempo y forma | C40: ='4. Entregas 100%'!$B$4 -> Por asignar | D40: Finanzas | E40: ='4. Entregas 100%'!$B$5 -> 1 | F40: =IFERROR(LOOKUP(2,1/('4. Entregas 100%'!$D$11:$D$91<>""),'4. Entregas 100%'!$D$11:$D$91),"Sin datos") -> Sin datos | G40: =IFERROR(LOOKUP(2,1/('4. Entregas 100%'!$D$11:$D$91<>""),'4. Entregas 100%'!$H$11:$H$91),"Sin datos") -> Sin datos | H40: 4. Entregas 100%
A41: 5 | B41: Incrementar el MV de servicios basados en el DC GBM San Marcos en $20,000 | C41: ='5. MV Datacenter'!$B$4 -> Por asignar | D41: Pre-Sales, Del - DC | E41: ='5. MV Datacenter'!$B$5 -> 20000 | F41: =IFERROR(LOOKUP(2,1/('5. MV Datacenter'!$D$11:$D$91<>""),'5. MV Datacenter'!$D$11:$D$91),"Sin datos") -> Sin datos | G41: =IFERROR(LOOKUP(2,1/('5. MV Datacenter'!$D$11:$D$91<>""),'5. MV Datacenter'!$H$11:$H$91),"Sin datos") -> Sin datos | H41: 5. MV Datacenter
A42: 6 | B42: Tener cero contratos expired en al menos 16 de los próximos 18 meses | C42: ='6. Cero Expired'!$B$4 -> Por asignar | D42: Customer Success, Del - DEX, Del - TSS, Del - DC | E42: ='6. Cero Expired'!$B$5 -> 0 | F42: =IFERROR(LOOKUP(2,1/('6. Cero Expired'!$D$11:$D$91<>""),'6. Cero Expired'!$D$11:$D$91),"Sin datos") -> Sin datos | G42: =IFERROR(LOOKUP(2,1/('6. Cero Expired'!$D$11:$D$91<>""),'6. Cero Expired'!$H$11:$H$91),"Sin datos") -> Sin datos | H42: 6. Cero Expired
A43: 7 | B43: Incrementar el MV de Digital Solutions en $30K/mes al 1ro de mayo 2027 | C43: ='7. MV Digital Sol'!$B$4 -> Por asignar | D43: Ventas, Del - DS | E43: ='7. MV Digital Sol'!$B$5 -> 30000 | F43: =IFERROR(LOOKUP(2,1/('7. MV Digital Sol'!$D$11:$D$56<>""),'7. MV Digital Sol'!$D$11:$D$56),"Sin datos") -> Sin datos | G43: =IFERROR(LOOKUP(2,1/('7. MV Digital Sol'!$D$11:$D$56<>""),'7. MV Digital Sol'!$H$11:$H$56),"Sin datos") -> Sin datos | H43: 7. MV Digital Sol
A44: 8 | B44: Lograr un GP consolidado de 16% en el 2027 | C44: ='8. GP 16%'!$B$4 -> Por asignar | D44: Finanzas (todas las áreas aportan) | E44: ='8. GP 16%'!$B$5 -> 0.16 | F44: =IFERROR(LOOKUP(2,1/('8. GP 16%'!$D$11:$D$28<>""),'8. GP 16%'!$D$11:$D$28),"Sin datos") -> Sin datos | G44: =IFERROR(LOOKUP(2,1/('8. GP 16%'!$D$11:$D$28<>""),'8. GP 16%'!$H$11:$H$28),"Sin datos") -> Sin datos | H44: 8. GP 16%
A45: 9 | B45: Incrementar el CSAT de X a Y, sosteniéndolo 4 meses consecutivos | C45: ='9. CSAT'!$B$4 -> Por asignar | D45: Customer Success (todas las áreas de entrega aportan) | E45: ='9. CSAT'!$B$5 -> 4.5 | F45: =IFERROR(LOOKUP(2,1/('9. CSAT'!$D$11:$D$28<>""),'9. CSAT'!$D$11:$D$28),"Sin datos") -> Sin datos | G45: =IFERROR(LOOKUP(2,1/('9. CSAT'!$D$11:$D$28<>""),'9. CSAT'!$H$11:$H$28),"Sin datos") -> Sin datos | H45: 9. CSAT
A46: 10 | B46: Sostener costos locales planos mientras crece el ingreso (apalancamiento operativo) | C46: ='10. Apalancamiento'!$B$4 -> Por asignar | D46: Finanzas, Customer Success, todas las áreas locales | E46: ='10. Apalancamiento'!$B$5 -> 0.09 | F46: =IFERROR(LOOKUP(2,1/('10. Apalancamiento'!$D$11:$D$28<>""),'10. Apalancamiento'!$D$11:$D$28),"Sin datos") -> Sin datos | G46: =IFERROR(LOOKUP(2,1/('10. Apalancamiento'!$D$11:$D$28<>""),'10. Apalancamiento'!$H$11:$H$28),"Sin datos") -> Sin datos | H46: 10. Apalancamiento
A47: 11 | B47: Recuperar el margen de Digital Solutions y eliminar líneas con GP negativo | C47: ='11. Recuperar DS'!$B$4 -> Por asignar | D47: Ventas, Pre-Sales, Del - DS, Finanzas | E47: ='11. Recuperar DS'!$B$5 -> 0 | F47: =IFERROR(LOOKUP(2,1/('11. Recuperar DS'!$D$11:$D$28<>""),'11. Recuperar DS'!$D$11:$D$28),"Sin datos") -> Sin datos | G47: =IFERROR(LOOKUP(2,1/('11. Recuperar DS'!$D$11:$D$28<>""),'11. Recuperar DS'!$H$11:$H$28),"Sin datos") -> Sin datos | H47: 11. Recuperar DS
A48: 12 | B48: Subir la utilización facturable de ingenieros locales de 42% a 48%+ | C48: ='12. Utilizacion'!$B$4 -> Por asignar | D48: Del - TSS, Del - DC, Customer Success, Pre-Sales | E48: ='12. Utilizacion'!$B$5 -> 0.48 | F48: =IFERROR(LOOKUP(2,1/('12. Utilizacion'!$D$11:$D$28<>""),'12. Utilizacion'!$D$11:$D$28),"Sin datos") -> Sin datos | G48: =IFERROR(LOOKUP(2,1/('12. Utilizacion'!$D$11:$D$28<>""),'12. Utilizacion'!$H$11:$H$28),"Sin datos") -> Sin datos | H48: 12. Utilizacion

Sheet 1. Smart User 500
A1: WIG 1 — Incrementar el Parque de Smart User en 500 equipos en el 2026
A2: Indicador lag: | B2: Equipos Smart User colocados (acumulado). 500 equipos a $40/mes = $6.4K MRR adicional en GP.
A3: De X a Y: | B3: De 0 a 500 equipos colocados, antes del 31 de diciembre de 2026.
A4: Dueño: | B4: Por asignar | D4: Equipo: | E4: Pre-Sales, Del - DEX
A5: Meta: | B5: 500 | D5: Inicio: | E5: 46188 | G5: Fin: | H5: 46384
A6: Leads: | B6: Hasta 8 indicadores predictivos a la derecha. L1–L2 = apuesta principal del equipo; L3–L8 = indicadores de apoyo. Nombre (fila 8) y meta semanal (fila 9) editables en azul.
A8: Periodos: | B8: =COUNT(A11:A39) -> 29 | H8: Lead → | I8: L1. Compromisos de asignación firmados (equipos) | K8: L2. Demos / POCs activos (Promerica, Disnorte, otros) | M8: L3. Presentaciones de oferta Smart User realizadas | O8: L4. Equipos cotizados en la semana | Q8: L5. Equipos en bodega listos para colocar | S8: L6. Clientes nuevos contactados con la oferta | U8: L7. % equipos colocados en ≤2 semanas tras firma | W8: (Disponible)
A9: Celdas azules = se digitan cada lunes. Celdas negras = fórmulas, no tocar. | H9: Meta → | I9: 20 | K9: 2 | M9: 3 | O9: 30 | Q9: 40 | S9: 2 | U9: 1
A10: # | B10: Semana | C10: Meta semana | D10: Real | E10: Meta acum. | F10: Real acum. | G10: % avance | H10: Estado | I10: Real | J10: % | K10: Real | L10: % | M10: Real | N10: % | O10: Real | P10: % | Q10: Real | R10: % | S10: Real | T10: % | U10: Real | V10: % | W10: Real | X10: %
A11: 1 | B11: 46188 | C11: =$B$5/$B$8 -> 17.241379 | E11: =SUM($C$11:C11) -> 17.241379 | F11: =SUM($D$11:D11) -> 0 | G11: =IF(COUNT($D$11:D11)=0,"",F11/E11) | H11: =IF(G11="","",IF(G11>=0.95,"En meta",IF(G11>=0.8,"Riesgo","Atrasado"))) | J11: =IF(I11="","",IF($I$9="","",IF($I$9=0,"",I11/$I$9))) | L11: =IF(K11="","",IF($K$9="","",IF($K$9=0,"",K11/$K$9))) | N11: =IF(M11="","",IF($M$9="","",IF($M$9=0,"",M11/$M$9))) | P11: =IF(O11="","",IF($O$9="","",IF($O$9=0,"",O11/$O$9))) | R11: =IF(Q11="","",IF($Q$9="","",IF($Q$9=0,"",Q11/$Q$9))) | T11: =IF(S11="","",IF($S$9="","",IF($S$9=0,"",S11/$S$9))) | V11: =IF(U11="","",IF($U$9="","",IF($U$9=0,"",U11/$U$9))) | X11: =IF(W11="","",IF($W$9="","",IF($W$9=0,"",W11/$W$9)))
A12: 2 | B12: 46195 | C12: =$B$5/$B$8 -> 17.241379 | E12: =SUM($C$11:C12) -> 34.482759 | F12: =SUM($D$11:D12) -> 0 | G12: =IF(COUNT($D$11:D12)=0,"",F12/E12) | H12: =IF(G12="","",IF(G12>=0.95,"En meta",IF(G12>=0.8,"Riesgo","Atrasado"))) | J12: =IF(I12="","",IF($I$9="","",IF($I$9=0,"",I12/$I$9))) | L12: =IF(K12="","",IF($K$9="","",IF($K$9=0,"",K12/$K$9))) | N12: =IF(M12="","",IF($M$9="","",IF($M$9=0,"",M12/$M$9))) | P12: =IF(O12="","",IF($O$9="","",IF($O$9=0,"",O12/$O$9))) | R12: =IF(Q12="","",IF($Q$9="","",IF($Q$9=0,"",Q12/$Q$9))) | T12: =IF(S12="","",IF($S$9="","",IF($S$9=0,"",S12/$S$9))) | V12: =IF(U12="","",IF($U$9="","",IF($U$9=0,"",U12/$U$9))) | X12: =IF(W12="","",IF($W$9="","",IF($W$9=0,"",W12/$W$9)))
A13: 3 | B13: 46202 | C13: =$B$5/$B$8 -> 17.241379 | E13: =SUM($C$11:C13) -> 51.724138 | F13: =SUM($D$11:D13) -> 0 | G13: =IF(COUNT($D$11:D13)=0,"",F13/E13) | H13: =IF(G13="","",IF(G13>=0.95,"En meta",IF(G13>=0.8,"Riesgo","Atrasado"))) | J13: =IF(I13="","",IF($I$9="","",IF($I$9=0,"",I13/$I$9))) | L13: =IF(K13="","",IF($K$9="","",IF($K$9=0,"",K13/$K$9))) | N13: =IF(M13="","",IF($M$9="","",IF($M$9=0,"",M13/$M$9))) | P13: =IF(O13="","",IF($O$9="","",IF($O$9=0,"",O13/$O$9))) | R13: =IF(Q13="","",IF($Q$9="","",IF($Q$9=0,"",Q13/$Q$9))) | T13: =IF(S13="","",IF($S$9="","",IF($S$9=0,"",S13/$S$9))) | V13: =IF(U13="","",IF($U$9="","",IF($U$9=0,"",U13/$U$9))) | X13: =IF(W13="","",IF($W$9="","",IF($W$9=0,"",W13/$W$9)))
A14: 4 | B14: 46209 | C14: =$B$5/$B$8 -> 17.241379 | E14: =SUM($C$11:C14) -> 68.965517 | F14: =SUM($D$11:D14) -> 0 | G14: =IF(COUNT($D$11:D14)=0,"",F14/E14) | H14: =IF(G14="","",IF(G14>=0.95,"En meta",IF(G14>=0.8,"Riesgo","Atrasado"))) | J14: =IF(I14="","",IF($I$9="","",IF($I$9=0,"",I14/$I$9))) | L14: =IF(K14="","",IF($K$9="","",IF($K$9=0,"",K14/$K$9))) | N14: =IF(M14="","",IF($M$9="","",IF($M$9=0,"",M14/$M$9))) | P14: =IF(O14="","",IF($O$9="","",IF($O$9=0,"",O14/$O$9))) | R14: =IF(Q14="","",IF($Q$9="","",IF($Q$9=0,"",Q14/$Q$9))) | T14: =IF(S14="","",IF($S$9="","",IF($S$9=0,"",S14/$S$9))) | V14: =IF(U14="","",IF($U$9="","",IF($U$9=0,"",U14/$U$9))) | X14: =IF(W14="","",IF($W$9="","",IF($W$9=0,"",W14/$W$9)))
A15: 5 | B15: 46216 | C15: =$B$5/$B$8 -> 17.241379 | E15: =SUM($C$11:C15) -> 86.206897 | F15: =SUM($D$11:D15) -> 0 | G15: =IF(COUNT($D$11:D15)=0,"",F15/E15) | H15: =IF(G15="","",IF(G15>=0.95,"En meta",IF(G15>=0.8,"Riesgo","Atrasado"))) | J15: =IF(I15="","",IF($I$9="","",IF($I$9=0,"",I15/$I$9))) | L15: =IF(K15="","",IF($K$9="","",IF($K$9=0,"",K15/$K$9))) | N15: =IF(M15="","",IF($M$9="","",IF($M$9=0,"",M15/$M$9))) | P15: =IF(O15="","",IF($O$9="","",IF($O$9=0,"",O15/$O$9))) | R15: =IF(Q15="","",IF($Q$9="","",IF($Q$9=0,"",Q15/$Q$9))) | T15: =IF(S15="","",IF($S$9="","",IF($S$9=0,"",S15/$S$9))) | V15: =IF(U15="","",IF($U$9="","",IF($U$9=0,"",U15/$U$9))) | X15: =IF(W15="","",IF($W$9="","",IF($W$9=0,"",W15/$W$9)))
A16: 6 | B16: 46223 | C16: =$B$5/$B$8 -> 17.241379 | E16: =SUM($C$11:C16) -> 103.44828 | F16: =SUM($D$11:D16) -> 0 | G16: =IF(COUNT($D$11:D16)=0,"",F16/E16) | H16: =IF(G16="","",IF(G16>=0.95,"En meta",IF(G16>=0.8,"Riesgo","Atrasado"))) | J16: =IF(I16="","",IF($I$9="","",IF($I$9=0,"",I16/$I$9))) | L16: =IF(K16="","",IF($K$9="","",IF($K$9=0,"",K16/$K$9))) | N16: =IF(M16="","",IF($M$9="","",IF($M$9=0,"",M16/$M$9))) | P16: =IF(O16="","",IF($O$9="","",IF($O$9=0,"",O16/$O$9))) | R16: =IF(Q16="","",IF($Q$9="","",IF($Q$9=0,"",Q16/$Q$9))) | T16: =IF(S16="","",IF($S$9="","",IF($S$9=0,"",S16/$S$9))) | V16: =IF(U16="","",IF($U$9="","",IF($U$9=0,"",U16/$U$9))) | X16: =IF(W16="","",IF($W$9="","",IF($W$9=0,"",W16/$W$9)))
A17: 7 | B17: 46230 | C17: =$B$5/$B$8 -> 17.241379 | E17: =SUM($C$11:C17) -> 120.68966 | F17: =SUM($D$11:D17) -> 0 | G17: =IF(COUNT($D$11:D17)=0,"",F17/E17) | H17: =IF(G17="","",IF(G17>=0.95,"En meta",IF(G17>=0.8,"Riesgo","Atrasado"))) | J17: =IF(I17="","",IF($I$9="","",IF($I$9=0,"",I17/$I$9))) | L17: =IF(K17="","",IF($K$9="","",IF($K$9=0,"",K17/$K$9))) | N17: =IF(M17="","",IF($M$9="","",IF($M$9=0,"",M17/$M$9))) | P17: =IF(O17="","",IF($O$9="","",IF($O$9=0,"",O17/$O$9))) | R17: =IF(Q17="","",IF($Q$9="","",IF($Q$9=0,"",Q17/$Q$9))) | T17: =IF(S17="","",IF($S$9="","",IF($S$9=0,"",S17/$S$9))) | V17: =IF(U17="","",IF($U$9="","",IF($U$9=0,"",U17/$U$9))) | X17: =IF(W17="","",IF($W$9="","",IF($W$9=0,"",W17/$W$9)))
A18: 8 | B18: 46237 | C18: =$B$5/$B$8 -> 17.241379 | E18: =SUM($C$11:C18) -> 137.93103 | F18: =SUM($D$11:D18) -> 0 | G18: =IF(COUNT($D$11:D18)=0,"",F18/E18) | H18: =IF(G18="","",IF(G18>=0.95,"En meta",IF(G18>=0.8,"Riesgo","Atrasado"))) | J18: =IF(I18="","",IF($I$9="","",IF($I$9=0,"",I18/$I$9))) | L18: =IF(K18="","",IF($K$9="","",IF($K$9=0,"",K18/$K$9))) | N18: =IF(M18="","",IF($M$9="","",IF($M$9=0,"",M18/$M$9))) | P18: =IF(O18="","",IF($O$9="","",IF($O$9=0,"",O18/$O$9))) | R18: =IF(Q18="","",IF($Q$9="","",IF($Q$9=0,"",Q18/$Q$9))) | T18: =IF(S18="","",IF($S$9="","",IF($S$9=0,"",S18/$S$9))) | V18: =IF(U18="","",IF($U$9="","",IF($U$9=0,"",U18/$U$9))) | X18: =IF(W18="","",IF($W$9="","",IF($W$9=0,"",W18/$W$9)))
A19: 9 | B19: 46244 | C19: =$B$5/$B$8 -> 17.241379 | E19: =SUM($C$11:C19) -> 155.17241 | F19: =SUM($D$11:D19) -> 0 | G19: =IF(COUNT($D$11:D19)=0,"",F19/E19) | H19: =IF(G19="","",IF(G19>=0.95,"En meta",IF(G19>=0.8,"Riesgo","Atrasado"))) | J19: =IF(I19="","",IF($I$9="","",IF($I$9=0,"",I19/$I$9))) | L19: =IF(K19="","",IF($K$9="","",IF($K$9=0,"",K19/$K$9))) | N19: =IF(M19="","",IF($M$9="","",IF($M$9=0,"",M19/$M$9))) | P19: =IF(O19="","",IF($O$9="","",IF($O$9=0,"",O19/$O$9))) | R19: =IF(Q19="","",IF($Q$9="","",IF($Q$9=0,"",Q19/$Q$9))) | T19: =IF(S19="","",IF($S$9="","",IF($S$9=0,"",S19/$S$9))) | V19: =IF(U19="","",IF($U$9="","",IF($U$9=0,"",U19/$U$9))) | X19: =IF(W19="","",IF($W$9="","",IF($W$9=0,"",W19/$W$9)))
A20: 10 | B20: 46251 | C20: =$B$5/$B$8 -> 17.241379 | E20: =SUM($C$11:C20) -> 172.41379 | F20: =SUM($D$11:D20) -> 0 | G20: =IF(COUNT($D$11:D20)=0,"",F20/E20) | H20: =IF(G20="","",IF(G20>=0.95,"En meta",IF(G20>=0.8,"Riesgo","Atrasado"))) | J20: =IF(I20="","",IF($I$9="","",IF($I$9=0,"",I20/$I$9))) | L20: =IF(K20="","",IF($K$9="","",IF($K$9=0,"",K20/$K$9))) | N20: =IF(M20="","",IF($M$9="","",IF($M$9=0,"",M20/$M$9))) | P20: =IF(O20="","",IF($O$9="","",IF($O$9=0,"",O20/$O$9))) | R20: =IF(Q20="","",IF($Q$9="","",IF($Q$9=0,"",Q20/$Q$9))) | T20: =IF(S20="","",IF($S$9="","",IF($S$9=0,"",S20/$S$9))) | V20: =IF(U20="","",IF($U$9="","",IF($U$9=0,"",U20/$U$9))) | X20: =IF(W20="","",IF($W$9="","",IF($W$9=0,"",W20/$W$9)))
A21: 11 | B21: 46258 | C21: =$B$5/$B$8 -> 17.241379 | E21: =SUM($C$11:C21) -> 189.65517 | F21: =SUM($D$11:D21) -> 0 | G21: =IF(COUNT($D$11:D21)=0,"",F21/E21) | H21: =IF(G21="","",IF(G21>=0.95,"En meta",IF(G21>=0.8,"Riesgo","Atrasado"))) | J21: =IF(I21="","",IF($I$9="","",IF($I$9=0,"",I21/$I$9))) | L21: =IF(K21="","",IF($K$9="","",IF($K$9=0,"",K21/$K$9))) | N21: =IF(M21="","",IF($M$9="","",IF($M$9=0,"",M21/$M$9))) | P21: =IF(O21="","",IF($O$9="","",IF($O$9=0,"",O21/$O$9))) | R21: =IF(Q21="","",IF($Q$9="","",IF($Q$9=0,"",Q21/$Q$9))) | T21: =IF(S21="","",IF($S$9="","",IF($S$9=0,"",S21/$S$9))) | V21: =IF(U21="","",IF($U$9="","",IF($U$9=0,"",U21/$U$9))) | X21: =IF(W21="","",IF($W$9="","",IF($W$9=0,"",W21/$W$9)))
A22: 12 | B22: 46265 | C22: =$B$5/$B$8 -> 17.241379 | E22: =SUM($C$11:C22) -> 206.89655 | F22: =SUM($D$11:D22) -> 0 | G22: =IF(COUNT($D$11:D22)=0,"",F22/E22) | H22: =IF(G22="","",IF(G22>=0.95,"En meta",IF(G22>=0.8,"Riesgo","Atrasado"))) | J22: =IF(I22="","",IF($I$9="","",IF($I$9=0,"",I22/$I$9))) | L22: =IF(K22="","",IF($K$9="","",IF($K$9=0,"",K22/$K$9))) | N22: =IF(M22="","",IF($M$9="","",IF($M$9=0,"",M22/$M$9))) | P22: =IF(O22="","",IF($O$9="","",IF($O$9=0,"",O22/$O$9))) | R22: =IF(Q22="","",IF($Q$9="","",IF($Q$9=0,"",Q22/$Q$9))) | T22: =IF(S22="","",IF($S$9="","",IF($S$9=0,"",S22/$S$9))) | V22: =IF(U22="","",IF($U$9="","",IF($U$9=0,"",U22/$U$9))) | X22: =IF(W22="","",IF($W$9="","",IF($W$9=0,"",W22/$W$9)))
... A39: 29 | B39: 46384 | C39: =$B$5/$B$8 -> 17.241379 | E39: =SUM($C$11:C39) -> 500 | F39: =SUM($D$11:D39) -> 0 | G39: =IF(COUNT($D$11:D39)=0,"",F39/E39) | H39: =IF(G39="","",IF(G39>=0.95,"En meta",IF(G39>=0.8,"Riesgo","Atrasado"))) | J39: =IF(I39="","",IF($I$9="","",IF($I$9=0,"",I39/$I$9))) | L39: =IF(K39="","",IF($K$9="","",IF($K$9=0,"",K39/$K$9))) | N39: =IF(M39="","",IF($M$9="","",IF($M$9=0,"",M39/$M$9))) | P39: =IF(O39="","",IF($O$9="","",IF($O$9=0,"",O39/$O$9))) | R39: =IF(Q39="","",IF($Q$9="","",IF($Q$9=0,"",Q39/$Q$9))) | T39: =IF(S39="","",IF($S$9="","",IF($S$9=0,"",S39/$S$9))) | V39: =IF(U39="","",IF($U$9="","",IF($U$9=0,"",U39/$U$9))) | X39: =IF(W39="","",IF($W$9="","",IF($W$9=0,"",W39/$W$9)))

Sheet 2. MV Advisory
A1: WIG 2 — Lograr un Monthly Value de $X en advisory en el primer trimestre de 2027
A2: Indicador lag: | B2: MV de horas advisory de ingenieros locales vendidas (USD acumulado). Costo fijo ya cubierto = mayor utilidad.
A3: De X a Y: | B3: De $0 a la meta de MV advisory, antes del 31 de marzo de 2027. (Definir $X en la celda Meta)
A4: Dueño: | B4: Por asignar | D4: Equipo: | E4: Ventas, Customer Success, Pre-Sales, Del - TSS
A5: Meta: | B5: 10000 | D5: Inicio: | E5: 46188 | G5: Fin: | H5: 46475
A6: Leads: | B6: Hasta 8 indicadores predictivos a la derecha. L1–L2 = apuesta principal del equipo; L3–L8 = indicadores de apoyo. Nombre (fila 8) y meta semanal (fila 9) editables en azul.
A8: Periodos: | B8: =COUNT(A11:A52) -> 42 | H8: Lead → | I8: L1. Propuestas de advisory presentadas | K8: L2. Horas advisory cotizadas | M8: L3. Reuniones de venta consultiva con clientes | O8: L4. Assessments / health checks ofrecidos | Q8: L5. % utilización de ingenieros locales en advisory | S8: L6. Opps de advisory activas en pipeline | U8: L7. Contratos advisory firmados en la semana | W8: (Disponible)
A9: Celdas azules = se digitan cada lunes. Celdas negras = fórmulas, no tocar. | H9: Meta → | I9: 3 | K9: 40 | M9: 4 | O9: 2 | Q9: 0.2 | S9: 6 | U9: 1
A10: # | B10: Semana | C10: Meta semana | D10: Real | E10: Meta acum. | F10: Real acum. | G10: % avance | H10: Estado | I10: Real | J10: % | K10: Real | L10: % | M10: Real | N10: % | O10: Real | P10: % | Q10: Real | R10: % | S10: Real | T10: % | U10: Real | V10: % | W10: Real | X10: %
A11: 1 | B11: 46188 | C11: =$B$5/$B$8 -> 238.09524 | E11: =SUM($C$11:C11) -> 238.09524 | F11: =SUM($D$11:D11) -> 0 | G11: =IF(COUNT($D$11:D11)=0,"",F11/E11) | H11: =IF(G11="","",IF(G11>=0.95,"En meta",IF(G11>=0.8,"Riesgo","Atrasado"))) | J11: =IF(I11="","",IF($I$9="","",IF($I$9=0,"",I11/$I$9))) | L11: =IF(K11="","",IF($K$9="","",IF($K$9=0,"",K11/$K$9))) | N11: =IF(M11="","",IF($M$9="","",IF($M$9=0,"",M11/$M$9))) | P11: =IF(O11="","",IF($O$9="","",IF($O$9=0,"",O11/$O$9))) | R11: =IF(Q11="","",IF($Q$9="","",IF($Q$9=0,"",Q11/$Q$9))) | T11: =IF(S11="","",IF($S$9="","",IF($S$9=0,"",S11/$S$9))) | V11: =IF(U11="","",IF($U$9="","",IF($U$9=0,"",U11/$U$9))) | X11: =IF(W11="","",IF($W$9="","",IF($W$9=0,"",W11/$W$9)))
A12: 2 | B12: 46195 | C12: =$B$5/$B$8 -> 238.09524 | E12: =SUM($C$11:C12) -> 476.19048 | F12: =SUM($D$11:D12) -> 0 | G12: =IF(COUNT($D$11:D12)=0,"",F12/E12) | H12: =IF(G12="","",IF(G12>=0.95,"En meta",IF(G12>=0.8,"Riesgo","Atrasado"))) | J12: =IF(I12="","",IF($I$9="","",IF($I$9=0,"",I12/$I$9))) | L12: =IF(K12="","",IF($K$9="","",IF($K$9=0,"",K12/$K$9))) | N12: =IF(M12="","",IF($M$9="","",IF($M$9=0,"",M12/$M$9))) | P12: =IF(O12="","",IF($O$9="","",IF($O$9=0,"",O12/$O$9))) | R12: =IF(Q12="","",IF($Q$9="","",IF($Q$9=0,"",Q12/$Q$9))) | T12: =IF(S12="","",IF($S$9="","",IF($S$9=0,"",S12/$S$9))) | V12: =IF(U12="","",IF($U$9="","",IF($U$9=0,"",U12/$U$9))) | X12: =IF(W12="","",IF($W$9="","",IF($W$9=0,"",W12/$W$9)))
A13: 3 | B13: 46202 | C13: =$B$5/$B$8 -> 238.09524 | E13: =SUM($C$11:C13) -> 714.28571 | F13: =SUM($D$11:D13) -> 0 | G13: =IF(COUNT($D$11:D13)=0,"",F13/E13) | H13: =IF(G13="","",IF(G13>=0.95,"En meta",IF(G13>=0.8,"Riesgo","Atrasado"))) | J13: =IF(I13="","",IF($I$9="","",IF($I$9=0,"",I13/$I$9))) | L13: =IF(K13="","",IF($K$9="","",IF($K$9=0,"",K13/$K$9))) | N13: =IF(M13="","",IF($M$9="","",IF($M$9=0,"",M13/$M$9))) | P13: =IF(O13="","",IF($O$9="","",IF($O$9=0,"",O13/$O$9))) | R13: =IF(Q13="","",IF($Q$9="","",IF($Q$9=0,"",Q13/$Q$9))) | T13: =IF(S13="","",IF($S$9="","",IF($S$9=0,"",S13/$S$9))) | V13: =IF(U13="","",IF($U$9="","",IF($U$9=0,"",U13/$U$9))) | X13: =IF(W13="","",IF($W$9="","",IF($W$9=0,"",W13/$W$9)))
A14: 4 | B14: 46209 | C14: =$B$5/$B$8 -> 238.09524 | E14: =SUM($C$11:C14) -> 952.38095 | F14: =SUM($D$11:D14) -> 0 | G14: =IF(COUNT($D$11:D14)=0,"",F14/E14) | H14: =IF(G14="","",IF(G14>=0.95,"En meta",IF(G14>=0.8,"Riesgo","Atrasado"))) | J14: =IF(I14="","",IF($I$9="","",IF($I$9=0,"",I14/$I$9))) | L14: =IF(K14="","",IF($K$9="","",IF($K$9=0,"",K14/$K$9))) | N14: =IF(M14="","",IF($M$9="","",IF($M$9=0,"",M14/$M$9))) | P14: =IF(O14="","",IF($O$9="","",IF($O$9=0,"",O14/$O$9))) | R14: =IF(Q14="","",IF($Q$9="","",IF($Q$9=0,"",Q14/$Q$9))) | T14: =IF(S14="","",IF($S$9="","",IF($S$9=0,"",S14/$S$9))) | V14: =IF(U14="","",IF($U$9="","",IF($U$9=0,"",U14/$U$9))) | X14: =IF(W14="","",IF($W$9="","",IF($W$9=0,"",W14/$W$9)))
A15: 5 | B15: 46216 | C15: =$B$5/$B$8 -> 238.09524 | E15: =SUM($C$11:C15) -> 1190.4762 | F15: =SUM($D$11:D15) -> 0 | G15: =IF(COUNT($D$11:D15)=0,"",F15/E15) | H15: =IF(G15="","",IF(G15>=0.95,"En meta",IF(G15>=0.8,"Riesgo","Atrasado"))) | J15: =IF(I15="","",IF($I$9="","",IF($I$9=0,"",I15/$I$9))) | L15: =IF(K15="","",IF($K$9="","",IF($K$9=0,"",K15/$K$9))) | N15: =IF(M15="","",IF($M$9="","",IF($M$9=0,"",M15/$M$9))) | P15: =IF(O15="","",IF($O$9="","",IF($O$9=0,"",O15/$O$9))) | R15: =IF(Q15="","",IF($Q$9="","",IF($Q$9=0,"",Q15/$Q$9))) | T15: =IF(S15="","",IF($S$9="","",IF($S$9=0,"",S15/$S$9))) | V15: =IF(U15="","",IF($U$9="","",IF($U$9=0,"",U15/$U$9))) | X15: =IF(W15="","",IF($W$9="","",IF($W$9=0,"",W15/$W$9)))
A16: 6 | B16: 46223 | C16: =$B$5/$B$8 -> 238.09524 | E16: =SUM($C$11:C16) -> 1428.5714 | F16: =SUM($D$11:D16) -> 0 | G16: =IF(COUNT($D$11:D16)=0,"",F16/E16) | H16: =IF(G16="","",IF(G16>=0.95,"En meta",IF(G16>=0.8,"Riesgo","Atrasado"))) | J16: =IF(I16="","",IF($I$9="","",IF($I$9=0,"",I16/$I$9))) | L16: =IF(K16="","",IF($K$9="","",IF($K$9=0,"",K16/$K$9))) | N16: =IF(M16="","",IF($M$9="","",IF($M$9=0,"",M16/$M$9))) | P16: =IF(O16="","",IF($O$9="","",IF($O$9=0,"",O16/$O$9))) | R16: =IF(Q16="","",IF($Q$9="","",IF($Q$9=0,"",Q16/$Q$9))) | T16: =IF(S16="","",IF($S$9="","",IF($S$9=0,"",S16/$S$9))) | V16: =IF(U16="","",IF($U$9="","",IF($U$9=0,"",U16/$U$9))) | X16: =IF(W16="","",IF($W$9="","",IF($W$9=0,"",W16/$W$9)))
A17: 7 | B17: 46230 | C17: =$B$5/$B$8 -> 238.09524 | E17: =SUM($C$11:C17) -> 1666.6667 | F17: =SUM($D$11:D17) -> 0 | G17: =IF(COUNT($D$11:D17)=0,"",F17/E17) | H17: =IF(G17="","",IF(G17>=0.95,"En meta",IF(G17>=0.8,"Riesgo","Atrasado"))) | J17: =IF(I17="","",IF($I$9="","",IF($I$9=0,"",I17/$I$9))) | L17: =IF(K17="","",IF($K$9="","",IF($K$9=0,"",K17/$K$9))) | N17: =IF(M17="","",IF($M$9="","",IF($M$9=0,"",M17/$M$9))) | P17: =IF(O17="","",IF($O$9="","",IF($O$9=0,"",O17/$O$9))) | R17: =IF(Q17="","",IF($Q$9="","",IF($Q$9=0,"",Q17/$Q$9))) | T17: =IF(S17="","",IF($S$9="","",IF($S$9=0,"",S17/$S$9))) | V17: =IF(U17="","",IF($U$9="","",IF($U$9=0,"",U17/$U$9))) | X17: =IF(W17="","",IF($W$9="","",IF($W$9=0,"",W17/$W$9)))
A18: 8 | B18: 46237 | C18: =$B$5/$B$8 -> 238.09524 | E18: =SUM($C$11:C18) -> 1904.7619 | F18: =SUM($D$11:D18) -> 0 | G18: =IF(COUNT($D$11:D18)=0,"",F18/E18) | H18: =IF(G18="","",IF(G18>=0.95,"En meta",IF(G18>=0.8,"Riesgo","Atrasado"))) | J18: =IF(I18="","",IF($I$9="","",IF($I$9=0,"",I18/$I$9))) | L18: =IF(K18="","",IF($K$9="","",IF($K$9=0,"",K18/$K$9))) | N18: =IF(M18="","",IF($M$9="","",IF($M$9=0,"",M18/$M$9))) | P18: =IF(O18="","",IF($O$9="","",IF($O$9=0,"",O18/$O$9))) | R18: =IF(Q18="","",IF($Q$9="","",IF($Q$9=0,"",Q18/$Q$9))) | T18: =IF(S18="","",IF($S$9="","",IF($S$9=0,"",S18/$S$9))) | V18: =IF(U18="","",IF($U$9="","",IF($U$9=0,"",U18/$U$9))) | X18: =IF(W18="","",IF($W$9="","",IF($W$9=0,"",W18/$W$9)))
A19: 9 | B19: 46244 | C19: =$B$5/$B$8 -> 238.09524 | E19: =SUM($C$11:C19) -> 2142.8571 | F19: =SUM($D$11:D19) -> 0 | G19: =IF(COUNT($D$11:D19)=0,"",F19/E19) | H19: =IF(G19="","",IF(G19>=0.95,"En meta",IF(G19>=0.8,"Riesgo","Atrasado"))) | J19: =IF(I19="","",IF($I$9="","",IF($I$9=0,"",I19/$I$9))) | L19: =IF(K19="","",IF($K$9="","",IF($K$9=0,"",K19/$K$9))) | N19: =IF(M19="","",IF($M$9="","",IF($M$9=0,"",M19/$M$9))) | P19: =IF(O19="","",IF($O$9="","",IF($O$9=0,"",O19/$O$9))) | R19: =IF(Q19="","",IF($Q$9="","",IF($Q$9=0,"",Q19/$Q$9))) | T19: =IF(S19="","",IF($S$9="","",IF($S$9=0,"",S19/$S$9))) | V19: =IF(U19="","",IF($U$9="","",IF($U$9=0,"",U19/$U$9))) | X19: =IF(W19="","",IF($W$9="","",IF($W$9=0,"",W19/$W$9)))
A20: 10 | B20: 46251 | C20: =$B$5/$B$8 -> 238.09524 | E20: =SUM($C$11:C20) -> 2380.9524 | F20: =SUM($D$11:D20) -> 0 | G20: =IF(COUNT($D$11:D20)=0,"",F20/E20) | H20: =IF(G20="","",IF(G20>=0.95,"En meta",IF(G20>=0.8,"Riesgo","Atrasado"))) | J20: =IF(I20="","",IF($I$9="","",IF($I$9=0,"",I20/$I$9))) | L20: =IF(K20="","",IF($K$9="","",IF($K$9=0,"",K20/$K$9))) | N20: =IF(M20="","",IF($M$9="","",IF($M$9=0,"",M20/$M$9))) | P20: =IF(O20="","",IF($O$9="","",IF($O$9=0,"",O20/$O$9))) | R20: =IF(Q20="","",IF($Q$9="","",IF($Q$9=0,"",Q20/$Q$9))) | T20: =IF(S20="","",IF($S$9="","",IF($S$9=0,"",S20/$S$9))) | V20: =IF(U20="","",IF($U$9="","",IF($U$9=0,"",U20/$U$9))) | X20: =IF(W20="","",IF($W$9="","",IF($W$9=0,"",W20/$W$9)))
A21: 11 | B21: 46258 | C21: =$B$5/$B$8 -> 238.09524 | E21: =SUM($C$11:C21) -> 2619.0476 | F21: =SUM($D$11:D21) -> 0 | G21: =IF(COUNT($D$11:D21)=0,"",F21/E21) | H21: =IF(G21="","",IF(G21>=0.95,"En meta",IF(G21>=0.8,"Riesgo","Atrasado"))) | J21: =IF(I21="","",IF($I$9="","",IF($I$9=0,"",I21/$I$9))) | L21: =IF(K21="","",IF($K$9="","",IF($K$9=0,"",K21/$K$9))) | N21: =IF(M21="","",IF($M$9="","",IF($M$9=0,"",M21/$M$9))) | P21: =IF(O21="","",IF($O$9="","",IF($O$9=0,"",O21/$O$9))) | R21: =IF(Q21="","",IF($Q$9="","",IF($Q$9=0,"",Q21/$Q$9))) | T21: =IF(S21="","",IF($S$9="","",IF($S$9=0,"",S21/$S$9))) | V21: =IF(U21="","",IF($U$9="","",IF($U$9=0,"",U21/$U$9))) | X21: =IF(W21="","",IF($W$9="","",IF($W$9=0,"",W21/$W$9)))
A22: 12 | B22: 46265 | C22: =$B$5/$B$8 -> 238.09524 | E22: =SUM($C$11:C22) -> 2857.1429 | F22: =SUM($D$11:D22) -> 0 | G22: =IF(COUNT($D$11:D22)=0,"",F22/E22) | H22: =IF(G22="","",IF(G22>=0.95,"En meta",IF(G22>=0.8,"Riesgo","Atrasado"))) | J22: =IF(I22="","",IF($I$9="","",IF($I$9=0,"",I22/$I$9))) | L22: =IF(K22="","",IF($K$9="","",IF($K$9=0,"",K22/$K$9))) | N22: =IF(M22="","",IF($M$9="","",IF($M$9=0,"",M22/$M$9))) | P22: =IF(O22="","",IF($O$9="","",IF($O$9=0,"",O22/$O$9))) | R22: =IF(Q22="","",IF($Q$9="","",IF($Q$9=0,"",Q22/$Q$9))) | T22: =IF(S22="","",IF($S$9="","",IF($S$9=0,"",S22/$S$9))) | V22: =IF(U22="","",IF($U$9="","",IF($U$9=0,"",U22/$U$9))) | X22: =IF(W22="","",IF($W$9="","",IF($W$9=0,"",W22/$W$9)))
... A52: 42 | B52: 46475 | C52: =$B$5/$B$8 -> 238.09524 | E52: =SUM($C$11:C52) -> 10000 | F52: =SUM($D$11:D52) -> 0 | G52: =IF(COUNT($D$11:D52)=0,"",F52/E52) | H52: =IF(G52="","",IF(G52>=0.95,"En meta",IF(G52>=0.8,"Riesgo","Atrasado"))) | J52: =IF(I52="","",IF($I$9="","",IF($I$9=0,"",I52/$I$9))) | L52: =IF(K52="","",IF($K$9="","",IF($K$9=0,"",K52/$K$9))) | N52: =IF(M52="","",IF($M$9="","",IF($M$9=0,"",M52/$M$9))) | P52: =IF(O52="","",IF($O$9="","",IF($O$9=0,"",O52/$O$9))) | R52: =IF(Q52="","",IF($Q$9="","",IF($Q$9=0,"",Q52/$Q$9))) | T52: =IF(S52="","",IF($S$9="","",IF($S$9=0,"",S52/$S$9))) | V52: =IF(U52="","",IF($U$9="","",IF($U$9=0,"",U52/$U$9))) | X52: =IF(W52="","",IF($W$9="","",IF($W$9=0,"",W52/$W$9)))

Sheet 3. Negocios +30K GP
A1: WIG 3 — Reconocer 10 negocios mayores a $30K de GP en el 2027
A2: Indicador lag: | B2: Negocios con GP > $30K reconocidos (acumulado). Negocios grandes que mueven el NAT.
A3: De X a Y: | B3: De 0 a 10 negocios > $30K GP reconocidos, antes del 31 de diciembre de 2027.
A4: Dueño: | B4: Por asignar | D4: Equipo: | E4: Ventas, Pre-Sales
A5: Meta: | B5: 10 | D5: Inicio: | E5: 46188 | G5: Fin: | H5: 46748
A6: Leads: | B6: Hasta 8 indicadores predictivos a la derecha. L1–L2 = apuesta principal del equipo; L3–L8 = indicadores de apoyo. Nombre (fila 8) y meta semanal (fila 9) editables en azul.
A8: Periodos: | B8: =COUNT(A11:A91) -> 81 | H8: Lead → | I8: L1. Opps > $30K GP activas en pipeline | K8: L2. Opps nuevas ingresadas en la semana | M8: L3. Propuestas > $30K presentadas | O8: L4. Reuniones C-level realizadas | Q8: L5. Leads activas al cierre de la semana | S8: L6. Opps > $30K avanzadas de etapa | U8: L7. Win rate de opps > $30K (acumulado) | W8: (Disponible)
A9: Celdas azules = se digitan cada lunes. Celdas negras = fórmulas, no tocar. | H9: Meta → | I9: 5 | K9: 4 | M9: 1 | O9: 2 | Q9: 10 | S9: 2 | U9: 0.3
A10: # | B10: Semana | C10: Meta semana | D10: Real | E10: Meta acum. | F10: Real acum. | G10: % avance | H10: Estado | I10: Real | J10: % | K10: Real | L10: % | M10: Real | N10: % | O10: Real | P10: % | Q10: Real | R10: % | S10: Real | T10: % | U10: Real | V10: % | W10: Real | X10: %
A11: 1 | B11: 46188 | C11: =$B$5/$B$8 -> 0.12345679 | E11: =SUM($C$11:C11) -> 0.12345679 | F11: =SUM($D$11:D11) -> 0 | G11: =IF(COUNT($D$11:D11)=0,"",F11/E11) | H11: =IF(G11="","",IF(G11>=0.95,"En meta",IF(G11>=0.8,"Riesgo","Atrasado"))) | J11: =IF(I11="","",IF($I$9="","",IF($I$9=0,"",I11/$I$9))) | L11: =IF(K11="","",IF($K$9="","",IF($K$9=0,"",K11/$K$9))) | N11: =IF(M11="","",IF($M$9="","",IF($M$9=0,"",M11/$M$9))) | P11: =IF(O11="","",IF($O$9="","",IF($O$9=0,"",O11/$O$9))) | R11: =IF(Q11="","",IF($Q$9="","",IF($Q$9=0,"",Q11/$Q$9))) | T11: =IF(S11="","",IF($S$9="","",IF($S$9=0,"",S11/$S$9))) | V11: =IF(U11="","",IF($U$9="","",IF($U$9=0,"",U11/$U$9))) | X11: =IF(W11="","",IF($W$9="","",IF($W$9=0,"",W11/$W$9)))
A12: 2 | B12: 46195 | C12: =$B$5/$B$8 -> 0.12345679 | E12: =SUM($C$11:C12) -> 0.24691358 | F12: =SUM($D$11:D12) -> 0 | G12: =IF(COUNT($D$11:D12)=0,"",F12/E12) | H12: =IF(G12="","",IF(G12>=0.95,"En meta",IF(G12>=0.8,"Riesgo","Atrasado"))) | J12: =IF(I12="","",IF($I$9="","",IF($I$9=0,"",I12/$I$9))) | L12: =IF(K12="","",IF($K$9="","",IF($K$9=0,"",K12/$K$9))) | N12: =IF(M12="","",IF($M$9="","",IF($M$9=0,"",M12/$M$9))) | P12: =IF(O12="","",IF($O$9="","",IF($O$9=0,"",O12/$O$9))) | R12: =IF(Q12="","",IF($Q$9="","",IF($Q$9=0,"",Q12/$Q$9))) | T12: =IF(S12="","",IF($S$9="","",IF($S$9=0,"",S12/$S$9))) | V12: =IF(U12="","",IF($U$9="","",IF($U$9=0,"",U12/$U$9))) | X12: =IF(W12="","",IF($W$9="","",IF($W$9=0,"",W12/$W$9)))
A13: 3 | B13: 46202 | C13: =$B$5/$B$8 -> 0.12345679 | E13: =SUM($C$11:C13) -> 0.37037037 | F13: =SUM($D$11:D13) -> 0 | G13: =IF(COUNT($D$11:D13)=0,"",F13/E13) | H13: =IF(G13="","",IF(G13>=0.95,"En meta",IF(G13>=0.8,"Riesgo","Atrasado"))) | J13: =IF(I13="","",IF($I$9="","",IF($I$9=0,"",I13/$I$9))) | L13: =IF(K13="","",IF($K$9="","",IF($K$9=0,"",K13/$K$9))) | N13: =IF(M13="","",IF($M$9="","",IF($M$9=0,"",M13/$M$9))) | P13: =IF(O13="","",IF($O$9="","",IF($O$9=0,"",O13/$O$9))) | R13: =IF(Q13="","",IF($Q$9="","",IF($Q$9=0,"",Q13/$Q$9))) | T13: =IF(S13="","",IF($S$9="","",IF($S$9=0,"",S13/$S$9))) | V13: =IF(U13="","",IF($U$9="","",IF($U$9=0,"",U13/$U$9))) | X13: =IF(W13="","",IF($W$9="","",IF($W$9=0,"",W13/$W$9)))
A14: 4 | B14: 46209 | C14: =$B$5/$B$8 -> 0.12345679 | E14: =SUM($C$11:C14) -> 0.49382716 | F14: =SUM($D$11:D14) -> 0 | G14: =IF(COUNT($D$11:D14)=0,"",F14/E14) | H14: =IF(G14="","",IF(G14>=0.95,"En meta",IF(G14>=0.8,"Riesgo","Atrasado"))) | J14: =IF(I14="","",IF($I$9="","",IF($I$9=0,"",I14/$I$9))) | L14: =IF(K14="","",IF($K$9="","",IF($K$9=0,"",K14/$K$9))) | N14: =IF(M14="","",IF($M$9="","",IF($M$9=0,"",M14/$M$9))) | P14: =IF(O14="","",IF($O$9="","",IF($O$9=0,"",O14/$O$9))) | R14: =IF(Q14="","",IF($Q$9="","",IF($Q$9=0,"",Q14/$Q$9))) | T14: =IF(S14="","",IF($S$9="","",IF($S$9=0,"",S14/$S$9))) | V14: =IF(U14="","",IF($U$9="","",IF($U$9=0,"",U14/$U$9))) | X14: =IF(W14="","",IF($W$9="","",IF($W$9=0,"",W14/$W$9)))
A15: 5 | B15: 46216 | C15: =$B$5/$B$8 -> 0.12345679 | E15: =SUM($C$11:C15) -> 0.61728395 | F15: =SUM($D$11:D15) -> 0 | G15: =IF(COUNT($D$11:D15)=0,"",F15/E15) | H15: =IF(G15="","",IF(G15>=0.95,"En meta",IF(G15>=0.8,"Riesgo","Atrasado"))) | J15: =IF(I15="","",IF($I$9="","",IF($I$9=0,"",I15/$I$9))) | L15: =IF(K15="","",IF($K$9="","",IF($K$9=0,"",K15/$K$9))) | N15: =IF(M15="","",IF($M$9="","",IF($M$9=0,"",M15/$M$9))) | P15: =IF(O15="","",IF($O$9="","",IF($O$9=0,"",O15/$O$9))) | R15: =IF(Q15="","",IF($Q$9="","",IF($Q$9=0,"",Q15/$Q$9))) | T15: =IF(S15="","",IF($S$9="","",IF($S$9=0,"",S15/$S$9))) | V15: =IF(U15="","",IF($U$9="","",IF($U$9=0,"",U15/$U$9))) | X15: =IF(W15="","",IF($W$9="","",IF($W$9=0,"",W15/$W$9)))
A16: 6 | B16: 46223 | C16: =$B$5/$B$8 -> 0.12345679 | E16: =SUM($C$11:C16) -> 0.74074074 | F16: =SUM($D$11:D16) -> 0 | G16: =IF(COUNT($D$11:D16)=0,"",F16/E16) | H16: =IF(G16="","",IF(G16>=0.95,"En meta",IF(G16>=0.8,"Riesgo","Atrasado"))) | J16: =IF(I16="","",IF($I$9="","",IF($I$9=0,"",I16/$I$9))) | L16: =IF(K16="","",IF($K$9="","",IF($K$9=0,"",K16/$K$9))) | N16: =IF(M16="","",IF($M$9="","",IF($M$9=0,"",M16/$M$9))) | P16: =IF(O16="","",IF($O$9="","",IF($O$9=0,"",O16/$O$9))) | R16: =IF(Q16="","",IF($Q$9="","",IF($Q$9=0,"",Q16/$Q$9))) | T16: =IF(S16="","",IF($S$9="","",IF($S$9=0,"",S16/$S$9))) | V16: =IF(U16="","",IF($U$9="","",IF($U$9=0,"",U16/$U$9))) | X16: =IF(W16="","",IF($W$9="","",IF($W$9=0,"",W16/$W$9)))
A17: 7 | B17: 46230 | C17: =$B$5/$B$8 -> 0.12345679 | E17: =SUM($C$11:C17) -> 0.86419753 | F17: =SUM($D$11:D17) -> 0 | G17: =IF(COUNT($D$11:D17)=0,"",F17/E17) | H17: =IF(G17="","",IF(G17>=0.95,"En meta",IF(G17>=0.8,"Riesgo","Atrasado"))) | J17: =IF(I17="","",IF($I$9="","",IF($I$9=0,"",I17/$I$9))) | L17: =IF(K17="","",IF($K$9="","",IF($K$9=0,"",K17/$K$9))) | N17: =IF(M17="","",IF($M$9="","",IF($M$9=0,"",M17/$M$9))) | P17: =IF(O17="","",IF($O$9="","",IF($O$9=0,"",O17/$O$9))) | R17: =IF(Q17="","",IF($Q$9="","",IF($Q$9=0,"",Q17/$Q$9))) | T17: =IF(S17="","",IF($S$9="","",IF($S$9=0,"",S17/$S$9))) | V17: =IF(U17="","",IF($U$9="","",IF($U$9=0,"",U17/$U$9))) | X17: =IF(W17="","",IF($W$9="","",IF($W$9=0,"",W17/$W$9)))
A18: 8 | B18: 46237 | C18: =$B$5/$B$8 -> 0.12345679 | E18: =SUM($C$11:C18) -> 0.98765432 | F18: =SUM($D$11:D18) -> 0 | G18: =IF(COUNT($D$11:D18)=0,"",F18/E18) | H18: =IF(G18="","",IF(G18>=0.95,"En meta",IF(G18>=0.8,"Riesgo","Atrasado"))) | J18: =IF(I18="","",IF($I$9="","",IF($I$9=0,"",I18/$I$9))) | L18: =IF(K18="","",IF($K$9="","",IF($K$9=0,"",K18/$K$9))) | N18: =IF(M18="","",IF($M$9="","",IF($M$9=0,"",M18/$M$9))) | P18: =IF(O18="","",IF($O$9="","",IF($O$9=0,"",O18/$O$9))) | R18: =IF(Q18="","",IF($Q$9="","",IF($Q$9=0,"",Q18/$Q$9))) | T18: =IF(S18="","",IF($S$9="","",IF($S$9=0,"",S18/$S$9))) | V18: =IF(U18="","",IF($U$9="","",IF($U$9=0,"",U18/$U$9))) | X18: =IF(W18="","",IF($W$9="","",IF($W$9=0,"",W18/$W$9)))
A19: 9 | B19: 46244 | C19: =$B$5/$B$8 -> 0.12345679 | E19: =SUM($C$11:C19) -> 1.1111111 | F19: =SUM($D$11:D19) -> 0 | G19: =IF(COUNT($D$11:D19)=0,"",F19/E19) | H19: =IF(G19="","",IF(G19>=0.95,"En meta",IF(G19>=0.8,"Riesgo","Atrasado"))) | J19: =IF(I19="","",IF($I$9="","",IF($I$9=0,"",I19/$I$9))) | L19: =IF(K19="","",IF($K$9="","",IF($K$9=0,"",K19/$K$9))) | N19: =IF(M19="","",IF($M$9="","",IF($M$9=0,"",M19/$M$9))) | P19: =IF(O19="","",IF($O$9="","",IF($O$9=0,"",O19/$O$9))) | R19: =IF(Q19="","",IF($Q$9="","",IF($Q$9=0,"",Q19/$Q$9))) | T19: =IF(S19="","",IF($S$9="","",IF($S$9=0,"",S19/$S$9))) | V19: =IF(U19="","",IF($U$9="","",IF($U$9=0,"",U19/$U$9))) | X19: =IF(W19="","",IF($W$9="","",IF($W$9=0,"",W19/$W$9)))
A20: 10 | B20: 46251 | C20: =$B$5/$B$8 -> 0.12345679 | E20: =SUM($C$11:C20) -> 1.2345679 | F20: =SUM($D$11:D20) -> 0 | G20: =IF(COUNT($D$11:D20)=0,"",F20/E20) | H20: =IF(G20="","",IF(G20>=0.95,"En meta",IF(G20>=0.8,"Riesgo","Atrasado"))) | J20: =IF(I20="","",IF($I$9="","",IF($I$9=0,"",I20/$I$9))) | L20: =IF(K20="","",IF($K$9="","",IF($K$9=0,"",K20/$K$9))) | N20: =IF(M20="","",IF($M$9="","",IF($M$9=0,"",M20/$M$9))) | P20: =IF(O20="","",IF($O$9="","",IF($O$9=0,"",O20/$O$9))) | R20: =IF(Q20="","",IF($Q$9="","",IF($Q$9=0,"",Q20/$Q$9))) | T20: =IF(S20="","",IF($S$9="","",IF($S$9=0,"",S20/$S$9))) | V20: =IF(U20="","",IF($U$9="","",IF($U$9=0,"",U20/$U$9))) | X20: =IF(W20="","",IF($W$9="","",IF($W$9=0,"",W20/$W$9)))
A21: 11 | B21: 46258 | C21: =$B$5/$B$8 -> 0.12345679 | E21: =SUM($C$11:C21) -> 1.3580247 | F21: =SUM($D$11:D21) -> 0 | G21: =IF(COUNT($D$11:D21)=0,"",F21/E21) | H21: =IF(G21="","",IF(G21>=0.95,"En meta",IF(G21>=0.8,"Riesgo","Atrasado"))) | J21: =IF(I21="","",IF($I$9="","",IF($I$9=0,"",I21/$I$9))) | L21: =IF(K21="","",IF($K$9="","",IF($K$9=0,"",K21/$K$9))) | N21: =IF(M21="","",IF($M$9="","",IF($M$9=0,"",M21/$M$9))) | P21: =IF(O21="","",IF($O$9="","",IF($O$9=0,"",O21/$O$9))) | R21: =IF(Q21="","",IF($Q$9="","",IF($Q$9=0,"",Q21/$Q$9))) | T21: =IF(S21="","",IF($S$9="","",IF($S$9=0,"",S21/$S$9))) | V21: =IF(U21="","",IF($U$9="","",IF($U$9=0,"",U21/$U$9))) | X21: =IF(W21="","",IF($W$9="","",IF($W$9=0,"",W21/$W$9)))
A22: 12 | B22: 46265 | C22: =$B$5/$B$8 -> 0.12345679 | E22: =SUM($C$11:C22) -> 1.4814815 | F22: =SUM($D$11:D22) -> 0 | G22: =IF(COUNT($D$11:D22)=0,"",F22/E22) | H22: =IF(G22="","",IF(G22>=0.95,"En meta",IF(G22>=0.8,"Riesgo","Atrasado"))) | J22: =IF(I22="","",IF($I$9="","",IF($I$9=0,"",I22/$I$9))) | L22: =IF(K22="","",IF($K$9="","",IF($K$9=0,"",K22/$K$9))) | N22: =IF(M22="","",IF($M$9="","",IF($M$9=0,"",M22/$M$9))) | P22: =IF(O22="","",IF($O$9="","",IF($O$9=0,"",O22/$O$9))) | R22: =IF(Q22="","",IF($Q$9="","",IF($Q$9=0,"",Q22/$Q$9))) | T22: =IF(S22="","",IF($S$9="","",IF($S$9=0,"",S22/$S$9))) | V22: =IF(U22="","",IF($U$9="","",IF($U$9=0,"",U22/$U$9))) | X22: =IF(W22="","",IF($W$9="","",IF($W$9=0,"",W22/$W$9)))
... A91: 81 | B91: 46748 | C91: =$B$5/$B$8 -> 0.12345679 | E91: =SUM($C$11:C91) -> 10 | F91: =SUM($D$11:D91) -> 0 | G91: =IF(COUNT($D$11:D91)=0,"",F91/E91) | H91: =IF(G91="","",IF(G91>=0.95,"En meta",IF(G91>=0.8,"Riesgo","Atrasado"))) | J91: =IF(I91="","",IF($I$9="","",IF($I$9=0,"",I91/$I$9))) | L91: =IF(K91="","",IF($K$9="","",IF($K$9=0,"",K91/$K$9))) | N91: =IF(M91="","",IF($M$9="","",IF($M$9=0,"",M91/$M$9))) | P91: =IF(O91="","",IF($O$9="","",IF($O$9=0,"",O91/$O$9))) | R91: =IF(Q91="","",IF($Q$9="","",IF($Q$9=0,"",Q91/$Q$9))) | T91: =IF(S91="","",IF($S$9="","",IF($S$9=0,"",S91/$S$9))) | V91: =IF(U91="","",IF($U$9="","",IF($U$9=0,"",U91/$U$9))) | X91: =IF(W91="","",IF($W$9="","",IF($W$9=0,"",W91/$W$9)))

Sheet 4. Entregas 100%
A1: WIG 4 — Cumplir el 100% de entregas y colocaciones en tiempo y forma
A2: Indicador lag: | B2: % de colocaciones y entregas de la semana realizadas en tiempo y forma.
A3: De X a Y: | B3: Sostener 100% de cumplimiento semanal durante todo el periodo.
A4: Dueño: | B4: Por asignar | D4: Equipo: | E4: Finanzas
A5: Meta: | B5: 1 | D5: Inicio: | E5: 46188 | G5: Fin: | H5: 46748
A6: Leads: | B6: Hasta 8 indicadores predictivos a la derecha. L1–L2 = apuesta principal del equipo; L3–L8 = indicadores de apoyo. Nombre (fila 8) y meta semanal (fila 9) editables en azul.
A8: Periodos: | B8: =COUNT(A11:A91) -> 81 | H8: Lead → | I8: L1. % entregas programadas con checklist completo | K8: L2. Riesgos de entrega escalados ≥1 semana antes | M8: L3. % órdenes de compra liberadas a tiempo | O8: L4. % inventario confirmado ≥5 días antes | Q8: L5. Coordinaciones logísticas confirmadas | S8: L6. % facturas emitidas ≤48h tras la entrega | U8: (Disponible) | W8: (Disponible)
A9: Celdas azules = se digitan cada lunes. Celdas negras = fórmulas, no tocar. | H9: Meta → | I9: 1 | K9: 1 | M9: 1 | O9: 1 | Q9: 5 | S9: 1
A10: # | B10: Semana | C10: Meta | D10: Real | G10: Brecha vs meta | H10: Estado | I10: Real | J10: % | K10: Real | L10: % | M10: Real | N10: % | O10: Real | P10: % | Q10: Real | R10: % | S10: Real | T10: % | U10: Real | V10: % | W10: Real | X10: %
A11: 1 | B11: 46188 | C11: =$B$5 -> 1 | G11: =IF(D11="","",D11-C11) | H11: =IF(D11="","",IF(D11>=C11,"En meta",IF(D11>=C11-0.05,"Riesgo","Atrasado"))) | J11: =IF(I11="","",IF($I$9="","",IF($I$9=0,"",I11/$I$9))) | L11: =IF(K11="","",IF($K$9="","",IF($K$9=0,"",K11/$K$9))) | N11: =IF(M11="","",IF($M$9="","",IF($M$9=0,"",M11/$M$9))) | P11: =IF(O11="","",IF($O$9="","",IF($O$9=0,"",O11/$O$9))) | R11: =IF(Q11="","",IF($Q$9="","",IF($Q$9=0,"",Q11/$Q$9))) | T11: =IF(S11="","",IF($S$9="","",IF($S$9=0,"",S11/$S$9))) | V11: =IF(U11="","",IF($U$9="","",IF($U$9=0,"",U11/$U$9))) | X11: =IF(W11="","",IF($W$9="","",IF($W$9=0,"",W11/$W$9)))
A12: 2 | B12: 46195 | C12: =$B$5 -> 1 | G12: =IF(D12="","",D12-C12) | H12: =IF(D12="","",IF(D12>=C12,"En meta",IF(D12>=C12-0.05,"Riesgo","Atrasado"))) | J12: =IF(I12="","",IF($I$9="","",IF($I$9=0,"",I12/$I$9))) | L12: =IF(K12="","",IF($K$9="","",IF($K$9=0,"",K12/$K$9))) | N12: =IF(M12="","",IF($M$9="","",IF($M$9=0,"",M12/$M$9))) | P12: =IF(O12="","",IF($O$9="","",IF($O$9=0,"",O12/$O$9))) | R12: =IF(Q12="","",IF($Q$9="","",IF($Q$9=0,"",Q12/$Q$9))) | T12: =IF(S12="","",IF($S$9="","",IF($S$9=0,"",S12/$S$9))) | V12: =IF(U12="","",IF($U$9="","",IF($U$9=0,"",U12/$U$9))) | X12: =IF(W12="","",IF($W$9="","",IF($W$9=0,"",W12/$W$9)))
A13: 3 | B13: 46202 | C13: =$B$5 -> 1 | G13: =IF(D13="","",D13-C13) | H13: =IF(D13="","",IF(D13>=C13,"En meta",IF(D13>=C13-0.05,"Riesgo","Atrasado"))) | J13: =IF(I13="","",IF($I$9="","",IF($I$9=0,"",I13/$I$9))) | L13: =IF(K13="","",IF($K$9="","",IF($K$9=0,"",K13/$K$9))) | N13: =IF(M13="","",IF($M$9="","",IF($M$9=0,"",M13/$M$9))) | P13: =IF(O13="","",IF($O$9="","",IF($O$9=0,"",O13/$O$9))) | R13: =IF(Q13="","",IF($Q$9="","",IF($Q$9=0,"",Q13/$Q$9))) | T13: =IF(S13="","",IF($S$9="","",IF($S$9=0,"",S13/$S$9))) | V13: =IF(U13="","",IF($U$9="","",IF($U$9=0,"",U13/$U$9))) | X13: =IF(W13="","",IF($W$9="","",IF($W$9=0,"",W13/$W$9)))
A14: 4 | B14: 46209 | C14: =$B$5 -> 1 | G14: =IF(D14="","",D14-C14) | H14: =IF(D14="","",IF(D14>=C14,"En meta",IF(D14>=C14-0.05,"Riesgo","Atrasado"))) | J14: =IF(I14="","",IF($I$9="","",IF($I$9=0,"",I14/$I$9))) | L14: =IF(K14="","",IF($K$9="","",IF($K$9=0,"",K14/$K$9))) | N14: =IF(M14="","",IF($M$9="","",IF($M$9=0,"",M14/$M$9))) | P14: =IF(O14="","",IF($O$9="","",IF($O$9=0,"",O14/$O$9))) | R14: =IF(Q14="","",IF($Q$9="","",IF($Q$9=0,"",Q14/$Q$9))) | T14: =IF(S14="","",IF($S$9="","",IF($S$9=0,"",S14/$S$9))) | V14: =IF(U14="","",IF($U$9="","",IF($U$9=0,"",U14/$U$9))) | X14: =IF(W14="","",IF($W$9="","",IF($W$9=0,"",W14/$W$9)))
A15: 5 | B15: 46216 | C15: =$B$5 -> 1 | G15: =IF(D15="","",D15-C15) | H15: =IF(D15="","",IF(D15>=C15,"En meta",IF(D15>=C15-0.05,"Riesgo","Atrasado"))) | J15: =IF(I15="","",IF($I$9="","",IF($I$9=0,"",I15/$I$9))) | L15: =IF(K15="","",IF($K$9="","",IF($K$9=0,"",K15/$K$9))) | N15: =IF(M15="","",IF($M$9="","",IF($M$9=0,"",M15/$M$9))) | P15: =IF(O15="","",IF($O$9="","",IF($O$9=0,"",O15/$O$9))) | R15: =IF(Q15="","",IF($Q$9="","",IF($Q$9=0,"",Q15/$Q$9))) | T15: =IF(S15="","",IF($S$9="","",IF($S$9=0,"",S15/$S$9))) | V15: =IF(U15="","",IF($U$9="","",IF($U$9=0,"",U15/$U$9))) | X15: =IF(W15="","",IF($W$9="","",IF($W$9=0,"",W15/$W$9)))
A16: 6 | B16: 46223 | C16: =$B$5 -> 1 | G16: =IF(D16="","",D16-C16) | H16: =IF(D16="","",IF(D16>=C16,"En meta",IF(D16>=C16-0.05,"Riesgo","Atrasado"))) | J16: =IF(I16="","",IF($I$9="","",IF($I$9=0,"",I16/$I$9))) | L16: =IF(K16="","",IF($K$9="","",IF($K$9=0,"",K16/$K$9))) | N16: =IF(M16="","",IF($M$9="","",IF($M$9=0,"",M16/$M$9))) | P16: =IF(O16="","",IF($O$9="","",IF($O$9=0,"",O16/$O$9))) | R16: =IF(Q16="","",IF($Q$9="","",IF($Q$9=0,"",Q16/$Q$9))) | T16: =IF(S16="","",IF($S$9="","",IF($S$9=0,"",S16/$S$9))) | V16: =IF(U16="","",IF($U$9="","",IF($U$9=0,"",U16/$U$9))) | X16: =IF(W16="","",IF($W$9="","",IF($W$9=0,"",W16/$W$9)))
A17: 7 | B17: 46230 | C17: =$B$5 -> 1 | G17: =IF(D17="","",D17-C17) | H17: =IF(D17="","",IF(D17>=C17,"En meta",IF(D17>=C17-0.05,"Riesgo","Atrasado"))) | J17: =IF(I17="","",IF($I$9="","",IF($I$9=0,"",I17/$I$9))) | L17: =IF(K17="","",IF($K$9="","",IF($K$9=0,"",K17/$K$9))) | N17: =IF(M17="","",IF($M$9="","",IF($M$9=0,"",M17/$M$9))) | P17: =IF(O17="","",IF($O$9="","",IF($O$9=0,"",O17/$O$9))) | R17: =IF(Q17="","",IF($Q$9="","",IF($Q$9=0,"",Q17/$Q$9))) | T17: =IF(S17="","",IF($S$9="","",IF($S$9=0,"",S17/$S$9))) | V17: =IF(U17="","",IF($U$9="","",IF($U$9=0,"",U17/$U$9))) | X17: =IF(W17="","",IF($W$9="","",IF($W$9=0,"",W17/$W$9)))
A18: 8 | B18: 46237 | C18: =$B$5 -> 1 | G18: =IF(D18="","",D18-C18) | H18: =IF(D18="","",IF(D18>=C18,"En meta",IF(D18>=C18-0.05,"Riesgo","Atrasado"))) | J18: =IF(I18="","",IF($I$9="","",IF($I$9=0,"",I18/$I$9))) | L18: =IF(K18="","",IF($K$9="","",IF($K$9=0,"",K18/$K$9))) | N18: =IF(M18="","",IF($M$9="","",IF($M$9=0,"",M18/$M$9))) | P18: =IF(O18="","",IF($O$9="","",IF($O$9=0,"",O18/$O$9))) | R18: =IF(Q18="","",IF($Q$9="","",IF($Q$9=0,"",Q18/$Q$9))) | T18: =IF(S18="","",IF($S$9="","",IF($S$9=0,"",S18/$S$9))) | V18: =IF(U18="","",IF($U$9="","",IF($U$9=0,"",U18/$U$9))) | X18: =IF(W18="","",IF($W$9="","",IF($W$9=0,"",W18/$W$9)))
A19: 9 | B19: 46244 | C19: =$B$5 -> 1 | G19: =IF(D19="","",D19-C19) | H19: =IF(D19="","",IF(D19>=C19,"En meta",IF(D19>=C19-0.05,"Riesgo","Atrasado"))) | J19: =IF(I19="","",IF($I$9="","",IF($I$9=0,"",I19/$I$9))) | L19: =IF(K19="","",IF($K$9="","",IF($K$9=0,"",K19/$K$9))) | N19: =IF(M19="","",IF($M$9="","",IF($M$9=0,"",M19/$M$9))) | P19: =IF(O19="","",IF($O$9="","",IF($O$9=0,"",O19/$O$9))) | R19: =IF(Q19="","",IF($Q$9="","",IF($Q$9=0,"",Q19/$Q$9))) | T19: =IF(S19="","",IF($S$9="","",IF($S$9=0,"",S19/$S$9))) | V19: =IF(U19="","",IF($U$9="","",IF($U$9=0,"",U19/$U$9))) | X19: =IF(W19="","",IF($W$9="","",IF($W$9=0,"",W19/$W$9)))
A20: 10 | B20: 46251 | C20: =$B$5 -> 1 | G20: =IF(D20="","",D20-C20) | H20: =IF(D20="","",IF(D20>=C20,"En meta",IF(D20>=C20-0.05,"Riesgo","Atrasado"))) | J20: =IF(I20="","",IF($I$9="","",IF($I$9=0,"",I20/$I$9))) | L20: =IF(K20="","",IF($K$9="","",IF($K$9=0,"",K20/$K$9))) | N20: =IF(M20="","",IF($M$9="","",IF($M$9=0,"",M20/$M$9))) | P20: =IF(O20="","",IF($O$9="","",IF($O$9=0,"",O20/$O$9))) | R20: =IF(Q20="","",IF($Q$9="","",IF($Q$9=0,"",Q20/$Q$9))) | T20: =IF(S20="","",IF($S$9="","",IF($S$9=0,"",S20/$S$9))) | V20: =IF(U20="","",IF($U$9="","",IF($U$9=0,"",U20/$U$9))) | X20: =IF(W20="","",IF($W$9="","",IF($W$9=0,"",W20/$W$9)))
A21: 11 | B21: 46258 | C21: =$B$5 -> 1 | G21: =IF(D21="","",D21-C21) | H21: =IF(D21="","",IF(D21>=C21,"En meta",IF(D21>=C21-0.05,"Riesgo","Atrasado"))) | J21: =IF(I21="","",IF($I$9="","",IF($I$9=0,"",I21/$I$9))) | L21: =IF(K21="","",IF($K$9="","",IF($K$9=0,"",K21/$K$9))) | N21: =IF(M21="","",IF($M$9="","",IF($M$9=0,"",M21/$M$9))) | P21: =IF(O21="","",IF($O$9="","",IF($O$9=0,"",O21/$O$9))) | R21: =IF(Q21="","",IF($Q$9="","",IF($Q$9=0,"",Q21/$Q$9))) | T21: =IF(S21="","",IF($S$9="","",IF($S$9=0,"",S21/$S$9))) | V21: =IF(U21="","",IF($U$9="","",IF($U$9=0,"",U21/$U$9))) | X21: =IF(W21="","",IF($W$9="","",IF($W$9=0,"",W21/$W$9)))
A22: 12 | B22: 46265 | C22: =$B$5 -> 1 | G22: =IF(D22="","",D22-C22) | H22: =IF(D22="","",IF(D22>=C22,"En meta",IF(D22>=C22-0.05,"Riesgo","Atrasado"))) | J22: =IF(I22="","",IF($I$9="","",IF($I$9=0,"",I22/$I$9))) | L22: =IF(K22="","",IF($K$9="","",IF($K$9=0,"",K22/$K$9))) | N22: =IF(M22="","",IF($M$9="","",IF($M$9=0,"",M22/$M$9))) | P22: =IF(O22="","",IF($O$9="","",IF($O$9=0,"",O22/$O$9))) | R22: =IF(Q22="","",IF($Q$9="","",IF($Q$9=0,"",Q22/$Q$9))) | T22: =IF(S22="","",IF($S$9="","",IF($S$9=0,"",S22/$S$9))) | V22: =IF(U22="","",IF($U$9="","",IF($U$9=0,"",U22/$U$9))) | X22: =IF(W22="","",IF($W$9="","",IF($W$9=0,"",W22/$W$9)))
... A91: 81 | B91: 46748 | C91: =$B$5 -> 1 | G91: =IF(D91="","",D91-C91) | H91: =IF(D91="","",IF(D91>=C91,"En meta",IF(D91>=C91-0.05,"Riesgo","Atrasado"))) | J91: =IF(I91="","",IF($I$9="","",IF($I$9=0,"",I91/$I$9))) | L91: =IF(K91="","",IF($K$9="","",IF($K$9=0,"",K91/$K$9))) | N91: =IF(M91="","",IF($M$9="","",IF($M$9=0,"",M91/$M$9))) | P91: =IF(O91="","",IF($O$9="","",IF($O$9=0,"",O91/$O$9))) | R91: =IF(Q91="","",IF($Q$9="","",IF($Q$9=0,"",Q91/$Q$9))) | T91: =IF(S91="","",IF($S$9="","",IF($S$9=0,"",S91/$S$9))) | V91: =IF(U91="","",IF($U$9="","",IF($U$9=0,"",U91/$U$9))) | X91: =IF(W91="","",IF($W$9="","",IF($W$9=0,"",W91/$W$9)))

Sheet 5. MV Datacenter
A1: WIG 5 — Incrementar el MV de servicios basados en el DC GBM San Marcos en $20,000
A2: Indicador lag: | B2: MV nuevo firmado de servicios basados desde el datacenter (USD acumulado).
A3: De X a Y: | B3: De $0 a +$20,000 de MV incremental, antes del 31 de diciembre de 2027.
A4: Dueño: | B4: Por asignar | D4: Equipo: | E4: Pre-Sales, Del - DC
A5: Meta: | B5: 20000 | D5: Inicio: | E5: 46188 | G5: Fin: | H5: 46748
A6: Leads: | B6: Hasta 8 indicadores predictivos a la derecha. L1–L2 = apuesta principal del equipo; L3–L8 = indicadores de apoyo. Nombre (fila 8) y meta semanal (fila 9) editables en azul.
A8: Periodos: | B8: =COUNT(A11:A91) -> 81 | H8: Lead → | I8: L1. Propuestas de servicios DC presentadas | K8: L2. Workloads nuevos aprovisionados / migrados | M8: L3. Assessments de migración realizados | O8: L4. Opps DC activas en pipeline | Q8: L5. Clientes contactados con oferta DC | S8: L6. % capacidad DC documentada y actualizada | U8: (Disponible) | W8: (Disponible)
A9: Celdas azules = se digitan cada lunes. Celdas negras = fórmulas, no tocar. | H9: Meta → | I9: 2 | K9: 1 | M9: 1 | O9: 4 | Q9: 3 | S9: 1
A10: # | B10: Semana | C10: Meta semana | D10: Real | E10: Meta acum. | F10: Real acum. | G10: % avance | H10: Estado | I10: Real | J10: % | K10: Real | L10: % | M10: Real | N10: % | O10: Real | P10: % | Q10: Real | R10: % | S10: Real | T10: % | U10: Real | V10: % | W10: Real | X10: %
A11: 1 | B11: 46188 | C11: =$B$5/$B$8 -> 246.91358 | E11: =SUM($C$11:C11) -> 246.91358 | F11: =SUM($D$11:D11) -> 0 | G11: =IF(COUNT($D$11:D11)=0,"",F11/E11) | H11: =IF(G11="","",IF(G11>=0.95,"En meta",IF(G11>=0.8,"Riesgo","Atrasado"))) | J11: =IF(I11="","",IF($I$9="","",IF($I$9=0,"",I11/$I$9))) | L11: =IF(K11="","",IF($K$9="","",IF($K$9=0,"",K11/$K$9))) | N11: =IF(M11="","",IF($M$9="","",IF($M$9=0,"",M11/$M$9))) | P11: =IF(O11="","",IF($O$9="","",IF($O$9=0,"",O11/$O$9))) | R11: =IF(Q11="","",IF($Q$9="","",IF($Q$9=0,"",Q11/$Q$9))) | T11: =IF(S11="","",IF($S$9="","",IF($S$9=0,"",S11/$S$9))) | V11: =IF(U11="","",IF($U$9="","",IF($U$9=0,"",U11/$U$9))) | X11: =IF(W11="","",IF($W$9="","",IF($W$9=0,"",W11/$W$9)))
A12: 2 | B12: 46195 | C12: =$B$5/$B$8 -> 246.91358 | E12: =SUM($C$11:C12) -> 493.82716 | F12: =SUM($D$11:D12) -> 0 | G12: =IF(COUNT($D$11:D12)=0,"",F12/E12) | H12: =IF(G12="","",IF(G12>=0.95,"En meta",IF(G12>=0.8,"Riesgo","Atrasado"))) | J12: =IF(I12="","",IF($I$9="","",IF($I$9=0,"",I12/$I$9))) | L12: =IF(K12="","",IF($K$9="","",IF($K$9=0,"",K12/$K$9))) | N12: =IF(M12="","",IF($M$9="","",IF($M$9=0,"",M12/$M$9))) | P12: =IF(O12="","",IF($O$9="","",IF($O$9=0,"",O12/$O$9))) | R12: =IF(Q12="","",IF($Q$9="","",IF($Q$9=0,"",Q12/$Q$9))) | T12: =IF(S12="","",IF($S$9="","",IF($S$9=0,"",S12/$S$9))) | V12: =IF(U12="","",IF($U$9="","",IF($U$9=0,"",U12/$U$9))) | X12: =IF(W12="","",IF($W$9="","",IF($W$9=0,"",W12/$W$9)))
A13: 3 | B13: 46202 | C13: =$B$5/$B$8 -> 246.91358 | E13: =SUM($C$11:C13) -> 740.74074 | F13: =SUM($D$11:D13) -> 0 | G13: =IF(COUNT($D$11:D13)=0,"",F13/E13) | H13: =IF(G13="","",IF(G13>=0.95,"En meta",IF(G13>=0.8,"Riesgo","Atrasado"))) | J13: =IF(I13="","",IF($I$9="","",IF($I$9=0,"",I13/$I$9))) | L13: =IF(K13="","",IF($K$9="","",IF($K$9=0,"",K13/$K$9))) | N13: =IF(M13="","",IF($M$9="","",IF($M$9=0,"",M13/$M$9))) | P13: =IF(O13="","",IF($O$9="","",IF($O$9=0,"",O13/$O$9))) | R13: =IF(Q13="","",IF($Q$9="","",IF($Q$9=0,"",Q13/$Q$9))) | T13: =IF(S13="","",IF($S$9="","",IF($S$9=0,"",S13/$S$9))) | V13: =IF(U13="","",IF($U$9="","",IF($U$9=0,"",U13/$U$9))) | X13: =IF(W13="","",IF($W$9="","",IF($W$9=0,"",W13/$W$9)))
A14: 4 | B14: 46209 | C14: =$B$5/$B$8 -> 246.91358 | E14: =SUM($C$11:C14) -> 987.65432 | F14: =SUM($D$11:D14) -> 0 | G14: =IF(COUNT($D$11:D14)=0,"",F14/E14) | H14: =IF(G14="","",IF(G14>=0.95,"En meta",IF(G14>=0.8,"Riesgo","Atrasado"))) | J14: =IF(I14="","",IF($I$9="","",IF($I$9=0,"",I14/$I$9))) | L14: =IF(K14="","",IF($K$9="","",IF($K$9=0,"",K14/$K$9))) | N14: =IF(M14="","",IF($M$9="","",IF($M$9=0,"",M14/$M$9))) | P14: =IF(O14="","",IF($O$9="","",IF($O$9=0,"",O14/$O$9))) | R14: =IF(Q14="","",IF($Q$9="","",IF($Q$9=0,"",Q14/$Q$9))) | T14: =IF(S14="","",IF($S$9="","",IF($S$9=0,"",S14/$S$9))) | V14: =IF(U14="","",IF($U$9="","",IF($U$9=0,"",U14/$U$9))) | X14: =IF(W14="","",IF($W$9="","",IF($W$9=0,"",W14/$W$9)))
A15: 5 | B15: 46216 | C15: =$B$5/$B$8 -> 246.91358 | E15: =SUM($C$11:C15) -> 1234.5679 | F15: =SUM($D$11:D15) -> 0 | G15: =IF(COUNT($D$11:D15)=0,"",F15/E15) | H15: =IF(G15="","",IF(G15>=0.95,"En meta",IF(G15>=0.8,"Riesgo","Atrasado"))) | J15: =IF(I15="","",IF($I$9="","",IF($I$9=0,"",I15/$I$9))) | L15: =IF(K15="","",IF($K$9="","",IF($K$9=0,"",K15/$K$9))) | N15: =IF(M15="","",IF($M$9="","",IF($M$9=0,"",M15/$M$9))) | P15: =IF(O15="","",IF($O$9="","",IF($O$9=0,"",O15/$O$9))) | R15: =IF(Q15="","",IF($Q$9="","",IF($Q$9=0,"",Q15/$Q$9))) | T15: =IF(S15="","",IF($S$9="","",IF($S$9=0,"",S15/$S$9))) | V15: =IF(U15="","",IF($U$9="","",IF($U$9=0,"",U15/$U$9))) | X15: =IF(W15="","",IF($W$9="","",IF($W$9=0,"",W15/$W$9)))
A16: 6 | B16: 46223 | C16: =$B$5/$B$8 -> 246.91358 | E16: =SUM($C$11:C16) -> 1481.4815 | F16: =SUM($D$11:D16) -> 0 | G16: =IF(COUNT($D$11:D16)=0,"",F16/E16) | H16: =IF(G16="","",IF(G16>=0.95,"En meta",IF(G16>=0.8,"Riesgo","Atrasado"))) | J16: =IF(I16="","",IF($I$9="","",IF($I$9=0,"",I16/$I$9))) | L16: =IF(K16="","",IF($K$9="","",IF($K$9=0,"",K16/$K$9))) | N16: =IF(M16="","",IF($M$9="","",IF($M$9=0,"",M16/$M$9))) | P16: =IF(O16="","",IF($O$9="","",IF($O$9=0,"",O16/$O$9))) | R16: =IF(Q16="","",IF($Q$9="","",IF($Q$9=0,"",Q16/$Q$9))) | T16: =IF(S16="","",IF($S$9="","",IF($S$9=0,"",S16/$S$9))) | V16: =IF(U16="","",IF($U$9="","",IF($U$9=0,"",U16/$U$9))) | X16: =IF(W16="","",IF($W$9="","",IF($W$9=0,"",W16/$W$9)))
A17: 7 | B17: 46230 | C17: =$B$5/$B$8 -> 246.91358 | E17: =SUM($C$11:C17) -> 1728.3951 | F17: =SUM($D$11:D17) -> 0 | G17: =IF(COUNT($D$11:D17)=0,"",F17/E17) | H17: =IF(G17="","",IF(G17>=0.95,"En meta",IF(G17>=0.8,"Riesgo","Atrasado"))) | J17: =IF(I17="","",IF($I$9="","",IF($I$9=0,"",I17/$I$9))) | L17: =IF(K17="","",IF($K$9="","",IF($K$9=0,"",K17/$K$9))) | N17: =IF(M17="","",IF($M$9="","",IF($M$9=0,"",M17/$M$9))) | P17: =IF(O17="","",IF($O$9="","",IF($O$9=0,"",O17/$O$9))) | R17: =IF(Q17="","",IF($Q$9="","",IF($Q$9=0,"",Q17/$Q$9))) | T17: =IF(S17="","",IF($S$9="","",IF($S$9=0,"",S17/$S$9))) | V17: =IF(U17="","",IF($U$9="","",IF($U$9=0,"",U17/$U$9))) | X17: =IF(W17="","",IF($W$9="","",IF($W$9=0,"",W17/$W$9)))
A18: 8 | B18: 46237 | C18: =$B$5/$B$8 -> 246.91358 | E18: =SUM($C$11:C18) -> 1975.3086 | F18: =SUM($D$11:D18) -> 0 | G18: =IF(COUNT($D$11:D18)=0,"",F18/E18) | H18: =IF(G18="","",IF(G18>=0.95,"En meta",IF(G18>=0.8,"Riesgo","Atrasado"))) | J18: =IF(I18="","",IF($I$9="","",IF($I$9=0,"",I18/$I$9))) | L18: =IF(K18="","",IF($K$9="","",IF($K$9=0,"",K18/$K$9))) | N18: =IF(M18="","",IF($M$9="","",IF($M$9=0,"",M18/$M$9))) | P18: =IF(O18="","",IF($O$9="","",IF($O$9=0,"",O18/$O$9))) | R18: =IF(Q18="","",IF($Q$9="","",IF($Q$9=0,"",Q18/$Q$9))) | T18: =IF(S18="","",IF($S$9="","",IF($S$9=0,"",S18/$S$9))) | V18: =IF(U18="","",IF($U$9="","",IF($U$9=0,"",U18/$U$9))) | X18: =IF(W18="","",IF($W$9="","",IF($W$9=0,"",W18/$W$9)))
A19: 9 | B19: 46244 | C19: =$B$5/$B$8 -> 246.91358 | E19: =SUM($C$11:C19) -> 2222.2222 | F19: =SUM($D$11:D19) -> 0 | G19: =IF(COUNT($D$11:D19)=0,"",F19/E19) | H19: =IF(G19="","",IF(G19>=0.95,"En meta",IF(G19>=0.8,"Riesgo","Atrasado"))) | J19: =IF(I19="","",IF($I$9="","",IF($I$9=0,"",I19/$I$9))) | L19: =IF(K19="","",IF($K$9="","",IF($K$9=0,"",K19/$K$9))) | N19: =IF(M19="","",IF($M$9="","",IF($M$9=0,"",M19/$M$9))) | P19: =IF(O19="","",IF($O$9="","",IF($O$9=0,"",O19/$O$9))) | R19: =IF(Q19="","",IF($Q$9="","",IF($Q$9=0,"",Q19/$Q$9))) | T19: =IF(S19="","",IF($S$9="","",IF($S$9=0,"",S19/$S$9))) | V19: =IF(U19="","",IF($U$9="","",IF($U$9=0,"",U19/$U$9))) | X19: =IF(W19="","",IF($W$9="","",IF($W$9=0,"",W19/$W$9)))
A20: 10 | B20: 46251 | C20: =$B$5/$B$8 -> 246.91358 | E20: =SUM($C$11:C20) -> 2469.1358 | F20: =SUM($D$11:D20) -> 0 | G20: =IF(COUNT($D$11:D20)=0,"",F20/E20) | H20: =IF(G20="","",IF(G20>=0.95,"En meta",IF(G20>=0.8,"Riesgo","Atrasado"))) | J20: =IF(I20="","",IF($I$9="","",IF($I$9=0,"",I20/$I$9))) | L20: =IF(K20="","",IF($K$9="","",IF($K$9=0,"",K20/$K$9))) | N20: =IF(M20="","",IF($M$9="","",IF($M$9=0,"",M20/$M$9))) | P20: =IF(O20="","",IF($O$9="","",IF($O$9=0,"",O20/$O$9))) | R20: =IF(Q20="","",IF($Q$9="","",IF($Q$9=0,"",Q20/$Q$9))) | T20: =IF(S20="","",IF($S$9="","",IF($S$9=0,"",S20/$S$9))) | V20: =IF(U20="","",IF($U$9="","",IF($U$9=0,"",U20/$U$9))) | X20: =IF(W20="","",IF($W$9="","",IF($W$9=0,"",W20/$W$9)))
A21: 11 | B21: 46258 | C21: =$B$5/$B$8 -> 246.91358 | E21: =SUM($C$11:C21) -> 2716.0494 | F21: =SUM($D$11:D21) -> 0 | G21: =IF(COUNT($D$11:D21)=0,"",F21/E21) | H21: =IF(G21="","",IF(G21>=0.95,"En meta",IF(G21>=0.8,"Riesgo","Atrasado"))) | J21: =IF(I21="","",IF($I$9="","",IF($I$9=0,"",I21/$I$9))) | L21: =IF(K21="","",IF($K$9="","",IF($K$9=0,"",K21/$K$9))) | N21: =IF(M21="","",IF($M$9="","",IF($M$9=0,"",M21/$M$9))) | P21: =IF(O21="","",IF($O$9="","",IF($O$9=0,"",O21/$O$9))) | R21: =IF(Q21="","",IF($Q$9="","",IF($Q$9=0,"",Q21/$Q$9))) | T21: =IF(S21="","",IF($S$9="","",IF($S$9=0,"",S21/$S$9))) | V21: =IF(U21="","",IF($U$9="","",IF($U$9=0,"",U21/$U$9))) | X21: =IF(W21="","",IF($W$9="","",IF($W$9=0,"",W21/$W$9)))
A22: 12 | B22: 46265 | C22: =$B$5/$B$8 -> 246.91358 | E22: =SUM($C$11:C22) -> 2962.963 | F22: =SUM($D$11:D22) -> 0 | G22: =IF(COUNT($D$11:D22)=0,"",F22/E22) | H22: =IF(G22="","",IF(G22>=0.95,"En meta",IF(G22>=0.8,"Riesgo","Atrasado"))) | J22: =IF(I22="","",IF($I$9="","",IF($I$9=0,"",I22/$I$9))) | L22: =IF(K22="","",IF($K$9="","",IF($K$9=0,"",K22/$K$9))) | N22: =IF(M22="","",IF($M$9="","",IF($M$9=0,"",M22/$M$9))) | P22: =IF(O22="","",IF($O$9="","",IF($O$9=0,"",O22/$O$9))) | R22: =IF(Q22="","",IF($Q$9="","",IF($Q$9=0,"",Q22/$Q$9))) | T22: =IF(S22="","",IF($S$9="","",IF($S$9=0,"",S22/$S$9))) | V22: =IF(U22="","",IF($U$9="","",IF($U$9=0,"",U22/$U$9))) | X22: =IF(W22="","",IF($W$9="","",IF($W$9=0,"",W22/$W$9)))
... A91: 81 | B91: 46748 | C91: =$B$5/$B$8 -> 246.91358 | E91: =SUM($C$11:C91) -> 20000 | F91: =SUM($D$11:D91) -> 0 | G91: =IF(COUNT($D$11:D91)=0,"",F91/E91) | H91: =IF(G91="","",IF(G91>=0.95,"En meta",IF(G91>=0.8,"Riesgo","Atrasado"))) | J91: =IF(I91="","",IF($I$9="","",IF($I$9=0,"",I91/$I$9))) | L91: =IF(K91="","",IF($K$9="","",IF($K$9=0,"",K91/$K$9))) | N91: =IF(M91="","",IF($M$9="","",IF($M$9=0,"",M91/$M$9))) | P91: =IF(O91="","",IF($O$9="","",IF($O$9=0,"",O91/$O$9))) | R91: =IF(Q91="","",IF($Q$9="","",IF($Q$9=0,"",Q91/$Q$9))) | T91: =IF(S91="","",IF($S$9="","",IF($S$9=0,"",S91/$S$9))) | V91: =IF(U91="","",IF($U$9="","",IF($U$9=0,"",U91/$U$9))) | X91: =IF(W91="","",IF($W$9="","",IF($W$9=0,"",W91/$W$9)))

Sheet 6. Cero Expired
A1: WIG 6 — Tener cero contratos expired en al menos 16 de los próximos 18 meses
A2: Indicador lag: | B2: Contratos en estado Expired / On-Hold al cierre de la semana (meta: 0).
A3: De X a Y: | B3: De N a 0 contratos expired, sosteniéndolo en 16 de los próximos 18 meses (jun 2026 – dic 2027).
A4: Dueño: | B4: Por asignar | D4: Equipo: | E4: Customer Success, Del - DEX, Del - TSS, Del - DC
A5: Meta: | B5: 0 | D5: Inicio: | E5: 46188 | G5: Fin: | H5: 46748
A6: Leads: | B6: Hasta 8 indicadores predictivos a la derecha. L1–L2 = apuesta principal del equipo; L3–L8 = indicadores de apoyo. Nombre (fila 8) y meta semanal (fila 9) editables en azul.
A8: Periodos: | B8: =COUNT(A11:A91) -> 81 | H8: Lead → | I8: L1. % contratos por vencer en 90 días con plan | K8: L2. Renovaciones cerradas a tiempo en la semana | M8: L3. Cotizaciones de renovación enviadas ≥60 días antes | O8: L4. QBRs con clientes en riesgo de no renovar | Q8: L5. % contratos on-hold con plan de reactivación | S8: L6. Forecast de renovaciones actualizado (1 = sí) | U8: (Disponible) | W8: (Disponible)
A9: Celdas azules = se digitan cada lunes. Celdas negras = fórmulas, no tocar. | H9: Meta → | I9: 1 | K9: 2 | M9: 3 | O9: 1 | Q9: 1 | S9: 1
A10: # | B10: Semana | C10: Meta | D10: Real | G10: Brecha vs meta | H10: Estado | I10: Real | J10: % | K10: Real | L10: % | M10: Real | N10: % | O10: Real | P10: % | Q10: Real | R10: % | S10: Real | T10: % | U10: Real | V10: % | W10: Real | X10: %
A11: 1 | B11: 46188 | C11: =$B$5 -> 0 | G11: =IF(D11="","",D11-C11) | H11: =IF(D11="","",IF(D11<=C11,"En meta",IF(D11<=C11+1,"Riesgo","Atrasado"))) | J11: =IF(I11="","",IF($I$9="","",IF($I$9=0,"",I11/$I$9))) | L11: =IF(K11="","",IF($K$9="","",IF($K$9=0,"",K11/$K$9))) | N11: =IF(M11="","",IF($M$9="","",IF($M$9=0,"",M11/$M$9))) | P11: =IF(O11="","",IF($O$9="","",IF($O$9=0,"",O11/$O$9))) | R11: =IF(Q11="","",IF($Q$9="","",IF($Q$9=0,"",Q11/$Q$9))) | T11: =IF(S11="","",IF($S$9="","",IF($S$9=0,"",S11/$S$9))) | V11: =IF(U11="","",IF($U$9="","",IF($U$9=0,"",U11/$U$9))) | X11: =IF(W11="","",IF($W$9="","",IF($W$9=0,"",W11/$W$9)))
A12: 2 | B12: 46195 | C12: =$B$5 -> 0 | G12: =IF(D12="","",D12-C12) | H12: =IF(D12="","",IF(D12<=C12,"En meta",IF(D12<=C12+1,"Riesgo","Atrasado"))) | J12: =IF(I12="","",IF($I$9="","",IF($I$9=0,"",I12/$I$9))) | L12: =IF(K12="","",IF($K$9="","",IF($K$9=0,"",K12/$K$9))) | N12: =IF(M12="","",IF($M$9="","",IF($M$9=0,"",M12/$M$9))) | P12: =IF(O12="","",IF($O$9="","",IF($O$9=0,"",O12/$O$9))) | R12: =IF(Q12="","",IF($Q$9="","",IF($Q$9=0,"",Q12/$Q$9))) | T12: =IF(S12="","",IF($S$9="","",IF($S$9=0,"",S12/$S$9))) | V12: =IF(U12="","",IF($U$9="","",IF($U$9=0,"",U12/$U$9))) | X12: =IF(W12="","",IF($W$9="","",IF($W$9=0,"",W12/$W$9)))
A13: 3 | B13: 46202 | C13: =$B$5 -> 0 | G13: =IF(D13="","",D13-C13) | H13: =IF(D13="","",IF(D13<=C13,"En meta",IF(D13<=C13+1,"Riesgo","Atrasado"))) | J13: =IF(I13="","",IF($I$9="","",IF($I$9=0,"",I13/$I$9))) | L13: =IF(K13="","",IF($K$9="","",IF($K$9=0,"",K13/$K$9))) | N13: =IF(M13="","",IF($M$9="","",IF($M$9=0,"",M13/$M$9))) | P13: =IF(O13="","",IF($O$9="","",IF($O$9=0,"",O13/$O$9))) | R13: =IF(Q13="","",IF($Q$9="","",IF($Q$9=0,"",Q13/$Q$9))) | T13: =IF(S13="","",IF($S$9="","",IF($S$9=0,"",S13/$S$9))) | V13: =IF(U13="","",IF($U$9="","",IF($U$9=0,"",U13/$U$9))) | X13: =IF(W13="","",IF($W$9="","",IF($W$9=0,"",W13/$W$9)))
A14: 4 | B14: 46209 | C14: =$B$5 -> 0 | G14: =IF(D14="","",D14-C14) | H14: =IF(D14="","",IF(D14<=C14,"En meta",IF(D14<=C14+1,"Riesgo","Atrasado"))) | J14: =IF(I14="","",IF($I$9="","",IF($I$9=0,"",I14/$I$9))) | L14: =IF(K14="","",IF($K$9="","",IF($K$9=0,"",K14/$K$9))) | N14: =IF(M14="","",IF($M$9="","",IF($M$9=0,"",M14/$M$9))) | P14: =IF(O14="","",IF($O$9="","",IF($O$9=0,"",O14/$O$9))) | R14: =IF(Q14="","",IF($Q$9="","",IF($Q$9=0,"",Q14/$Q$9))) | T14: =IF(S14="","",IF($S$9="","",IF($S$9=0,"",S14/$S$9))) | V14: =IF(U14="","",IF($U$9="","",IF($U$9=0,"",U14/$U$9))) | X14: =IF(W14="","",IF($W$9="","",IF($W$9=0,"",W14/$W$9)))
A15: 5 | B15: 46216 | C15: =$B$5 -> 0 | G15: =IF(D15="","",D15-C15) | H15: =IF(D15="","",IF(D15<=C15,"En meta",IF(D15<=C15+1,"Riesgo","Atrasado"))) | J15: =IF(I15="","",IF($I$9="","",IF($I$9=0,"",I15/$I$9))) | L15: =IF(K15="","",IF($K$9="","",IF($K$9=0,"",K15/$K$9))) | N15: =IF(M15="","",IF($M$9="","",IF($M$9=0,"",M15/$M$9))) | P15: =IF(O15="","",IF($O$9="","",IF($O$9=0,"",O15/$O$9))) | R15: =IF(Q15="","",IF($Q$9="","",IF($Q$9=0,"",Q15/$Q$9))) | T15: =IF(S15="","",IF($S$9="","",IF($S$9=0,"",S15/$S$9))) | V15: =IF(U15="","",IF($U$9="","",IF($U$9=0,"",U15/$U$9))) | X15: =IF(W15="","",IF($W$9="","",IF($W$9=0,"",W15/$W$9)))
A16: 6 | B16: 46223 | C16: =$B$5 -> 0 | G16: =IF(D16="","",D16-C16) | H16: =IF(D16="","",IF(D16<=C16,"En meta",IF(D16<=C16+1,"Riesgo","Atrasado"))) | J16: =IF(I16="","",IF($I$9="","",IF($I$9=0,"",I16/$I$9))) | L16: =IF(K16="","",IF($K$9="","",IF($K$9=0,"",K16/$K$9))) | N16: =IF(M16="","",IF($M$9="","",IF($M$9=0,"",M16/$M$9))) | P16: =IF(O16="","",IF($O$9="","",IF($O$9=0,"",O16/$O$9))) | R16: =IF(Q16="","",IF($Q$9="","",IF($Q$9=0,"",Q16/$Q$9))) | T16: =IF(S16="","",IF($S$9="","",IF($S$9=0,"",S16/$S$9))) | V16: =IF(U16="","",IF($U$9="","",IF($U$9=0,"",U16/$U$9))) | X16: =IF(W16="","",IF($W$9="","",IF($W$9=0,"",W16/$W$9)))
A17: 7 | B17: 46230 | C17: =$B$5 -> 0 | G17: =IF(D17="","",D17-C17) | H17: =IF(D17="","",IF(D17<=C17,"En meta",IF(D17<=C17+1,"Riesgo","Atrasado"))) | J17: =IF(I17="","",IF($I$9="","",IF($I$9=0,"",I17/$I$9))) | L17: =IF(K17="","",IF($K$9="","",IF($K$9=0,"",K17/$K$9))) | N17: =IF(M17="","",IF($M$9="","",IF($M$9=0,"",M17/$M$9))) | P17: =IF(O17="","",IF($O$9="","",IF($O$9=0,"",O17/$O$9))) | R17: =IF(Q17="","",IF($Q$9="","",IF($Q$9=0,"",Q17/$Q$9))) | T17: =IF(S17="","",IF($S$9="","",IF($S$9=0,"",S17/$S$9))) | V17: =IF(U17="","",IF($U$9="","",IF($U$9=0,"",U17/$U$9))) | X17: =IF(W17="","",IF($W$9="","",IF($W$9=0,"",W17/$W$9)))
A18: 8 | B18: 46237 | C18: =$B$5 -> 0 | G18: =IF(D18="","",D18-C18) | H18: =IF(D18="","",IF(D18<=C18,"En meta",IF(D18<=C18+1,"Riesgo","Atrasado"))) | J18: =IF(I18="","",IF($I$9="","",IF($I$9=0,"",I18/$I$9))) | L18: =IF(K18="","",IF($K$9="","",IF($K$9=0,"",K18/$K$9))) | N18: =IF(M18="","",IF($M$9="","",IF($M$9=0,"",M18/$M$9))) | P18: =IF(O18="","",IF($O$9="","",IF($O$9=0,"",O18/$O$9))) | R18: =IF(Q18="","",IF($Q$9="","",IF($Q$9=0,"",Q18/$Q$9))) | T18: =IF(S18="","",IF($S$9="","",IF($S$9=0,"",S18/$S$9))) | V18: =IF(U18="","",IF($U$9="","",IF($U$9=0,"",U18/$U$9))) | X18: =IF(W18="","",IF($W$9="","",IF($W$9=0,"",W18/$W$9)))
A19: 9 | B19: 46244 | C19: =$B$5 -> 0 | G19: =IF(D19="","",D19-C19) | H19: =IF(D19="","",IF(D19<=C19,"En meta",IF(D19<=C19+1,"Riesgo","Atrasado"))) | J19: =IF(I19="","",IF($I$9="","",IF($I$9=0,"",I19/$I$9))) | L19: =IF(K19="","",IF($K$9="","",IF($K$9=0,"",K19/$K$9))) | N19: =IF(M19="","",IF($M$9="","",IF($M$9=0,"",M19/$M$9))) | P19: =IF(O19="","",IF($O$9="","",IF($O$9=0,"",O19/$O$9))) | R19: =IF(Q19="","",IF($Q$9="","",IF($Q$9=0,"",Q19/$Q$9))) | T19: =IF(S19="","",IF($S$9="","",IF($S$9=0,"",S19/$S$9))) | V19: =IF(U19="","",IF($U$9="","",IF($U$9=0,"",U19/$U$9))) | X19: =IF(W19="","",IF($W$9="","",IF($W$9=0,"",W19/$W$9)))
A20: 10 | B20: 46251 | C20: =$B$5 -> 0 | G20: =IF(D20="","",D20-C20) | H20: =IF(D20="","",IF(D20<=C20,"En meta",IF(D20<=C20+1,"Riesgo","Atrasado"))) | J20: =IF(I20="","",IF($I$9="","",IF($I$9=0,"",I20/$I$9))) | L20: =IF(K20="","",IF($K$9="","",IF($K$9=0,"",K20/$K$9))) | N20: =IF(M20="","",IF($M$9="","",IF($M$9=0,"",M20/$M$9))) | P20: =IF(O20="","",IF($O$9="","",IF($O$9=0,"",O20/$O$9))) | R20: =IF(Q20="","",IF($Q$9="","",IF($Q$9=0,"",Q20/$Q$9))) | T20: =IF(S20="","",IF($S$9="","",IF($S$9=0,"",S20/$S$9))) | V20: =IF(U20="","",IF($U$9="","",IF($U$9=0,"",U20/$U$9))) | X20: =IF(W20="","",IF($W$9="","",IF($W$9=0,"",W20/$W$9)))
A21: 11 | B21: 46258 | C21: =$B$5 -> 0 | G21: =IF(D21="","",D21-C21) | H21: =IF(D21="","",IF(D21<=C21,"En meta",IF(D21<=C21+1,"Riesgo","Atrasado"))) | J21: =IF(I21="","",IF($I$9="","",IF($I$9=0,"",I21/$I$9))) | L21: =IF(K21="","",IF($K$9="","",IF($K$9=0,"",K21/$K$9))) | N21: =IF(M21="","",IF($M$9="","",IF($M$9=0,"",M21/$M$9))) | P21: =IF(O21="","",IF($O$9="","",IF($O$9=0,"",O21/$O$9))) | R21: =IF(Q21="","",IF($Q$9="","",IF($Q$9=0,"",Q21/$Q$9))) | T21: =IF(S21="","",IF($S$9="","",IF($S$9=0,"",S21/$S$9))) | V21: =IF(U21="","",IF($U$9="","",IF($U$9=0,"",U21/$U$9))) | X21: =IF(W21="","",IF($W$9="","",IF($W$9=0,"",W21/$W$9)))
A22: 12 | B22: 46265 | C22: =$B$5 -> 0 | G22: =IF(D22="","",D22-C22) | H22: =IF(D22="","",IF(D22<=C22,"En meta",IF(D22<=C22+1,"Riesgo","Atrasado"))) | J22: =IF(I22="","",IF($I$9="","",IF($I$9=0,"",I22/$I$9))) | L22: =IF(K22="","",IF($K$9="","",IF($K$9=0,"",K22/$K$9))) | N22: =IF(M22="","",IF($M$9="","",IF($M$9=0,"",M22/$M$9))) | P22: =IF(O22="","",IF($O$9="","",IF($O$9=0,"",O22/$O$9))) | R22: =IF(Q22="","",IF($Q$9="","",IF($Q$9=0,"",Q22/$Q$9))) | T22: =IF(S22="","",IF($S$9="","",IF($S$9=0,"",S22/$S$9))) | V22: =IF(U22="","",IF($U$9="","",IF($U$9=0,"",U22/$U$9))) | X22: =IF(W22="","",IF($W$9="","",IF($W$9=0,"",W22/$W$9)))
... A91: 81 | B91: 46748 | C91: =$B$5 -> 0 | G91: =IF(D91="","",D91-C91) | H91: =IF(D91="","",IF(D91<=C91,"En meta",IF(D91<=C91+1,"Riesgo","Atrasado"))) | J91: =IF(I91="","",IF($I$9="","",IF($I$9=0,"",I91/$I$9))) | L91: =IF(K91="","",IF($K$9="","",IF($K$9=0,"",K91/$K$9))) | N91: =IF(M91="","",IF($M$9="","",IF($M$9=0,"",M91/$M$9))) | P91: =IF(O91="","",IF($O$9="","",IF($O$9=0,"",O91/$O$9))) | R91: =IF(Q91="","",IF($Q$9="","",IF($Q$9=0,"",Q91/$Q$9))) | T91: =IF(S91="","",IF($S$9="","",IF($S$9=0,"",S91/$S$9))) | V91: =IF(U91="","",IF($U$9="","",IF($U$9=0,"",U91/$U$9))) | X91: =IF(W91="","",IF($W$9="","",IF($W$9=0,"",W91/$W$9)))

Sheet 7. MV Digital Sol
A1: WIG 7 — Incrementar el MV de Digital Solutions en $30K/mes al 1ro de mayo 2027
A2: Indicador lag: | B2: MV incremental firmado de servicios Digital Solutions (SOC y Célula), USD acumulado.
A3: De X a Y: | B3: De $0 a +$30,000 de MV mensual, antes del 1 de mayo de 2027.
A4: Dueño: | B4: Por asignar | D4: Equipo: | E4: Ventas, Del - DS
A5: Meta: | B5: 30000 | D5: Inicio: | E5: 46188 | G5: Fin: | H5: 46503
A6: Leads: | B6: Hasta 8 indicadores predictivos a la derecha. L1–L2 = apuesta principal del equipo; L3–L8 = indicadores de apoyo. Nombre (fila 8) y meta semanal (fila 9) editables en azul.
A8: Periodos: | B8: =COUNT(A11:A56) -> 46 | H8: Lead → | I8: L1. Opps SOC / Célula activas en pipeline | K8: L2. Propuestas DS presentadas | M8: L3. Demos / PoV de SOC ejecutados | O8: L4. Workshops de células de desarrollo | Q8: L5. Casos de éxito / referencias compartidas | S8: L6. Opps DS avanzadas de etapa | U8: (Disponible) | W8: (Disponible)
A9: Celdas azules = se digitan cada lunes. Celdas negras = fórmulas, no tocar. | H9: Meta → | I9: 4 | K9: 2 | M9: 1 | O9: 1 | Q9: 1 | S9: 2
A10: # | B10: Semana | C10: Meta semana | D10: Real | E10: Meta acum. | F10: Real acum. | G10: % avance | H10: Estado | I10: Real | J10: % | K10: Real | L10: % | M10: Real | N10: % | O10: Real | P10: % | Q10: Real | R10: % | S10: Real | T10: % | U10: Real | V10: % | W10: Real | X10: %
A11: 1 | B11: 46188 | C11: =$B$5/$B$8 -> 652.17391 | E11: =SUM($C$11:C11) -> 652.17391 | F11: =SUM($D$11:D11) -> 0 | G11: =IF(COUNT($D$11:D11)=0,"",F11/E11) | H11: =IF(G11="","",IF(G11>=0.95,"En meta",IF(G11>=0.8,"Riesgo","Atrasado"))) | J11: =IF(I11="","",IF($I$9="","",IF($I$9=0,"",I11/$I$9))) | L11: =IF(K11="","",IF($K$9="","",IF($K$9=0,"",K11/$K$9))) | N11: =IF(M11="","",IF($M$9="","",IF($M$9=0,"",M11/$M$9))) | P11: =IF(O11="","",IF($O$9="","",IF($O$9=0,"",O11/$O$9))) | R11: =IF(Q11="","",IF($Q$9="","",IF($Q$9=0,"",Q11/$Q$9))) | T11: =IF(S11="","",IF($S$9="","",IF($S$9=0,"",S11/$S$9))) | V11: =IF(U11="","",IF($U$9="","",IF($U$9=0,"",U11/$U$9))) | X11: =IF(W11="","",IF($W$9="","",IF($W$9=0,"",W11/$W$9)))
A12: 2 | B12: 46195 | C12: =$B$5/$B$8 -> 652.17391 | E12: =SUM($C$11:C12) -> 1304.3478 | F12: =SUM($D$11:D12) -> 0 | G12: =IF(COUNT($D$11:D12)=0,"",F12/E12) | H12: =IF(G12="","",IF(G12>=0.95,"En meta",IF(G12>=0.8,"Riesgo","Atrasado"))) | J12: =IF(I12="","",IF($I$9="","",IF($I$9=0,"",I12/$I$9))) | L12: =IF(K12="","",IF($K$9="","",IF($K$9=0,"",K12/$K$9))) | N12: =IF(M12="","",IF($M$9="","",IF($M$9=0,"",M12/$M$9))) | P12: =IF(O12="","",IF($O$9="","",IF($O$9=0,"",O12/$O$9))) | R12: =IF(Q12="","",IF($Q$9="","",IF($Q$9=0,"",Q12/$Q$9))) | T12: =IF(S12="","",IF($S$9="","",IF($S$9=0,"",S12/$S$9))) | V12: =IF(U12="","",IF($U$9="","",IF($U$9=0,"",U12/$U$9))) | X12: =IF(W12="","",IF($W$9="","",IF($W$9=0,"",W12/$W$9)))
A13: 3 | B13: 46202 | C13: =$B$5/$B$8 -> 652.17391 | E13: =SUM($C$11:C13) -> 1956.5217 | F13: =SUM($D$11:D13) -> 0 | G13: =IF(COUNT($D$11:D13)=0,"",F13/E13) | H13: =IF(G13="","",IF(G13>=0.95,"En meta",IF(G13>=0.8,"Riesgo","Atrasado"))) | J13: =IF(I13="","",IF($I$9="","",IF($I$9=0,"",I13/$I$9))) | L13: =IF(K13="","",IF($K$9="","",IF($K$9=0,"",K13/$K$9))) | N13: =IF(M13="","",IF($M$9="","",IF($M$9=0,"",M13/$M$9))) | P13: =IF(O13="","",IF($O$9="","",IF($O$9=0,"",O13/$O$9))) | R13: =IF(Q13="","",IF($Q$9="","",IF($Q$9=0,"",Q13/$Q$9))) | T13: =IF(S13="","",IF($S$9="","",IF($S$9=0,"",S13/$S$9))) | V13: =IF(U13="","",IF($U$9="","",IF($U$9=0,"",U13/$U$9))) | X13: =IF(W13="","",IF($W$9="","",IF($W$9=0,"",W13/$W$9)))
A14: 4 | B14: 46209 | C14: =$B$5/$B$8 -> 652.17391 | E14: =SUM($C$11:C14) -> 2608.6957 | F14: =SUM($D$11:D14) -> 0 | G14: =IF(COUNT($D$11:D14)=0,"",F14/E14) | H14: =IF(G14="","",IF(G14>=0.95,"En meta",IF(G14>=0.8,"Riesgo","Atrasado"))) | J14: =IF(I14="","",IF($I$9="","",IF($I$9=0,"",I14/$I$9))) | L14: =IF(K14="","",IF($K$9="","",IF($K$9=0,"",K14/$K$9))) | N14: =IF(M14="","",IF($M$9="","",IF($M$9=0,"",M14/$M$9))) | P14: =IF(O14="","",IF($O$9="","",IF($O$9=0,"",O14/$O$9))) | R14: =IF(Q14="","",IF($Q$9="","",IF($Q$9=0,"",Q14/$Q$9))) | T14: =IF(S14="","",IF($S$9="","",IF($S$9=0,"",S14/$S$9))) | V14: =IF(U14="","",IF($U$9="","",IF($U$9=0,"",U14/$U$9))) | X14: =IF(W14="","",IF($W$9="","",IF($W$9=0,"",W14/$W$9)))
A15: 5 | B15: 46216 | C15: =$B$5/$B$8 -> 652.17391 | E15: =SUM($C$11:C15) -> 3260.8696 | F15: =SUM($D$11:D15) -> 0 | G15: =IF(COUNT($D$11:D15)=0,"",F15/E15) | H15: =IF(G15="","",IF(G15>=0.95,"En meta",IF(G15>=0.8,"Riesgo","Atrasado"))) | J15: =IF(I15="","",IF($I$9="","",IF($I$9=0,"",I15/$I$9))) | L15: =IF(K15="","",IF($K$9="","",IF($K$9=0,"",K15/$K$9))) | N15: =IF(M15="","",IF($M$9="","",IF($M$9=0,"",M15/$M$9))) | P15: =IF(O15="","",IF($O$9="","",IF($O$9=0,"",O15/$O$9))) | R15: =IF(Q15="","",IF($Q$9="","",IF($Q$9=0,"",Q15/$Q$9))) | T15: =IF(S15="","",IF($S$9="","",IF($S$9=0,"",S15/$S$9))) | V15: =IF(U15="","",IF($U$9="","",IF($U$9=0,"",U15/$U$9))) | X15: =IF(W15="","",IF($W$9="","",IF($W$9=0,"",W15/$W$9)))
A16: 6 | B16: 46223 | C16: =$B$5/$B$8 -> 652.17391 | E16: =SUM($C$11:C16) -> 3913.0435 | F16: =SUM($D$11:D16) -> 0 | G16: =IF(COUNT($D$11:D16)=0,"",F16/E16) | H16: =IF(G16="","",IF(G16>=0.95,"En meta",IF(G16>=0.8,"Riesgo","Atrasado"))) | J16: =IF(I16="","",IF($I$9="","",IF($I$9=0,"",I16/$I$9))) | L16: =IF(K16="","",IF($K$9="","",IF($K$9=0,"",K16/$K$9))) | N16: =IF(M16="","",IF($M$9="","",IF($M$9=0,"",M16/$M$9))) | P16: =IF(O16="","",IF($O$9="","",IF($O$9=0,"",O16/$O$9))) | R16: =IF(Q16="","",IF($Q$9="","",IF($Q$9=0,"",Q16/$Q$9))) | T16: =IF(S16="","",IF($S$9="","",IF($S$9=0,"",S16/$S$9))) | V16: =IF(U16="","",IF($U$9="","",IF($U$9=0,"",U16/$U$9))) | X16: =IF(W16="","",IF($W$9="","",IF($W$9=0,"",W16/$W$9)))
A17: 7 | B17: 46230 | C17: =$B$5/$B$8 -> 652.17391 | E17: =SUM($C$11:C17) -> 4565.2174 | F17: =SUM($D$11:D17) -> 0 | G17: =IF(COUNT($D$11:D17)=0,"",F17/E17) | H17: =IF(G17="","",IF(G17>=0.95,"En meta",IF(G17>=0.8,"Riesgo","Atrasado"))) | J17: =IF(I17="","",IF($I$9="","",IF($I$9=0,"",I17/$I$9))) | L17: =IF(K17="","",IF($K$9="","",IF($K$9=0,"",K17/$K$9))) | N17: =IF(M17="","",IF($M$9="","",IF($M$9=0,"",M17/$M$9))) | P17: =IF(O17="","",IF($O$9="","",IF($O$9=0,"",O17/$O$9))) | R17: =IF(Q17="","",IF($Q$9="","",IF($Q$9=0,"",Q17/$Q$9))) | T17: =IF(S17="","",IF($S$9="","",IF($S$9=0,"",S17/$S$9))) | V17: =IF(U17="","",IF($U$9="","",IF($U$9=0,"",U17/$U$9))) | X17: =IF(W17="","",IF($W$9="","",IF($W$9=0,"",W17/$W$9)))
A18: 8 | B18: 46237 | C18: =$B$5/$B$8 -> 652.17391 | E18: =SUM($C$11:C18) -> 5217.3913 | F18: =SUM($D$11:D18) -> 0 | G18: =IF(COUNT($D$11:D18)=0,"",F18/E18) | H18: =IF(G18="","",IF(G18>=0.95,"En meta",IF(G18>=0.8,"Riesgo","Atrasado"))) | J18: =IF(I18="","",IF($I$9="","",IF($I$9=0,"",I18/$I$9))) | L18: =IF(K18="","",IF($K$9="","",IF($K$9=0,"",K18/$K$9))) | N18: =IF(M18="","",IF($M$9="","",IF($M$9=0,"",M18/$M$9))) | P18: =IF(O18="","",IF($O$9="","",IF($O$9=0,"",O18/$O$9))) | R18: =IF(Q18="","",IF($Q$9="","",IF($Q$9=0,"",Q18/$Q$9))) | T18: =IF(S18="","",IF($S$9="","",IF($S$9=0,"",S18/$S$9))) | V18: =IF(U18="","",IF($U$9="","",IF($U$9=0,"",U18/$U$9))) | X18: =IF(W18="","",IF($W$9="","",IF($W$9=0,"",W18/$W$9)))
A19: 9 | B19: 46244 | C19: =$B$5/$B$8 -> 652.17391 | E19: =SUM($C$11:C19) -> 5869.5652 | F19: =SUM($D$11:D19) -> 0 | G19: =IF(COUNT($D$11:D19)=0,"",F19/E19) | H19: =IF(G19="","",IF(G19>=0.95,"En meta",IF(G19>=0.8,"Riesgo","Atrasado"))) | J19: =IF(I19="","",IF($I$9="","",IF($I$9=0,"",I19/$I$9))) | L19: =IF(K19="","",IF($K$9="","",IF($K$9=0,"",K19/$K$9))) | N19: =IF(M19="","",IF($M$9="","",IF($M$9=0,"",M19/$M$9))) | P19: =IF(O19="","",IF($O$9="","",IF($O$9=0,"",O19/$O$9))) | R19: =IF(Q19="","",IF($Q$9="","",IF($Q$9=0,"",Q19/$Q$9))) | T19: =IF(S19="","",IF($S$9="","",IF($S$9=0,"",S19/$S$9))) | V19: =IF(U19="","",IF($U$9="","",IF($U$9=0,"",U19/$U$9))) | X19: =IF(W19="","",IF($W$9="","",IF($W$9=0,"",W19/$W$9)))
A20: 10 | B20: 46251 | C20: =$B$5/$B$8 -> 652.17391 | E20: =SUM($C$11:C20) -> 6521.7391 | F20: =SUM($D$11:D20) -> 0 | G20: =IF(COUNT($D$11:D20)=0,"",F20/E20) | H20: =IF(G20="","",IF(G20>=0.95,"En meta",IF(G20>=0.8,"Riesgo","Atrasado"))) | J20: =IF(I20="","",IF($I$9="","",IF($I$9=0,"",I20/$I$9))) | L20: =IF(K20="","",IF($K$9="","",IF($K$9=0,"",K20/$K$9))) | N20: =IF(M20="","",IF($M$9="","",IF($M$9=0,"",M20/$M$9))) | P20: =IF(O20="","",IF($O$9="","",IF($O$9=0,"",O20/$O$9))) | R20: =IF(Q20="","",IF($Q$9="","",IF($Q$9=0,"",Q20/$Q$9))) | T20: =IF(S20="","",IF($S$9="","",IF($S$9=0,"",S20/$S$9))) | V20: =IF(U20="","",IF($U$9="","",IF($U$9=0,"",U20/$U$9))) | X20: =IF(W20="","",IF($W$9="","",IF($W$9=0,"",W20/$W$9)))
A21: 11 | B21: 46258 | C21: =$B$5/$B$8 -> 652.17391 | E21: =SUM($C$11:C21) -> 7173.913 | F21: =SUM($D$11:D21) -> 0 | G21: =IF(COUNT($D$11:D21)=0,"",F21/E21) | H21: =IF(G21="","",IF(G21>=0.95,"En meta",IF(G21>=0.8,"Riesgo","Atrasado"))) | J21: =IF(I21="","",IF($I$9="","",IF($I$9=0,"",I21/$I$9))) | L21: =IF(K21="","",IF($K$9="","",IF($K$9=0,"",K21/$K$9))) | N21: =IF(M21="","",IF($M$9="","",IF($M$9=0,"",M21/$M$9))) | P21: =IF(O21="","",IF($O$9="","",IF($O$9=0,"",O21/$O$9))) | R21: =IF(Q21="","",IF($Q$9="","",IF($Q$9=0,"",Q21/$Q$9))) | T21: =IF(S21="","",IF($S$9="","",IF($S$9=0,"",S21/$S$9))) | V21: =IF(U21="","",IF($U$9="","",IF($U$9=0,"",U21/$U$9))) | X21: =IF(W21="","",IF($W$9="","",IF($W$9=0,"",W21/$W$9)))
A22: 12 | B22: 46265 | C22: =$B$5/$B$8 -> 652.17391 | E22: =SUM($C$11:C22) -> 7826.087 | F22: =SUM($D$11:D22) -> 0 | G22: =IF(COUNT($D$11:D22)=0,"",F22/E22) | H22: =IF(G22="","",IF(G22>=0.95,"En meta",IF(G22>=0.8,"Riesgo","Atrasado"))) | J22: =IF(I22="","",IF($I$9="","",IF($I$9=0,"",I22/$I$9))) | L22: =IF(K22="","",IF($K$9="","",IF($K$9=0,"",K22/$K$9))) | N22: =IF(M22="","",IF($M$9="","",IF($M$9=0,"",M22/$M$9))) | P22: =IF(O22="","",IF($O$9="","",IF($O$9=0,"",O22/$O$9))) | R22: =IF(Q22="","",IF($Q$9="","",IF($Q$9=0,"",Q22/$Q$9))) | T22: =IF(S22="","",IF($S$9="","",IF($S$9=0,"",S22/$S$9))) | V22: =IF(U22="","",IF($U$9="","",IF($U$9=0,"",U22/$U$9))) | X22: =IF(W22="","",IF($W$9="","",IF($W$9=0,"",W22/$W$9)))
... A56: 46 | B56: 46503 | C56: =$B$5/$B$8 -> 652.17391 | E56: =SUM($C$11:C56) -> 30000 | F56: =SUM($D$11:D56) -> 0 | G56: =IF(COUNT($D$11:D56)=0,"",F56/E56) | H56: =IF(G56="","",IF(G56>=0.95,"En meta",IF(G56>=0.8,"Riesgo","Atrasado"))) | J56: =IF(I56="","",IF($I$9="","",IF($I$9=0,"",I56/$I$9))) | L56: =IF(K56="","",IF($K$9="","",IF($K$9=0,"",K56/$K$9))) | N56: =IF(M56="","",IF($M$9="","",IF($M$9=0,"",M56/$M$9))) | P56: =IF(O56="","",IF($O$9="","",IF($O$9=0,"",O56/$O$9))) | R56: =IF(Q56="","",IF($Q$9="","",IF($Q$9=0,"",Q56/$Q$9))) | T56: =IF(S56="","",IF($S$9="","",IF($S$9=0,"",S56/$S$9))) | V56: =IF(U56="","",IF($U$9="","",IF($U$9=0,"",U56/$U$9))) | X56: =IF(W56="","",IF($W$9="","",IF($W$9=0,"",W56/$W$9)))

Sheet 8. GP 16%
A1: WIG 8 — Lograr un GP consolidado de 16% en el 2027
A2: Indicador lag: | B2: GP consolidado del mes (%).
A3: De X a Y: | B3: De GP actual a 16% consolidado sostenido en 2027.
A4: Dueño: | B4: Por asignar | D4: Equipo: | E4: Finanzas (todas las áreas aportan)
A5: Meta: | B5: 0.16 | D5: Inicio: | E5: 46204 | G5: Fin: | H5: 46722
A6: Leads: | B6: Hasta 8 indicadores predictivos a la derecha. L1–L2 = apuesta principal del equipo; L3–L8 = indicadores de apoyo. Nombre (fila 8) y meta mensual (fila 9) editables en azul.
A8: Periodos: | B8: =COUNT(A11:A28) -> 18 | H8: Lead → | I8: L1. % distribuciones del mes vs plan de baja distribución | K8: L2. % reservas (inventario + ITA + IR) bajo el tope del plan | M8: L3. % negocios cotizados con GP ≥ margen mínimo | O8: L4. Acciones de recuperación de margen ejecutadas | Q8: L5. Revisiones de pricing realizadas en el mes | S8: L6. % proyectos con revisión de rentabilidad mensual | U8: (Disponible) | W8: (Disponible)
A9: Celdas azules = se digitan cada lunes. Celdas negras = fórmulas, no tocar. | H9: Meta → | I9: 1 | K9: 1 | M9: 1 | O9: 2 | Q9: 4 | S9: 1
A10: # | B10: Mes | C10: Meta | D10: Real | G10: Brecha vs meta | H10: Estado | I10: Real | J10: % | K10: Real | L10: % | M10: Real | N10: % | O10: Real | P10: % | Q10: Real | R10: % | S10: Real | T10: % | U10: Real | V10: % | W10: Real | X10: %
A11: 1 | B11: 46204 | C11: =$B$5 -> 0.16 | G11: =IF(D11="","",D11-C11) | H11: =IF(D11="","",IF(D11>=C11,"En meta",IF(D11>=C11-0.01,"Riesgo","Atrasado"))) | J11: =IF(I11="","",IF($I$9="","",IF($I$9=0,"",I11/$I$9))) | L11: =IF(K11="","",IF($K$9="","",IF($K$9=0,"",K11/$K$9))) | N11: =IF(M11="","",IF($M$9="","",IF($M$9=0,"",M11/$M$9))) | P11: =IF(O11="","",IF($O$9="","",IF($O$9=0,"",O11/$O$9))) | R11: =IF(Q11="","",IF($Q$9="","",IF($Q$9=0,"",Q11/$Q$9))) | T11: =IF(S11="","",IF($S$9="","",IF($S$9=0,"",S11/$S$9))) | V11: =IF(U11="","",IF($U$9="","",IF($U$9=0,"",U11/$U$9))) | X11: =IF(W11="","",IF($W$9="","",IF($W$9=0,"",W11/$W$9)))
A12: 2 | B12: 46235 | C12: =$B$5 -> 0.16 | G12: =IF(D12="","",D12-C12) | H12: =IF(D12="","",IF(D12>=C12,"En meta",IF(D12>=C12-0.01,"Riesgo","Atrasado"))) | J12: =IF(I12="","",IF($I$9="","",IF($I$9=0,"",I12/$I$9))) | L12: =IF(K12="","",IF($K$9="","",IF($K$9=0,"",K12/$K$9))) | N12: =IF(M12="","",IF($M$9="","",IF($M$9=0,"",M12/$M$9))) | P12: =IF(O12="","",IF($O$9="","",IF($O$9=0,"",O12/$O$9))) | R12: =IF(Q12="","",IF($Q$9="","",IF($Q$9=0,"",Q12/$Q$9))) | T12: =IF(S12="","",IF($S$9="","",IF($S$9=0,"",S12/$S$9))) | V12: =IF(U12="","",IF($U$9="","",IF($U$9=0,"",U12/$U$9))) | X12: =IF(W12="","",IF($W$9="","",IF($W$9=0,"",W12/$W$9)))
A13: 3 | B13: 46266 | C13: =$B$5 -> 0.16 | G13: =IF(D13="","",D13-C13) | H13: =IF(D13="","",IF(D13>=C13,"En meta",IF(D13>=C13-0.01,"Riesgo","Atrasado"))) | J13: =IF(I13="","",IF($I$9="","",IF($I$9=0,"",I13/$I$9))) | L13: =IF(K13="","",IF($K$9="","",IF($K$9=0,"",K13/$K$9))) | N13: =IF(M13="","",IF($M$9="","",IF($M$9=0,"",M13/$M$9))) | P13: =IF(O13="","",IF($O$9="","",IF($O$9=0,"",O13/$O$9))) | R13: =IF(Q13="","",IF($Q$9="","",IF($Q$9=0,"",Q13/$Q$9))) | T13: =IF(S13="","",IF($S$9="","",IF($S$9=0,"",S13/$S$9))) | V13: =IF(U13="","",IF($U$9="","",IF($U$9=0,"",U13/$U$9))) | X13: =IF(W13="","",IF($W$9="","",IF($W$9=0,"",W13/$W$9)))
A14: 4 | B14: 46296 | C14: =$B$5 -> 0.16 | G14: =IF(D14="","",D14-C14) | H14: =IF(D14="","",IF(D14>=C14,"En meta",IF(D14>=C14-0.01,"Riesgo","Atrasado"))) | J14: =IF(I14="","",IF($I$9="","",IF($I$9=0,"",I14/$I$9))) | L14: =IF(K14="","",IF($K$9="","",IF($K$9=0,"",K14/$K$9))) | N14: =IF(M14="","",IF($M$9="","",IF($M$9=0,"",M14/$M$9))) | P14: =IF(O14="","",IF($O$9="","",IF($O$9=0,"",O14/$O$9))) | R14: =IF(Q14="","",IF($Q$9="","",IF($Q$9=0,"",Q14/$Q$9))) | T14: =IF(S14="","",IF($S$9="","",IF($S$9=0,"",S14/$S$9))) | V14: =IF(U14="","",IF($U$9="","",IF($U$9=0,"",U14/$U$9))) | X14: =IF(W14="","",IF($W$9="","",IF($W$9=0,"",W14/$W$9)))
A15: 5 | B15: 46327 | C15: =$B$5 -> 0.16 | G15: =IF(D15="","",D15-C15) | H15: =IF(D15="","",IF(D15>=C15,"En meta",IF(D15>=C15-0.01,"Riesgo","Atrasado"))) | J15: =IF(I15="","",IF($I$9="","",IF($I$9=0,"",I15/$I$9))) | L15: =IF(K15="","",IF($K$9="","",IF($K$9=0,"",K15/$K$9))) | N15: =IF(M15="","",IF($M$9="","",IF($M$9=0,"",M15/$M$9))) | P15: =IF(O15="","",IF($O$9="","",IF($O$9=0,"",O15/$O$9))) | R15: =IF(Q15="","",IF($Q$9="","",IF($Q$9=0,"",Q15/$Q$9))) | T15: =IF(S15="","",IF($S$9="","",IF($S$9=0,"",S15/$S$9))) | V15: =IF(U15="","",IF($U$9="","",IF($U$9=0,"",U15/$U$9))) | X15: =IF(W15="","",IF($W$9="","",IF($W$9=0,"",W15/$W$9)))
A16: 6 | B16: 46357 | C16: =$B$5 -> 0.16 | G16: =IF(D16="","",D16-C16) | H16: =IF(D16="","",IF(D16>=C16,"En meta",IF(D16>=C16-0.01,"Riesgo","Atrasado"))) | J16: =IF(I16="","",IF($I$9="","",IF($I$9=0,"",I16/$I$9))) | L16: =IF(K16="","",IF($K$9="","",IF($K$9=0,"",K16/$K$9))) | N16: =IF(M16="","",IF($M$9="","",IF($M$9=0,"",M16/$M$9))) | P16: =IF(O16="","",IF($O$9="","",IF($O$9=0,"",O16/$O$9))) | R16: =IF(Q16="","",IF($Q$9="","",IF($Q$9=0,"",Q16/$Q$9))) | T16: =IF(S16="","",IF($S$9="","",IF($S$9=0,"",S16/$S$9))) | V16: =IF(U16="","",IF($U$9="","",IF($U$9=0,"",U16/$U$9))) | X16: =IF(W16="","",IF($W$9="","",IF($W$9=0,"",W16/$W$9)))
A17: 7 | B17: 46388 | C17: =$B$5 -> 0.16 | G17: =IF(D17="","",D17-C17) | H17: =IF(D17="","",IF(D17>=C17,"En meta",IF(D17>=C17-0.01,"Riesgo","Atrasado"))) | J17: =IF(I17="","",IF($I$9="","",IF($I$9=0,"",I17/$I$9))) | L17: =IF(K17="","",IF($K$9="","",IF($K$9=0,"",K17/$K$9))) | N17: =IF(M17="","",IF($M$9="","",IF($M$9=0,"",M17/$M$9))) | P17: =IF(O17="","",IF($O$9="","",IF($O$9=0,"",O17/$O$9))) | R17: =IF(Q17="","",IF($Q$9="","",IF($Q$9=0,"",Q17/$Q$9))) | T17: =IF(S17="","",IF($S$9="","",IF($S$9=0,"",S17/$S$9))) | V17: =IF(U17="","",IF($U$9="","",IF($U$9=0,"",U17/$U$9))) | X17: =IF(W17="","",IF($W$9="","",IF($W$9=0,"",W17/$W$9)))
A18: 8 | B18: 46419 | C18: =$B$5 -> 0.16 | G18: =IF(D18="","",D18-C18) | H18: =IF(D18="","",IF(D18>=C18,"En meta",IF(D18>=C18-0.01,"Riesgo","Atrasado"))) | J18: =IF(I18="","",IF($I$9="","",IF($I$9=0,"",I18/$I$9))) | L18: =IF(K18="","",IF($K$9="","",IF($K$9=0,"",K18/$K$9))) | N18: =IF(M18="","",IF($M$9="","",IF($M$9=0,"",M18/$M$9))) | P18: =IF(O18="","",IF($O$9="","",IF($O$9=0,"",O18/$O$9))) | R18: =IF(Q18="","",IF($Q$9="","",IF($Q$9=0,"",Q18/$Q$9))) | T18: =IF(S18="","",IF($S$9="","",IF($S$9=0,"",S18/$S$9))) | V18: =IF(U18="","",IF($U$9="","",IF($U$9=0,"",U18/$U$9))) | X18: =IF(W18="","",IF($W$9="","",IF($W$9=0,"",W18/$W$9)))
A19: 9 | B19: 46447 | C19: =$B$5 -> 0.16 | G19: =IF(D19="","",D19-C19) | H19: =IF(D19="","",IF(D19>=C19,"En meta",IF(D19>=C19-0.01,"Riesgo","Atrasado"))) | J19: =IF(I19="","",IF($I$9="","",IF($I$9=0,"",I19/$I$9))) | L19: =IF(K19="","",IF($K$9="","",IF($K$9=0,"",K19/$K$9))) | N19: =IF(M19="","",IF($M$9="","",IF($M$9=0,"",M19/$M$9))) | P19: =IF(O19="","",IF($O$9="","",IF($O$9=0,"",O19/$O$9))) | R19: =IF(Q19="","",IF($Q$9="","",IF($Q$9=0,"",Q19/$Q$9))) | T19: =IF(S19="","",IF($S$9="","",IF($S$9=0,"",S19/$S$9))) | V19: =IF(U19="","",IF($U$9="","",IF($U$9=0,"",U19/$U$9))) | X19: =IF(W19="","",IF($W$9="","",IF($W$9=0,"",W19/$W$9)))
A20: 10 | B20: 46478 | C20: =$B$5 -> 0.16 | G20: =IF(D20="","",D20-C20) | H20: =IF(D20="","",IF(D20>=C20,"En meta",IF(D20>=C20-0.01,"Riesgo","Atrasado"))) | J20: =IF(I20="","",IF($I$9="","",IF($I$9=0,"",I20/$I$9))) | L20: =IF(K20="","",IF($K$9="","",IF($K$9=0,"",K20/$K$9))) | N20: =IF(M20="","",IF($M$9="","",IF($M$9=0,"",M20/$M$9))) | P20: =IF(O20="","",IF($O$9="","",IF($O$9=0,"",O20/$O$9))) | R20: =IF(Q20="","",IF($Q$9="","",IF($Q$9=0,"",Q20/$Q$9))) | T20: =IF(S20="","",IF($S$9="","",IF($S$9=0,"",S20/$S$9))) | V20: =IF(U20="","",IF($U$9="","",IF($U$9=0,"",U20/$U$9))) | X20: =IF(W20="","",IF($W$9="","",IF($W$9=0,"",W20/$W$9)))
A21: 11 | B21: 46508 | C21: =$B$5 -> 0.16 | G21: =IF(D21="","",D21-C21) | H21: =IF(D21="","",IF(D21>=C21,"En meta",IF(D21>=C21-0.01,"Riesgo","Atrasado"))) | J21: =IF(I21="","",IF($I$9="","",IF($I$9=0,"",I21/$I$9))) | L21: =IF(K21="","",IF($K$9="","",IF($K$9=0,"",K21/$K$9))) | N21: =IF(M21="","",IF($M$9="","",IF($M$9=0,"",M21/$M$9))) | P21: =IF(O21="","",IF($O$9="","",IF($O$9=0,"",O21/$O$9))) | R21: =IF(Q21="","",IF($Q$9="","",IF($Q$9=0,"",Q21/$Q$9))) | T21: =IF(S21="","",IF($S$9="","",IF($S$9=0,"",S21/$S$9))) | V21: =IF(U21="","",IF($U$9="","",IF($U$9=0,"",U21/$U$9))) | X21: =IF(W21="","",IF($W$9="","",IF($W$9=0,"",W21/$W$9)))
A22: 12 | B22: 46539 | C22: =$B$5 -> 0.16 | G22: =IF(D22="","",D22-C22) | H22: =IF(D22="","",IF(D22>=C22,"En meta",IF(D22>=C22-0.01,"Riesgo","Atrasado"))) | J22: =IF(I22="","",IF($I$9="","",IF($I$9=0,"",I22/$I$9))) | L22: =IF(K22="","",IF($K$9="","",IF($K$9=0,"",K22/$K$9))) | N22: =IF(M22="","",IF($M$9="","",IF($M$9=0,"",M22/$M$9))) | P22: =IF(O22="","",IF($O$9="","",IF($O$9=0,"",O22/$O$9))) | R22: =IF(Q22="","",IF($Q$9="","",IF($Q$9=0,"",Q22/$Q$9))) | T22: =IF(S22="","",IF($S$9="","",IF($S$9=0,"",S22/$S$9))) | V22: =IF(U22="","",IF($U$9="","",IF($U$9=0,"",U22/$U$9))) | X22: =IF(W22="","",IF($W$9="","",IF($W$9=0,"",W22/$W$9)))
... A28: 18 | B28: 46722 | C28: =$B$5 -> 0.16 | G28: =IF(D28="","",D28-C28) | H28: =IF(D28="","",IF(D28>=C28,"En meta",IF(D28>=C28-0.01,"Riesgo","Atrasado"))) | J28: =IF(I28="","",IF($I$9="","",IF($I$9=0,"",I28/$I$9))) | L28: =IF(K28="","",IF($K$9="","",IF($K$9=0,"",K28/$K$9))) | N28: =IF(M28="","",IF($M$9="","",IF($M$9=0,"",M28/$M$9))) | P28: =IF(O28="","",IF($O$9="","",IF($O$9=0,"",O28/$O$9))) | R28: =IF(Q28="","",IF($Q$9="","",IF($Q$9=0,"",Q28/$Q$9))) | T28: =IF(S28="","",IF($S$9="","",IF($S$9=0,"",S28/$S$9))) | V28: =IF(U28="","",IF($U$9="","",IF($U$9=0,"",U28/$U$9))) | X28: =IF(W28="","",IF($W$9="","",IF($W$9=0,"",W28/$W$9)))

Sheet 9. CSAT
A1: WIG 9 — Incrementar el CSAT de X a Y, sosteniéndolo 4 meses consecutivos
A2: Indicador lag: | B2: CSAT del mes (puntaje de encuestas de satisfacción).
A3: De X a Y: | B3: De X a Y, con 4 meses consecutivos en la meta. (Definir X y Y en la celda Meta)
A4: Dueño: | B4: Por asignar | D4: Equipo: | E4: Customer Success (todas las áreas de entrega aportan)
A5: Meta: | B5: 4.5 | D5: Inicio: | E5: 46204 | G5: Fin: | H5: 46722
A6: Leads: | B6: Hasta 8 indicadores predictivos a la derecha. L1–L2 = apuesta principal del equipo; L3–L8 = indicadores de apoyo. Nombre (fila 8) y meta mensual (fila 9) editables en azul.
A8: Periodos: | B8: =COUNT(A11:A28) -> 18 | H8: Lead → | I8: L1. % encuestas CSAT enviadas y respondidas | K8: L2. QBRs / touchpoints de CS ejecutados | M8: L3. % detractores con plan de acción en ≤5 días | O8: L4. % casos críticos resueltos dentro del SLA | Q8: L5. Llamadas proactivas de CSM en el mes | S8: L6. Promotores contactados para referencia | U8: (Disponible) | W8: (Disponible)
A9: Celdas azules = se digitan cada lunes. Celdas negras = fórmulas, no tocar. | H9: Meta → | I9: 0.6 | K9: 8 | M9: 1 | O9: 0.95 | Q9: 12 | S9: 3
A10: # | B10: Mes | C10: Meta | D10: Real | G10: Brecha vs meta | H10: Estado | I10: Real | J10: % | K10: Real | L10: % | M10: Real | N10: % | O10: Real | P10: % | Q10: Real | R10: % | S10: Real | T10: % | U10: Real | V10: % | W10: Real | X10: %
A11: 1 | B11: 46204 | C11: =$B$5 -> 4.5 | G11: =IF(D11="","",D11-C11) | H11: =IF(D11="","",IF(D11>=C11,"En meta",IF(D11>=C11-0.3,"Riesgo","Atrasado"))) | J11: =IF(I11="","",IF($I$9="","",IF($I$9=0,"",I11/$I$9))) | L11: =IF(K11="","",IF($K$9="","",IF($K$9=0,"",K11/$K$9))) | N11: =IF(M11="","",IF($M$9="","",IF($M$9=0,"",M11/$M$9))) | P11: =IF(O11="","",IF($O$9="","",IF($O$9=0,"",O11/$O$9))) | R11: =IF(Q11="","",IF($Q$9="","",IF($Q$9=0,"",Q11/$Q$9))) | T11: =IF(S11="","",IF($S$9="","",IF($S$9=0,"",S11/$S$9))) | V11: =IF(U11="","",IF($U$9="","",IF($U$9=0,"",U11/$U$9))) | X11: =IF(W11="","",IF($W$9="","",IF($W$9=0,"",W11/$W$9)))
A12: 2 | B12: 46235 | C12: =$B$5 -> 4.5 | G12: =IF(D12="","",D12-C12) | H12: =IF(D12="","",IF(D12>=C12,"En meta",IF(D12>=C12-0.3,"Riesgo","Atrasado"))) | J12: =IF(I12="","",IF($I$9="","",IF($I$9=0,"",I12/$I$9))) | L12: =IF(K12="","",IF($K$9="","",IF($K$9=0,"",K12/$K$9))) | N12: =IF(M12="","",IF($M$9="","",IF($M$9=0,"",M12/$M$9))) | P12: =IF(O12="","",IF($O$9="","",IF($O$9=0,"",O12/$O$9))) | R12: =IF(Q12="","",IF($Q$9="","",IF($Q$9=0,"",Q12/$Q$9))) | T12: =IF(S12="","",IF($S$9="","",IF($S$9=0,"",S12/$S$9))) | V12: =IF(U12="","",IF($U$9="","",IF($U$9=0,"",U12/$U$9))) | X12: =IF(W12="","",IF($W$9="","",IF($W$9=0,"",W12/$W$9)))
A13: 3 | B13: 46266 | C13: =$B$5 -> 4.5 | G13: =IF(D13="","",D13-C13) | H13: =IF(D13="","",IF(D13>=C13,"En meta",IF(D13>=C13-0.3,"Riesgo","Atrasado"))) | J13: =IF(I13="","",IF($I$9="","",IF($I$9=0,"",I13/$I$9))) | L13: =IF(K13="","",IF($K$9="","",IF($K$9=0,"",K13/$K$9))) | N13: =IF(M13="","",IF($M$9="","",IF($M$9=0,"",M13/$M$9))) | P13: =IF(O13="","",IF($O$9="","",IF($O$9=0,"",O13/$O$9))) | R13: =IF(Q13="","",IF($Q$9="","",IF($Q$9=0,"",Q13/$Q$9))) | T13: =IF(S13="","",IF($S$9="","",IF($S$9=0,"",S13/$S$9))) | V13: =IF(U13="","",IF($U$9="","",IF($U$9=0,"",U13/$U$9))) | X13: =IF(W13="","",IF($W$9="","",IF($W$9=0,"",W13/$W$9)))
A14: 4 | B14: 46296 | C14: =$B$5 -> 4.5 | G14: =IF(D14="","",D14-C14) | H14: =IF(D14="","",IF(D14>=C14,"En meta",IF(D14>=C14-0.3,"Riesgo","Atrasado"))) | J14: =IF(I14="","",IF($I$9="","",IF($I$9=0,"",I14/$I$9))) | L14: =IF(K14="","",IF($K$9="","",IF($K$9=0,"",K14/$K$9))) | N14: =IF(M14="","",IF($M$9="","",IF($M$9=0,"",M14/$M$9))) | P14: =IF(O14="","",IF($O$9="","",IF($O$9=0,"",O14/$O$9))) | R14: =IF(Q14="","",IF($Q$9="","",IF($Q$9=0,"",Q14/$Q$9))) | T14: =IF(S14="","",IF($S$9="","",IF($S$9=0,"",S14/$S$9))) | V14: =IF(U14="","",IF($U$9="","",IF($U$9=0,"",U14/$U$9))) | X14: =IF(W14="","",IF($W$9="","",IF($W$9=0,"",W14/$W$9)))
A15: 5 | B15: 46327 | C15: =$B$5 -> 4.5 | G15: =IF(D15="","",D15-C15) | H15: =IF(D15="","",IF(D15>=C15,"En meta",IF(D15>=C15-0.3,"Riesgo","Atrasado"))) | J15: =IF(I15="","",IF($I$9="","",IF($I$9=0,"",I15/$I$9))) | L15: =IF(K15="","",IF($K$9="","",IF($K$9=0,"",K15/$K$9))) | N15: =IF(M15="","",IF($M$9="","",IF($M$9=0,"",M15/$M$9))) | P15: =IF(O15="","",IF($O$9="","",IF($O$9=0,"",O15/$O$9))) | R15: =IF(Q15="","",IF($Q$9="","",IF($Q$9=0,"",Q15/$Q$9))) | T15: =IF(S15="","",IF($S$9="","",IF($S$9=0,"",S15/$S$9))) | V15: =IF(U15="","",IF($U$9="","",IF($U$9=0,"",U15/$U$9))) | X15: =IF(W15="","",IF($W$9="","",IF($W$9=0,"",W15/$W$9)))
A16: 6 | B16: 46357 | C16: =$B$5 -> 4.5 | G16: =IF(D16="","",D16-C16) | H16: =IF(D16="","",IF(D16>=C16,"En meta",IF(D16>=C16-0.3,"Riesgo","Atrasado"))) | J16: =IF(I16="","",IF($I$9="","",IF($I$9=0,"",I16/$I$9))) | L16: =IF(K16="","",IF($K$9="","",IF($K$9=0,"",K16/$K$9))) | N16: =IF(M16="","",IF($M$9="","",IF($M$9=0,"",M16/$M$9))) | P16: =IF(O16="","",IF($O$9="","",IF($O$9=0,"",O16/$O$9))) | R16: =IF(Q16="","",IF($Q$9="","",IF($Q$9=0,"",Q16/$Q$9))) | T16: =IF(S16="","",IF($S$9="","",IF($S$9=0,"",S16/$S$9))) | V16: =IF(U16="","",IF($U$9="","",IF($U$9=0,"",U16/$U$9))) | X16: =IF(W16="","",IF($W$9="","",IF($W$9=0,"",W16/$W$9)))
A17: 7 | B17: 46388 | C17: =$B$5 -> 4.5 | G17: =IF(D17="","",D17-C17) | H17: =IF(D17="","",IF(D17>=C17,"En meta",IF(D17>=C17-0.3,"Riesgo","Atrasado"))) | J17: =IF(I17="","",IF($I$9="","",IF($I$9=0,"",I17/$I$9))) | L17: =IF(K17="","",IF($K$9="","",IF($K$9=0,"",K17/$K$9))) | N17: =IF(M17="","",IF($M$9="","",IF($M$9=0,"",M17/$M$9))) | P17: =IF(O17="","",IF($O$9="","",IF($O$9=0,"",O17/$O$9))) | R17: =IF(Q17="","",IF($Q$9="","",IF($Q$9=0,"",Q17/$Q$9))) | T17: =IF(S17="","",IF($S$9="","",IF($S$9=0,"",S17/$S$9))) | V17: =IF(U17="","",IF($U$9="","",IF($U$9=0,"",U17/$U$9))) | X17: =IF(W17="","",IF($W$9="","",IF($W$9=0,"",W17/$W$9)))
A18: 8 | B18: 46419 | C18: =$B$5 -> 4.5 | G18: =IF(D18="","",D18-C18) | H18: =IF(D18="","",IF(D18>=C18,"En meta",IF(D18>=C18-0.3,"Riesgo","Atrasado"))) | J18: =IF(I18="","",IF($I$9="","",IF($I$9=0,"",I18/$I$9))) | L18: =IF(K18="","",IF($K$9="","",IF($K$9=0,"",K18/$K$9))) | N18: =IF(M18="","",IF($M$9="","",IF($M$9=0,"",M18/$M$9))) | P18: =IF(O18="","",IF($O$9="","",IF($O$9=0,"",O18/$O$9))) | R18: =IF(Q18="","",IF($Q$9="","",IF($Q$9=0,"",Q18/$Q$9))) | T18: =IF(S18="","",IF($S$9="","",IF($S$9=0,"",S18/$S$9))) | V18: =IF(U18="","",IF($U$9="","",IF($U$9=0,"",U18/$U$9))) | X18: =IF(W18="","",IF($W$9="","",IF($W$9=0,"",W18/$W$9)))
A19: 9 | B19: 46447 | C19: =$B$5 -> 4.5 | G19: =IF(D19="","",D19-C19) | H19: =IF(D19="","",IF(D19>=C19,"En meta",IF(D19>=C19-0.3,"Riesgo","Atrasado"))) | J19: =IF(I19="","",IF($I$9="","",IF($I$9=0,"",I19/$I$9))) | L19: =IF(K19="","",IF($K$9="","",IF($K$9=0,"",K19/$K$9))) | N19: =IF(M19="","",IF($M$9="","",IF($M$9=0,"",M19/$M$9))) | P19: =IF(O19="","",IF($O$9="","",IF($O$9=0,"",O19/$O$9))) | R19: =IF(Q19="","",IF($Q$9="","",IF($Q$9=0,"",Q19/$Q$9))) | T19: =IF(S19="","",IF($S$9="","",IF($S$9=0,"",S19/$S$9))) | V19: =IF(U19="","",IF($U$9="","",IF($U$9=0,"",U19/$U$9))) | X19: =IF(W19="","",IF($W$9="","",IF($W$9=0,"",W19/$W$9)))
A20: 10 | B20: 46478 | C20: =$B$5 -> 4.5 | G20: =IF(D20="","",D20-C20) | H20: =IF(D20="","",IF(D20>=C20,"En meta",IF(D20>=C20-0.3,"Riesgo","Atrasado"))) | J20: =IF(I20="","",IF($I$9="","",IF($I$9=0,"",I20/$I$9))) | L20: =IF(K20="","",IF($K$9="","",IF($K$9=0,"",K20/$K$9))) | N20: =IF(M20="","",IF($M$9="","",IF($M$9=0,"",M20/$M$9))) | P20: =IF(O20="","",IF($O$9="","",IF($O$9=0,"",O20/$O$9))) | R20: =IF(Q20="","",IF($Q$9="","",IF($Q$9=0,"",Q20/$Q$9))) | T20: =IF(S20="","",IF($S$9="","",IF($S$9=0,"",S20/$S$9))) | V20: =IF(U20="","",IF($U$9="","",IF($U$9=0,"",U20/$U$9))) | X20: =IF(W20="","",IF($W$9="","",IF($W$9=0,"",W20/$W$9)))
A21: 11 | B21: 46508 | C21: =$B$5 -> 4.5 | G21: =IF(D21="","",D21-C21) | H21: =IF(D21="","",IF(D21>=C21,"En meta",IF(D21>=C21-0.3,"Riesgo","Atrasado"))) | J21: =IF(I21="","",IF($I$9="","",IF($I$9=0,"",I21/$I$9))) | L21: =IF(K21="","",IF($K$9="","",IF($K$9=0,"",K21/$K$9))) | N21: =IF(M21="","",IF($M$9="","",IF($M$9=0,"",M21/$M$9))) | P21: =IF(O21="","",IF($O$9="","",IF($O$9=0,"",O21/$O$9))) | R21: =IF(Q21="","",IF($Q$9="","",IF($Q$9=0,"",Q21/$Q$9))) | T21: =IF(S21="","",IF($S$9="","",IF($S$9=0,"",S21/$S$9))) | V21: =IF(U21="","",IF($U$9="","",IF($U$9=0,"",U21/$U$9))) | X21: =IF(W21="","",IF($W$9="","",IF($W$9=0,"",W21/$W$9)))
A22: 12 | B22: 46539 | C22: =$B$5 -> 4.5 | G22: =IF(D22="","",D22-C22) | H22: =IF(D22="","",IF(D22>=C22,"En meta",IF(D22>=C22-0.3,"Riesgo","Atrasado"))) | J22: =IF(I22="","",IF($I$9="","",IF($I$9=0,"",I22/$I$9))) | L22: =IF(K22="","",IF($K$9="","",IF($K$9=0,"",K22/$K$9))) | N22: =IF(M22="","",IF($M$9="","",IF($M$9=0,"",M22/$M$9))) | P22: =IF(O22="","",IF($O$9="","",IF($O$9=0,"",O22/$O$9))) | R22: =IF(Q22="","",IF($Q$9="","",IF($Q$9=0,"",Q22/$Q$9))) | T22: =IF(S22="","",IF($S$9="","",IF($S$9=0,"",S22/$S$9))) | V22: =IF(U22="","",IF($U$9="","",IF($U$9=0,"",U22/$U$9))) | X22: =IF(W22="","",IF($W$9="","",IF($W$9=0,"",W22/$W$9)))
... A28: 18 | B28: 46722 | C28: =$B$5 -> 4.5 | G28: =IF(D28="","",D28-C28) | H28: =IF(D28="","",IF(D28>=C28,"En meta",IF(D28>=C28-0.3,"Riesgo","Atrasado"))) | J28: =IF(I28="","",IF($I$9="","",IF($I$9=0,"",I28/$I$9))) | L28: =IF(K28="","",IF($K$9="","",IF($K$9=0,"",K28/$K$9))) | N28: =IF(M28="","",IF($M$9="","",IF($M$9=0,"",M28/$M$9))) | P28: =IF(O28="","",IF($O$9="","",IF($O$9=0,"",O28/$O$9))) | R28: =IF(Q28="","",IF($Q$9="","",IF($Q$9=0,"",Q28/$Q$9))) | T28: =IF(S28="","",IF($S$9="","",IF($S$9=0,"",S28/$S$9))) | V28: =IF(U28="","",IF($U$9="","",IF($U$9=0,"",U28/$U$9))) | X28: =IF(W28="","",IF($W$9="","",IF($W$9=0,"",W28/$W$9)))

Sheet 10. Apalancamiento
A1: WIG 10 — Sostener costos locales planos mientras crece el ingreso (apalancamiento operativo)
A2: Indicador lag: | B2: Costo indirecto local + OREX del mes como % del ingreso del mes (objetivo: que BAJE al crecer ventas).
A3: De X a Y: | B3: De ~13% (local+OREX / ingreso) hacia ≤9% sostenido, manteniendo el costo local en valor absoluto plano mientras el ingreso crece.
A4: Dueño: | B4: Por asignar | D4: Equipo: | E4: Finanzas, Customer Success, todas las áreas locales
A5: Meta: | B5: 0.09 | D5: Inicio: | E5: 46204 | G5: Fin: | H5: 46722
A6: Leads: | B6: Hasta 8 indicadores predictivos a la derecha. L1–L2 = apuesta principal del equipo; L3–L8 = indicadores de apoyo. Nombre (fila 8) y meta mensual (fila 9) editables en azul.
A8: Periodos: | B8: =COUNT(A11:A28) -> 18 | H8: Lead → | I8: L1. Costo local absoluto del mes vs. mes base (≤100%) | K8: L2. Headcount local de apoyo vs. plan plano (≤100%) | M8: L3. Vacantes de apoyo cubiertas con productividad, no contratación | O8: L4. % de crecimiento de ingreso absorbido sin nuevo costo local | Q8: L5. Iniciativas de automatización/eficiencia en marcha | S8: L6. Revisión mensual de costo local por área ejecutada (1 = sí) | U8: (Disponible) | W8: (Disponible)
A9: Celdas azules = se digitan cada lunes. Celdas negras = fórmulas, no tocar. | H9: Meta → | I9: 1 | K9: 1 | M9: 1 | O9: 1 | Q9: 1 | S9: 1
A10: # | B10: Mes | C10: Meta | D10: Real | G10: Brecha vs meta | H10: Estado | I10: Real | J10: % | K10: Real | L10: % | M10: Real | N10: % | O10: Real | P10: % | Q10: Real | R10: % | S10: Real | T10: % | U10: Real | V10: % | W10: Real | X10: %
A11: 1 | B11: 46204 | C11: =$B$5 -> 0.09 | G11: =IF(D11="","",D11-C11) | H11: =IF(D11="","",IF(D11<=C11,"En meta",IF(D11<=C11+0.01,"Riesgo","Atrasado"))) | J11: =IF(I11="","",IF($I$9="","",IF($I$9=0,"",I11/$I$9))) | L11: =IF(K11="","",IF($K$9="","",IF($K$9=0,"",K11/$K$9))) | N11: =IF(M11="","",IF($M$9="","",IF($M$9=0,"",M11/$M$9))) | P11: =IF(O11="","",IF($O$9="","",IF($O$9=0,"",O11/$O$9))) | R11: =IF(Q11="","",IF($Q$9="","",IF($Q$9=0,"",Q11/$Q$9))) | T11: =IF(S11="","",IF($S$9="","",IF($S$9=0,"",S11/$S$9))) | V11: =IF(U11="","",IF($U$9="","",IF($U$9=0,"",U11/$U$9))) | X11: =IF(W11="","",IF($W$9="","",IF($W$9=0,"",W11/$W$9)))
A12: 2 | B12: 46235 | C12: =$B$5 -> 0.09 | G12: =IF(D12="","",D12-C12) | H12: =IF(D12="","",IF(D12<=C12,"En meta",IF(D12<=C12+0.01,"Riesgo","Atrasado"))) | J12: =IF(I12="","",IF($I$9="","",IF($I$9=0,"",I12/$I$9))) | L12: =IF(K12="","",IF($K$9="","",IF($K$9=0,"",K12/$K$9))) | N12: =IF(M12="","",IF($M$9="","",IF($M$9=0,"",M12/$M$9))) | P12: =IF(O12="","",IF($O$9="","",IF($O$9=0,"",O12/$O$9))) | R12: =IF(Q12="","",IF($Q$9="","",IF($Q$9=0,"",Q12/$Q$9))) | T12: =IF(S12="","",IF($S$9="","",IF($S$9=0,"",S12/$S$9))) | V12: =IF(U12="","",IF($U$9="","",IF($U$9=0,"",U12/$U$9))) | X12: =IF(W12="","",IF($W$9="","",IF($W$9=0,"",W12/$W$9)))
A13: 3 | B13: 46266 | C13: =$B$5 -> 0.09 | G13: =IF(D13="","",D13-C13) | H13: =IF(D13="","",IF(D13<=C13,"En meta",IF(D13<=C13+0.01,"Riesgo","Atrasado"))) | J13: =IF(I13="","",IF($I$9="","",IF($I$9=0,"",I13/$I$9))) | L13: =IF(K13="","",IF($K$9="","",IF($K$9=0,"",K13/$K$9))) | N13: =IF(M13="","",IF($M$9="","",IF($M$9=0,"",M13/$M$9))) | P13: =IF(O13="","",IF($O$9="","",IF($O$9=0,"",O13/$O$9))) | R13: =IF(Q13="","",IF($Q$9="","",IF($Q$9=0,"",Q13/$Q$9))) | T13: =IF(S13="","",IF($S$9="","",IF($S$9=0,"",S13/$S$9))) | V13: =IF(U13="","",IF($U$9="","",IF($U$9=0,"",U13/$U$9))) | X13: =IF(W13="","",IF($W$9="","",IF($W$9=0,"",W13/$W$9)))
A14: 4 | B14: 46296 | C14: =$B$5 -> 0.09 | G14: =IF(D14="","",D14-C14) | H14: =IF(D14="","",IF(D14<=C14,"En meta",IF(D14<=C14+0.01,"Riesgo","Atrasado"))) | J14: =IF(I14="","",IF($I$9="","",IF($I$9=0,"",I14/$I$9))) | L14: =IF(K14="","",IF($K$9="","",IF($K$9=0,"",K14/$K$9))) | N14: =IF(M14="","",IF($M$9="","",IF($M$9=0,"",M14/$M$9))) | P14: =IF(O14="","",IF($O$9="","",IF($O$9=0,"",O14/$O$9))) | R14: =IF(Q14="","",IF($Q$9="","",IF($Q$9=0,"",Q14/$Q$9))) | T14: =IF(S14="","",IF($S$9="","",IF($S$9=0,"",S14/$S$9))) | V14: =IF(U14="","",IF($U$9="","",IF($U$9=0,"",U14/$U$9))) | X14: =IF(W14="","",IF($W$9="","",IF($W$9=0,"",W14/$W$9)))
A15: 5 | B15: 46327 | C15: =$B$5 -> 0.09 | G15: =IF(D15="","",D15-C15) | H15: =IF(D15="","",IF(D15<=C15,"En meta",IF(D15<=C15+0.01,"Riesgo","Atrasado"))) | J15: =IF(I15="","",IF($I$9="","",IF($I$9=0,"",I15/$I$9))) | L15: =IF(K15="","",IF($K$9="","",IF($K$9=0,"",K15/$K$9))) | N15: =IF(M15="","",IF($M$9="","",IF($M$9=0,"",M15/$M$9))) | P15: =IF(O15="","",IF($O$9="","",IF($O$9=0,"",O15/$O$9))) | R15: =IF(Q15="","",IF($Q$9="","",IF($Q$9=0,"",Q15/$Q$9))) | T15: =IF(S15="","",IF($S$9="","",IF($S$9=0,"",S15/$S$9))) | V15: =IF(U15="","",IF($U$9="","",IF($U$9=0,"",U15/$U$9))) | X15: =IF(W15="","",IF($W$9="","",IF($W$9=0,"",W15/$W$9)))
A16: 6 | B16: 46357 | C16: =$B$5 -> 0.09 | G16: =IF(D16="","",D16-C16) | H16: =IF(D16="","",IF(D16<=C16,"En meta",IF(D16<=C16+0.01,"Riesgo","Atrasado"))) | J16: =IF(I16="","",IF($I$9="","",IF($I$9=0,"",I16/$I$9))) | L16: =IF(K16="","",IF($K$9="","",IF($K$9=0,"",K16/$K$9))) | N16: =IF(M16="","",IF($M$9="","",IF($M$9=0,"",M16/$M$9))) | P16: =IF(O16="","",IF($O$9="","",IF($O$9=0,"",O16/$O$9))) | R16: =IF(Q16="","",IF($Q$9="","",IF($Q$9=0,"",Q16/$Q$9))) | T16: =IF(S16="","",IF($S$9="","",IF($S$9=0,"",S16/$S$9))) | V16: =IF(U16="","",IF($U$9="","",IF($U$9=0,"",U16/$U$9))) | X16: =IF(W16="","",IF($W$9="","",IF($W$9=0,"",W16/$W$9)))
A17: 7 | B17: 46388 | C17: =$B$5 -> 0.09 | G17: =IF(D17="","",D17-C17) | H17: =IF(D17="","",IF(D17<=C17,"En meta",IF(D17<=C17+0.01,"Riesgo","Atrasado"))) | J17: =IF(I17="","",IF($I$9="","",IF($I$9=0,"",I17/$I$9))) | L17: =IF(K17="","",IF($K$9="","",IF($K$9=0,"",K17/$K$9))) | N17: =IF(M17="","",IF($M$9="","",IF($M$9=0,"",M17/$M$9))) | P17: =IF(O17="","",IF($O$9="","",IF($O$9=0,"",O17/$O$9))) | R17: =IF(Q17="","",IF($Q$9="","",IF($Q$9=0,"",Q17/$Q$9))) | T17: =IF(S17="","",IF($S$9="","",IF($S$9=0,"",S17/$S$9))) | V17: =IF(U17="","",IF($U$9="","",IF($U$9=0,"",U17/$U$9))) | X17: =IF(W17="","",IF($W$9="","",IF($W$9=0,"",W17/$W$9)))
A18: 8 | B18: 46419 | C18: =$B$5 -> 0.09 | G18: =IF(D18="","",D18-C18) | H18: =IF(D18="","",IF(D18<=C18,"En meta",IF(D18<=C18+0.01,"Riesgo","Atrasado"))) | J18: =IF(I18="","",IF($I$9="","",IF($I$9=0,"",I18/$I$9))) | L18: =IF(K18="","",IF($K$9="","",IF($K$9=0,"",K18/$K$9))) | N18: =IF(M18="","",IF($M$9="","",IF($M$9=0,"",M18/$M$9))) | P18: =IF(O18="","",IF($O$9="","",IF($O$9=0,"",O18/$O$9))) | R18: =IF(Q18="","",IF($Q$9="","",IF($Q$9=0,"",Q18/$Q$9))) | T18: =IF(S18="","",IF($S$9="","",IF($S$9=0,"",S18/$S$9))) | V18: =IF(U18="","",IF($U$9="","",IF($U$9=0,"",U18/$U$9))) | X18: =IF(W18="","",IF($W$9="","",IF($W$9=0,"",W18/$W$9)))
A19: 9 | B19: 46447 | C19: =$B$5 -> 0.09 | G19: =IF(D19="","",D19-C19) | H19: =IF(D19="","",IF(D19<=C19,"En meta",IF(D19<=C19+0.01,"Riesgo","Atrasado"))) | J19: =IF(I19="","",IF($I$9="","",IF($I$9=0,"",I19/$I$9))) | L19: =IF(K19="","",IF($K$9="","",IF($K$9=0,"",K19/$K$9))) | N19: =IF(M19="","",IF($M$9="","",IF($M$9=0,"",M19/$M$9))) | P19: =IF(O19="","",IF($O$9="","",IF($O$9=0,"",O19/$O$9))) | R19: =IF(Q19="","",IF($Q$9="","",IF($Q$9=0,"",Q19/$Q$9))) | T19: =IF(S19="","",IF($S$9="","",IF($S$9=0,"",S19/$S$9))) | V19: =IF(U19="","",IF($U$9="","",IF($U$9=0,"",U19/$U$9))) | X19: =IF(W19="","",IF($W$9="","",IF($W$9=0,"",W19/$W$9)))
A20: 10 | B20: 46478 | C20: =$B$5 -> 0.09 | G20: =IF(D20="","",D20-C20) | H20: =IF(D20="","",IF(D20<=C20,"En meta",IF(D20<=C20+0.01,"Riesgo","Atrasado"))) | J20: =IF(I20="","",IF($I$9="","",IF($I$9=0,"",I20/$I$9))) | L20: =IF(K20="","",IF($K$9="","",IF($K$9=0,"",K20/$K$9))) | N20: =IF(M20="","",IF($M$9="","",IF($M$9=0,"",M20/$M$9))) | P20: =IF(O20="","",IF($O$9="","",IF($O$9=0,"",O20/$O$9))) | R20: =IF(Q20="","",IF($Q$9="","",IF($Q$9=0,"",Q20/$Q$9))) | T20: =IF(S20="","",IF($S$9="","",IF($S$9=0,"",S20/$S$9))) | V20: =IF(U20="","",IF($U$9="","",IF($U$9=0,"",U20/$U$9))) | X20: =IF(W20="","",IF($W$9="","",IF($W$9=0,"",W20/$W$9)))
A21: 11 | B21: 46508 | C21: =$B$5 -> 0.09 | G21: =IF(D21="","",D21-C21) | H21: =IF(D21="","",IF(D21<=C21,"En meta",IF(D21<=C21+0.01,"Riesgo","Atrasado"))) | J21: =IF(I21="","",IF($I$9="","",IF($I$9=0,"",I21/$I$9))) | L21: =IF(K21="","",IF($K$9="","",IF($K$9=0,"",K21/$K$9))) | N21: =IF(M21="","",IF($M$9="","",IF($M$9=0,"",M21/$M$9))) | P21: =IF(O21="","",IF($O$9="","",IF($O$9=0,"",O21/$O$9))) | R21: =IF(Q21="","",IF($Q$9="","",IF($Q$9=0,"",Q21/$Q$9))) | T21: =IF(S21="","",IF($S$9="","",IF($S$9=0,"",S21/$S$9))) | V21: =IF(U21="","",IF($U$9="","",IF($U$9=0,"",U21/$U$9))) | X21: =IF(W21="","",IF($W$9="","",IF($W$9=0,"",W21/$W$9)))
A22: 12 | B22: 46539 | C22: =$B$5 -> 0.09 | G22: =IF(D22="","",D22-C22) | H22: =IF(D22="","",IF(D22<=C22,"En meta",IF(D22<=C22+0.01,"Riesgo","Atrasado"))) | J22: =IF(I22="","",IF($I$9="","",IF($I$9=0,"",I22/$I$9))) | L22: =IF(K22="","",IF($K$9="","",IF($K$9=0,"",K22/$K$9))) | N22: =IF(M22="","",IF($M$9="","",IF($M$9=0,"",M22/$M$9))) | P22: =IF(O22="","",IF($O$9="","",IF($O$9=0,"",O22/$O$9))) | R22: =IF(Q22="","",IF($Q$9="","",IF($Q$9=0,"",Q22/$Q$9))) | T22: =IF(S22="","",IF($S$9="","",IF($S$9=0,"",S22/$S$9))) | V22: =IF(U22="","",IF($U$9="","",IF($U$9=0,"",U22/$U$9))) | X22: =IF(W22="","",IF($W$9="","",IF($W$9=0,"",W22/$W$9)))
... A28: 18 | B28: 46722 | C28: =$B$5 -> 0.09 | G28: =IF(D28="","",D28-C28) | H28: =IF(D28="","",IF(D28<=C28,"En meta",IF(D28<=C28+0.01,"Riesgo","Atrasado"))) | J28: =IF(I28="","",IF($I$9="","",IF($I$9=0,"",I28/$I$9))) | L28: =IF(K28="","",IF($K$9="","",IF($K$9=0,"",K28/$K$9))) | N28: =IF(M28="","",IF($M$9="","",IF($M$9=0,"",M28/$M$9))) | P28: =IF(O28="","",IF($O$9="","",IF($O$9=0,"",O28/$O$9))) | R28: =IF(Q28="","",IF($Q$9="","",IF($Q$9=0,"",Q28/$Q$9))) | T28: =IF(S28="","",IF($S$9="","",IF($S$9=0,"",S28/$S$9))) | V28: =IF(U28="","",IF($U$9="","",IF($U$9=0,"",U28/$U$9))) | X28: =IF(W28="","",IF($W$9="","",IF($W$9=0,"",W28/$W$9)))

Sheet 11. Recuperar DS
A1: WIG 11 — Recuperar el margen de Digital Solutions y eliminar líneas con GP negativo
A2: Indicador lag: | B2: GP del mes de las líneas hoy negativas (Digital Solutions + service-attach): de negativo a positivo (USD).
A3: De X a Y: | B3: De ~-$78K/mes de arrastre (DS + líneas negativas) a GP ≥ $0 y luego positivo, antes de dic 2027.
A4: Dueño: | B4: Por asignar | D4: Equipo: | E4: Ventas, Pre-Sales, Del - DS, Finanzas
A5: Meta: | B5: 0 | D5: Inicio: | E5: 46204 | G5: Fin: | H5: 46722
A6: Leads: | B6: Hasta 8 indicadores predictivos a la derecha. L1–L2 = apuesta principal del equipo; L3–L8 = indicadores de apoyo. Nombre (fila 8) y meta mensual (fila 9) editables en azul.
A8: Periodos: | B8: =COUNT(A11:A28) -> 18 | H8: Lead → | I8: L1. % negocios DS cotizados con GP ≥ piso de margen | K8: L2. Líneas con GP negativo re-precificadas o cerradas (acum.) | M8: L3. Contratos DS renegociados al alza en el mes | O8: L4. % utilización de la célula / SOC | Q8: L5. Revisión de rentabilidad por línea DS ejecutada (1 = sí) | S8: L6. Casos de service-attach negativo investigados | U8: (Disponible) | W8: (Disponible)
A9: Celdas azules = se digitan cada lunes. Celdas negras = fórmulas, no tocar. | H9: Meta → | I9: 1 | K9: 1 | M9: 1 | O9: 0.7 | Q9: 1 | S9: 2
A10: # | B10: Mes | C10: Meta | D10: Real | G10: Brecha vs meta | H10: Estado | I10: Real | J10: % | K10: Real | L10: % | M10: Real | N10: % | O10: Real | P10: % | Q10: Real | R10: % | S10: Real | T10: % | U10: Real | V10: % | W10: Real | X10: %
A11: 1 | B11: 46204 | C11: =$B$5 -> 0 | G11: =IF(D11="","",D11-C11) | H11: =IF(D11="","",IF(D11>=C11,"En meta",IF(D11>=C11-10000,"Riesgo","Atrasado"))) | J11: =IF(I11="","",IF($I$9="","",IF($I$9=0,"",I11/$I$9))) | L11: =IF(K11="","",IF($K$9="","",IF($K$9=0,"",K11/$K$9))) | N11: =IF(M11="","",IF($M$9="","",IF($M$9=0,"",M11/$M$9))) | P11: =IF(O11="","",IF($O$9="","",IF($O$9=0,"",O11/$O$9))) | R11: =IF(Q11="","",IF($Q$9="","",IF($Q$9=0,"",Q11/$Q$9))) | T11: =IF(S11="","",IF($S$9="","",IF($S$9=0,"",S11/$S$9))) | V11: =IF(U11="","",IF($U$9="","",IF($U$9=0,"",U11/$U$9))) | X11: =IF(W11="","",IF($W$9="","",IF($W$9=0,"",W11/$W$9)))
A12: 2 | B12: 46235 | C12: =$B$5 -> 0 | G12: =IF(D12="","",D12-C12) | H12: =IF(D12="","",IF(D12>=C12,"En meta",IF(D12>=C12-10000,"Riesgo","Atrasado"))) | J12: =IF(I12="","",IF($I$9="","",IF($I$9=0,"",I12/$I$9))) | L12: =IF(K12="","",IF($K$9="","",IF($K$9=0,"",K12/$K$9))) | N12: =IF(M12="","",IF($M$9="","",IF($M$9=0,"",M12/$M$9))) | P12: =IF(O12="","",IF($O$9="","",IF($O$9=0,"",O12/$O$9))) | R12: =IF(Q12="","",IF($Q$9="","",IF($Q$9=0,"",Q12/$Q$9))) | T12: =IF(S12="","",IF($S$9="","",IF($S$9=0,"",S12/$S$9))) | V12: =IF(U12="","",IF($U$9="","",IF($U$9=0,"",U12/$U$9))) | X12: =IF(W12="","",IF($W$9="","",IF($W$9=0,"",W12/$W$9)))
A13: 3 | B13: 46266 | C13: =$B$5 -> 0 | G13: =IF(D13="","",D13-C13) | H13: =IF(D13="","",IF(D13>=C13,"En meta",IF(D13>=C13-10000,"Riesgo","Atrasado"))) | J13: =IF(I13="","",IF($I$9="","",IF($I$9=0,"",I13/$I$9))) | L13: =IF(K13="","",IF($K$9="","",IF($K$9=0,"",K13/$K$9))) | N13: =IF(M13="","",IF($M$9="","",IF($M$9=0,"",M13/$M$9))) | P13: =IF(O13="","",IF($O$9="","",IF($O$9=0,"",O13/$O$9))) | R13: =IF(Q13="","",IF($Q$9="","",IF($Q$9=0,"",Q13/$Q$9))) | T13: =IF(S13="","",IF($S$9="","",IF($S$9=0,"",S13/$S$9))) | V13: =IF(U13="","",IF($U$9="","",IF($U$9=0,"",U13/$U$9))) | X13: =IF(W13="","",IF($W$9="","",IF($W$9=0,"",W13/$W$9)))
A14: 4 | B14: 46296 | C14: =$B$5 -> 0 | G14: =IF(D14="","",D14-C14) | H14: =IF(D14="","",IF(D14>=C14,"En meta",IF(D14>=C14-10000,"Riesgo","Atrasado"))) | J14: =IF(I14="","",IF($I$9="","",IF($I$9=0,"",I14/$I$9))) | L14: =IF(K14="","",IF($K$9="","",IF($K$9=0,"",K14/$K$9))) | N14: =IF(M14="","",IF($M$9="","",IF($M$9=0,"",M14/$M$9))) | P14: =IF(O14="","",IF($O$9="","",IF($O$9=0,"",O14/$O$9))) | R14: =IF(Q14="","",IF($Q$9="","",IF($Q$9=0,"",Q14/$Q$9))) | T14: =IF(S14="","",IF($S$9="","",IF($S$9=0,"",S14/$S$9))) | V14: =IF(U14="","",IF($U$9="","",IF($U$9=0,"",U14/$U$9))) | X14: =IF(W14="","",IF($W$9="","",IF($W$9=0,"",W14/$W$9)))
A15: 5 | B15: 46327 | C15: =$B$5 -> 0 | G15: =IF(D15="","",D15-C15) | H15: =IF(D15="","",IF(D15>=C15,"En meta",IF(D15>=C15-10000,"Riesgo","Atrasado"))) | J15: =IF(I15="","",IF($I$9="","",IF($I$9=0,"",I15/$I$9))) | L15: =IF(K15="","",IF($K$9="","",IF($K$9=0,"",K15/$K$9))) | N15: =IF(M15="","",IF($M$9="","",IF($M$9=0,"",M15/$M$9))) | P15: =IF(O15="","",IF($O$9="","",IF($O$9=0,"",O15/$O$9))) | R15: =IF(Q15="","",IF($Q$9="","",IF($Q$9=0,"",Q15/$Q$9))) | T15: =IF(S15="","",IF($S$9="","",IF($S$9=0,"",S15/$S$9))) | V15: =IF(U15="","",IF($U$9="","",IF($U$9=0,"",U15/$U$9))) | X15: =IF(W15="","",IF($W$9="","",IF($W$9=0,"",W15/$W$9)))
A16: 6 | B16: 46357 | C16: =$B$5 -> 0 | G16: =IF(D16="","",D16-C16) | H16: =IF(D16="","",IF(D16>=C16,"En meta",IF(D16>=C16-10000,"Riesgo","Atrasado"))) | J16: =IF(I16="","",IF($I$9="","",IF($I$9=0,"",I16/$I$9))) | L16: =IF(K16="","",IF($K$9="","",IF($K$9=0,"",K16/$K$9))) | N16: =IF(M16="","",IF($M$9="","",IF($M$9=0,"",M16/$M$9))) | P16: =IF(O16="","",IF($O$9="","",IF($O$9=0,"",O16/$O$9))) | R16: =IF(Q16="","",IF($Q$9="","",IF($Q$9=0,"",Q16/$Q$9))) | T16: =IF(S16="","",IF($S$9="","",IF($S$9=0,"",S16/$S$9))) | V16: =IF(U16="","",IF($U$9="","",IF($U$9=0,"",U16/$U$9))) | X16: =IF(W16="","",IF($W$9="","",IF($W$9=0,"",W16/$W$9)))
A17: 7 | B17: 46388 | C17: =$B$5 -> 0 | G17: =IF(D17="","",D17-C17) | H17: =IF(D17="","",IF(D17>=C17,"En meta",IF(D17>=C17-10000,"Riesgo","Atrasado"))) | J17: =IF(I17="","",IF($I$9="","",IF($I$9=0,"",I17/$I$9))) | L17: =IF(K17="","",IF($K$9="","",IF($K$9=0,"",K17/$K$9))) | N17: =IF(M17="","",IF($M$9="","",IF($M$9=0,"",M17/$M$9))) | P17: =IF(O17="","",IF($O$9="","",IF($O$9=0,"",O17/$O$9))) | R17: =IF(Q17="","",IF($Q$9="","",IF($Q$9=0,"",Q17/$Q$9))) | T17: =IF(S17="","",IF($S$9="","",IF($S$9=0,"",S17/$S$9))) | V17: =IF(U17="","",IF($U$9="","",IF($U$9=0,"",U17/$U$9))) | X17: =IF(W17="","",IF($W$9="","",IF($W$9=0,"",W17/$W$9)))
A18: 8 | B18: 46419 | C18: =$B$5 -> 0 | G18: =IF(D18="","",D18-C18) | H18: =IF(D18="","",IF(D18>=C18,"En meta",IF(D18>=C18-10000,"Riesgo","Atrasado"))) | J18: =IF(I18="","",IF($I$9="","",IF($I$9=0,"",I18/$I$9))) | L18: =IF(K18="","",IF($K$9="","",IF($K$9=0,"",K18/$K$9))) | N18: =IF(M18="","",IF($M$9="","",IF($M$9=0,"",M18/$M$9))) | P18: =IF(O18="","",IF($O$9="","",IF($O$9=0,"",O18/$O$9))) | R18: =IF(Q18="","",IF($Q$9="","",IF($Q$9=0,"",Q18/$Q$9))) | T18: =IF(S18="","",IF($S$9="","",IF($S$9=0,"",S18/$S$9))) | V18: =IF(U18="","",IF($U$9="","",IF($U$9=0,"",U18/$U$9))) | X18: =IF(W18="","",IF($W$9="","",IF($W$9=0,"",W18/$W$9)))
A19: 9 | B19: 46447 | C19: =$B$5 -> 0 | G19: =IF(D19="","",D19-C19) | H19: =IF(D19="","",IF(D19>=C19,"En meta",IF(D19>=C19-10000,"Riesgo","Atrasado"))) | J19: =IF(I19="","",IF($I$9="","",IF($I$9=0,"",I19/$I$9))) | L19: =IF(K19="","",IF($K$9="","",IF($K$9=0,"",K19/$K$9))) | N19: =IF(M19="","",IF($M$9="","",IF($M$9=0,"",M19/$M$9))) | P19: =IF(O19="","",IF($O$9="","",IF($O$9=0,"",O19/$O$9))) | R19: =IF(Q19="","",IF($Q$9="","",IF($Q$9=0,"",Q19/$Q$9))) | T19: =IF(S19="","",IF($S$9="","",IF($S$9=0,"",S19/$S$9))) | V19: =IF(U19="","",IF($U$9="","",IF($U$9=0,"",U19/$U$9))) | X19: =IF(W19="","",IF($W$9="","",IF($W$9=0,"",W19/$W$9)))
A20: 10 | B20: 46478 | C20: =$B$5 -> 0 | G20: =IF(D20="","",D20-C20) | H20: =IF(D20="","",IF(D20>=C20,"En meta",IF(D20>=C20-10000,"Riesgo","Atrasado"))) | J20: =IF(I20="","",IF($I$9="","",IF($I$9=0,"",I20/$I$9))) | L20: =IF(K20="","",IF($K$9="","",IF($K$9=0,"",K20/$K$9))) | N20: =IF(M20="","",IF($M$9="","",IF($M$9=0,"",M20/$M$9))) | P20: =IF(O20="","",IF($O$9="","",IF($O$9=0,"",O20/$O$9))) | R20: =IF(Q20="","",IF($Q$9="","",IF($Q$9=0,"",Q20/$Q$9))) | T20: =IF(S20="","",IF($S$9="","",IF($S$9=0,"",S20/$S$9))) | V20: =IF(U20="","",IF($U$9="","",IF($U$9=0,"",U20/$U$9))) | X20: =IF(W20="","",IF($W$9="","",IF($W$9=0,"",W20/$W$9)))
A21: 11 | B21: 46508 | C21: =$B$5 -> 0 | G21: =IF(D21="","",D21-C21) | H21: =IF(D21="","",IF(D21>=C21,"En meta",IF(D21>=C21-10000,"Riesgo","Atrasado"))) | J21: =IF(I21="","",IF($I$9="","",IF($I$9=0,"",I21/$I$9))) | L21: =IF(K21="","",IF($K$9="","",IF($K$9=0,"",K21/$K$9))) | N21: =IF(M21="","",IF($M$9="","",IF($M$9=0,"",M21/$M$9))) | P21: =IF(O21="","",IF($O$9="","",IF($O$9=0,"",O21/$O$9))) | R21: =IF(Q21="","",IF($Q$9="","",IF($Q$9=0,"",Q21/$Q$9))) | T21: =IF(S21="","",IF($S$9="","",IF($S$9=0,"",S21/$S$9))) | V21: =IF(U21="","",IF($U$9="","",IF($U$9=0,"",U21/$U$9))) | X21: =IF(W21="","",IF($W$9="","",IF($W$9=0,"",W21/$W$9)))
A22: 12 | B22: 46539 | C22: =$B$5 -> 0 | G22: =IF(D22="","",D22-C22) | H22: =IF(D22="","",IF(D22>=C22,"En meta",IF(D22>=C22-10000,"Riesgo","Atrasado"))) | J22: =IF(I22="","",IF($I$9="","",IF($I$9=0,"",I22/$I$9))) | L22: =IF(K22="","",IF($K$9="","",IF($K$9=0,"",K22/$K$9))) | N22: =IF(M22="","",IF($M$9="","",IF($M$9=0,"",M22/$M$9))) | P22: =IF(O22="","",IF($O$9="","",IF($O$9=0,"",O22/$O$9))) | R22: =IF(Q22="","",IF($Q$9="","",IF($Q$9=0,"",Q22/$Q$9))) | T22: =IF(S22="","",IF($S$9="","",IF($S$9=0,"",S22/$S$9))) | V22: =IF(U22="","",IF($U$9="","",IF($U$9=0,"",U22/$U$9))) | X22: =IF(W22="","",IF($W$9="","",IF($W$9=0,"",W22/$W$9)))
... A28: 18 | B28: 46722 | C28: =$B$5 -> 0 | G28: =IF(D28="","",D28-C28) | H28: =IF(D28="","",IF(D28>=C28,"En meta",IF(D28>=C28-10000,"Riesgo","Atrasado"))) | J28: =IF(I28="","",IF($I$9="","",IF($I$9=0,"",I28/$I$9))) | L28: =IF(K28="","",IF($K$9="","",IF($K$9=0,"",K28/$K$9))) | N28: =IF(M28="","",IF($M$9="","",IF($M$9=0,"",M28/$M$9))) | P28: =IF(O28="","",IF($O$9="","",IF($O$9=0,"",O28/$O$9))) | R28: =IF(Q28="","",IF($Q$9="","",IF($Q$9=0,"",Q28/$Q$9))) | T28: =IF(S28="","",IF($S$9="","",IF($S$9=0,"",S28/$S$9))) | V28: =IF(U28="","",IF($U$9="","",IF($U$9=0,"",U28/$U$9))) | X28: =IF(W28="","",IF($W$9="","",IF($W$9=0,"",W28/$W$9)))

Sheet 12. Utilizacion
A1: WIG 12 — Subir la utilización facturable de ingenieros locales de 42% a 48%+
A2: Indicador lag: | B2: % de horas facturables sobre horas disponibles de los ingenieros locales (mes). Costo ya fijo = margen directo.
A3: De X a Y: | B3: De 42% a ≥48% de utilización facturable, sostenido, antes de dic 2027.
A4: Dueño: | B4: Por asignar | D4: Equipo: | E4: Del - TSS, Del - DC, Customer Success, Pre-Sales
A5: Meta: | B5: 0.48 | D5: Inicio: | E5: 46204 | G5: Fin: | H5: 46722
A6: Leads: | B6: Hasta 8 indicadores predictivos a la derecha. L1–L2 = apuesta principal del equipo; L3–L8 = indicadores de apoyo. Nombre (fila 8) y meta mensual (fila 9) editables en azul.
A8: Periodos: | B8: =COUNT(A11:A28) -> 18 | H8: Lead → | I8: L1. Horas facturables registradas en el mes vs. meta | K8: L2. % de timesheets completos y a tiempo | M8: L3. Horas advisory/billable vendidas en el mes | O8: L4. Ingenieros con utilización < 40% con plan de acción | Q8: L5. Proyectos con staffing confirmado 2 semanas antes | S8: L6. % de horas no facturables justificadas/categorizadas | U8: (Disponible) | W8: (Disponible)
A9: Celdas azules = se digitan cada lunes. Celdas negras = fórmulas, no tocar. | H9: Meta → | I9: 1 | K9: 1 | M9: 40 | O9: 1 | Q9: 3 | S9: 1
A10: # | B10: Mes | C10: Meta | D10: Real | G10: Brecha vs meta | H10: Estado | I10: Real | J10: % | K10: Real | L10: % | M10: Real | N10: % | O10: Real | P10: % | Q10: Real | R10: % | S10: Real | T10: % | U10: Real | V10: % | W10: Real | X10: %
A11: 1 | B11: 46204 | C11: =$B$5 -> 0.48 | G11: =IF(D11="","",D11-C11) | H11: =IF(D11="","",IF(D11>=C11,"En meta",IF(D11>=C11-0.03,"Riesgo","Atrasado"))) | J11: =IF(I11="","",IF($I$9="","",IF($I$9=0,"",I11/$I$9))) | L11: =IF(K11="","",IF($K$9="","",IF($K$9=0,"",K11/$K$9))) | N11: =IF(M11="","",IF($M$9="","",IF($M$9=0,"",M11/$M$9))) | P11: =IF(O11="","",IF($O$9="","",IF($O$9=0,"",O11/$O$9))) | R11: =IF(Q11="","",IF($Q$9="","",IF($Q$9=0,"",Q11/$Q$9))) | T11: =IF(S11="","",IF($S$9="","",IF($S$9=0,"",S11/$S$9))) | V11: =IF(U11="","",IF($U$9="","",IF($U$9=0,"",U11/$U$9))) | X11: =IF(W11="","",IF($W$9="","",IF($W$9=0,"",W11/$W$9)))
A12: 2 | B12: 46235 | C12: =$B$5 -> 0.48 | G12: =IF(D12="","",D12-C12) | H12: =IF(D12="","",IF(D12>=C12,"En meta",IF(D12>=C12-0.03,"Riesgo","Atrasado"))) | J12: =IF(I12="","",IF($I$9="","",IF($I$9=0,"",I12/$I$9))) | L12: =IF(K12="","",IF($K$9="","",IF($K$9=0,"",K12/$K$9))) | N12: =IF(M12="","",IF($M$9="","",IF($M$9=0,"",M12/$M$9))) | P12: =IF(O12="","",IF($O$9="","",IF($O$9=0,"",O12/$O$9))) | R12: =IF(Q12="","",IF($Q$9="","",IF($Q$9=0,"",Q12/$Q$9))) | T12: =IF(S12="","",IF($S$9="","",IF($S$9=0,"",S12/$S$9))) | V12: =IF(U12="","",IF($U$9="","",IF($U$9=0,"",U12/$U$9))) | X12: =IF(W12="","",IF($W$9="","",IF($W$9=0,"",W12/$W$9)))
A13: 3 | B13: 46266 | C13: =$B$5 -> 0.48 | G13: =IF(D13="","",D13-C13) | H13: =IF(D13="","",IF(D13>=C13,"En meta",IF(D13>=C13-0.03,"Riesgo","Atrasado"))) | J13: =IF(I13="","",IF($I$9="","",IF($I$9=0,"",I13/$I$9))) | L13: =IF(K13="","",IF($K$9="","",IF($K$9=0,"",K13/$K$9))) | N13: =IF(M13="","",IF($M$9="","",IF($M$9=0,"",M13/$M$9))) | P13: =IF(O13="","",IF($O$9="","",IF($O$9=0,"",O13/$O$9))) | R13: =IF(Q13="","",IF($Q$9="","",IF($Q$9=0,"",Q13/$Q$9))) | T13: =IF(S13="","",IF($S$9="","",IF($S$9=0,"",S13/$S$9))) | V13: =IF(U13="","",IF($U$9="","",IF($U$9=0,"",U13/$U$9))) | X13: =IF(W13="","",IF($W$9="","",IF($W$9=0,"",W13/$W$9)))
A14: 4 | B14: 46296 | C14: =$B$5 -> 0.48 | G14: =IF(D14="","",D14-C14) | H14: =IF(D14="","",IF(D14>=C14,"En meta",IF(D14>=C14-0.03,"Riesgo","Atrasado"))) | J14: =IF(I14="","",IF($I$9="","",IF($I$9=0,"",I14/$I$9))) | L14: =IF(K14="","",IF($K$9="","",IF($K$9=0,"",K14/$K$9))) | N14: =IF(M14="","",IF($M$9="","",IF($M$9=0,"",M14/$M$9))) | P14: =IF(O14="","",IF($O$9="","",IF($O$9=0,"",O14/$O$9))) | R14: =IF(Q14="","",IF($Q$9="","",IF($Q$9=0,"",Q14/$Q$9))) | T14: =IF(S14="","",IF($S$9="","",IF($S$9=0,"",S14/$S$9))) | V14: =IF(U14="","",IF($U$9="","",IF($U$9=0,"",U14/$U$9))) | X14: =IF(W14="","",IF($W$9="","",IF($W$9=0,"",W14/$W$9)))
A15: 5 | B15: 46327 | C15: =$B$5 -> 0.48 | G15: =IF(D15="","",D15-C15) | H15: =IF(D15="","",IF(D15>=C15,"En meta",IF(D15>=C15-0.03,"Riesgo","Atrasado"))) | J15: =IF(I15="","",IF($I$9="","",IF($I$9=0,"",I15/$I$9))) | L15: =IF(K15="","",IF($K$9="","",IF($K$9=0,"",K15/$K$9))) | N15: =IF(M15="","",IF($M$9="","",IF($M$9=0,"",M15/$M$9))) | P15: =IF(O15="","",IF($O$9="","",IF($O$9=0,"",O15/$O$9))) | R15: =IF(Q15="","",IF($Q$9="","",IF($Q$9=0,"",Q15/$Q$9))) | T15: =IF(S15="","",IF($S$9="","",IF($S$9=0,"",S15/$S$9))) | V15: =IF(U15="","",IF($U$9="","",IF($U$9=0,"",U15/$U$9))) | X15: =IF(W15="","",IF($W$9="","",IF($W$9=0,"",W15/$W$9)))
A16: 6 | B16: 46357 | C16: =$B$5 -> 0.48 | G16: =IF(D16="","",D16-C16) | H16: =IF(D16="","",IF(D16>=C16,"En meta",IF(D16>=C16-0.03,"Riesgo","Atrasado"))) | J16: =IF(I16="","",IF($I$9="","",IF($I$9=0,"",I16/$I$9))) | L16: =IF(K16="","",IF($K$9="","",IF($K$9=0,"",K16/$K$9))) | N16: =IF(M16="","",IF($M$9="","",IF($M$9=0,"",M16/$M$9))) | P16: =IF(O16="","",IF($O$9="","",IF($O$9=0,"",O16/$O$9))) | R16: =IF(Q16="","",IF($Q$9="","",IF($Q$9=0,"",Q16/$Q$9))) | T16: =IF(S16="","",IF($S$9="","",IF($S$9=0,"",S16/$S$9))) | V16: =IF(U16="","",IF($U$9="","",IF($U$9=0,"",U16/$U$9))) | X16: =IF(W16="","",IF($W$9="","",IF($W$9=0,"",W16/$W$9)))
A17: 7 | B17: 46388 | C17: =$B$5 -> 0.48 | G17: =IF(D17="","",D17-C17) | H17: =IF(D17="","",IF(D17>=C17,"En meta",IF(D17>=C17-0.03,"Riesgo","Atrasado"))) | J17: =IF(I17="","",IF($I$9="","",IF($I$9=0,"",I17/$I$9))) | L17: =IF(K17="","",IF($K$9="","",IF($K$9=0,"",K17/$K$9))) | N17: =IF(M17="","",IF($M$9="","",IF($M$9=0,"",M17/$M$9))) | P17: =IF(O17="","",IF($O$9="","",IF($O$9=0,"",O17/$O$9))) | R17: =IF(Q17="","",IF($Q$9="","",IF($Q$9=0,"",Q17/$Q$9))) | T17: =IF(S17="","",IF($S$9="","",IF($S$9=0,"",S17/$S$9))) | V17: =IF(U17="","",IF($U$9="","",IF($U$9=0,"",U17/$U$9))) | X17: =IF(W17="","",IF($W$9="","",IF($W$9=0,"",W17/$W$9)))
A18: 8 | B18: 46419 | C18: =$B$5 -> 0.48 | G18: =IF(D18="","",D18-C18) | H18: =IF(D18="","",IF(D18>=C18,"En meta",IF(D18>=C18-0.03,"Riesgo","Atrasado"))) | J18: =IF(I18="","",IF($I$9="","",IF($I$9=0,"",I18/$I$9))) | L18: =IF(K18="","",IF($K$9="","",IF($K$9=0,"",K18/$K$9))) | N18: =IF(M18="","",IF($M$9="","",IF($M$9=0,"",M18/$M$9))) | P18: =IF(O18="","",IF($O$9="","",IF($O$9=0,"",O18/$O$9))) | R18: =IF(Q18="","",IF($Q$9="","",IF($Q$9=0,"",Q18/$Q$9))) | T18: =IF(S18="","",IF($S$9="","",IF($S$9=0,"",S18/$S$9))) | V18: =IF(U18="","",IF($U$9="","",IF($U$9=0,"",U18/$U$9))) | X18: =IF(W18="","",IF($W$9="","",IF($W$9=0,"",W18/$W$9)))
A19: 9 | B19: 46447 | C19: =$B$5 -> 0.48 | G19: =IF(D19="","",D19-C19) | H19: =IF(D19="","",IF(D19>=C19,"En meta",IF(D19>=C19-0.03,"Riesgo","Atrasado"))) | J19: =IF(I19="","",IF($I$9="","",IF($I$9=0,"",I19/$I$9))) | L19: =IF(K19="","",IF($K$9="","",IF($K$9=0,"",K19/$K$9))) | N19: =IF(M19="","",IF($M$9="","",IF($M$9=0,"",M19/$M$9))) | P19: =IF(O19="","",IF($O$9="","",IF($O$9=0,"",O19/$O$9))) | R19: =IF(Q19="","",IF($Q$9="","",IF($Q$9=0,"",Q19/$Q$9))) | T19: =IF(S19="","",IF($S$9="","",IF($S$9=0,"",S19/$S$9))) | V19: =IF(U19="","",IF($U$9="","",IF($U$9=0,"",U19/$U$9))) | X19: =IF(W19="","",IF($W$9="","",IF($W$9=0,"",W19/$W$9)))
A20: 10 | B20: 46478 | C20: =$B$5 -> 0.48 | G20: =IF(D20="","",D20-C20) | H20: =IF(D20="","",IF(D20>=C20,"En meta",IF(D20>=C20-0.03,"Riesgo","Atrasado"))) | J20: =IF(I20="","",IF($I$9="","",IF($I$9=0,"",I20/$I$9))) | L20: =IF(K20="","",IF($K$9="","",IF($K$9=0,"",K20/$K$9))) | N20: =IF(M20="","",IF($M$9="","",IF($M$9=0,"",M20/$M$9))) | P20: =IF(O20="","",IF($O$9="","",IF($O$9=0,"",O20/$O$9))) | R20: =IF(Q20="","",IF($Q$9="","",IF($Q$9=0,"",Q20/$Q$9))) | T20: =IF(S20="","",IF($S$9="","",IF($S$9=0,"",S20/$S$9))) | V20: =IF(U20="","",IF($U$9="","",IF($U$9=0,"",U20/$U$9))) | X20: =IF(W20="","",IF($W$9="","",IF($W$9=0,"",W20/$W$9)))
A21: 11 | B21: 46508 | C21: =$B$5 -> 0.48 | G21: =IF(D21="","",D21-C21) | H21: =IF(D21="","",IF(D21>=C21,"En meta",IF(D21>=C21-0.03,"Riesgo","Atrasado"))) | J21: =IF(I21="","",IF($I$9="","",IF($I$9=0,"",I21/$I$9))) | L21: =IF(K21="","",IF($K$9="","",IF($K$9=0,"",K21/$K$9))) | N21: =IF(M21="","",IF($M$9="","",IF($M$9=0,"",M21/$M$9))) | P21: =IF(O21="","",IF($O$9="","",IF($O$9=0,"",O21/$O$9))) | R21: =IF(Q21="","",IF($Q$9="","",IF($Q$9=0,"",Q21/$Q$9))) | T21: =IF(S21="","",IF($S$9="","",IF($S$9=0,"",S21/$S$9))) | V21: =IF(U21="","",IF($U$9="","",IF($U$9=0,"",U21/$U$9))) | X21: =IF(W21="","",IF($W$9="","",IF($W$9=0,"",W21/$W$9)))
A22: 12 | B22: 46539 | C22: =$B$5 -> 0.48 | G22: =IF(D22="","",D22-C22) | H22: =IF(D22="","",IF(D22>=C22,"En meta",IF(D22>=C22-0.03,"Riesgo","Atrasado"))) | J22: =IF(I22="","",IF($I$9="","",IF($I$9=0,"",I22/$I$9))) | L22: =IF(K22="","",IF($K$9="","",IF($K$9=0,"",K22/$K$9))) | N22: =IF(M22="","",IF($M$9="","",IF($M$9=0,"",M22/$M$9))) | P22: =IF(O22="","",IF($O$9="","",IF($O$9=0,"",O22/$O$9))) | R22: =IF(Q22="","",IF($Q$9="","",IF($Q$9=0,"",Q22/$Q$9))) | T22: =IF(S22="","",IF($S$9="","",IF($S$9=0,"",S22/$S$9))) | V22: =IF(U22="","",IF($U$9="","",IF($U$9=0,"",U22/$U$9))) | X22: =IF(W22="","",IF($W$9="","",IF($W$9=0,"",W22/$W$9)))
... A28: 18 | B28: 46722 | C28: =$B$5 -> 0.48 | G28: =IF(D28="","",D28-C28) | H28: =IF(D28="","",IF(D28>=C28,"En meta",IF(D28>=C28-0.03,"Riesgo","Atrasado"))) | J28: =IF(I28="","",IF($I$9="","",IF($I$9=0,"",I28/$I$9))) | L28: =IF(K28="","",IF($K$9="","",IF($K$9=0,"",K28/$K$9))) | N28: =IF(M28="","",IF($M$9="","",IF($M$9=0,"",M28/$M$9))) | P28: =IF(O28="","",IF($O$9="","",IF($O$9=0,"",O28/$O$9))) | R28: =IF(Q28="","",IF($Q$9="","",IF($Q$9=0,"",Q28/$Q$9))) | T28: =IF(S28="","",IF($S$9="","",IF($S$9=0,"",S28/$S$9))) | V28: =IF(U28="","",IF($U$9="","",IF($U$9=0,"",U28/$U$9))) | X28: =IF(W28="","",IF($W$9="","",IF($W$9=0,"",W28/$W$9)))

Sheet 2027
A1: 2027 — Meta de Utilidad Neta (NAT)
A2: Meta de utilidad neta después de impuestos para 2027. Debajo: el camino de GP y la cobertura de backlog — cuánto GP ya está comprometido por contratos conocidos y cuánto falta vender. Se actualiza cada semana de 2026.
A4: Ingreso meta: | B4: 21000000 | D4: GP meta %: | E4: 0.16
A5: GP meta (Ingreso × GP%): | B5: =B4*E4 -> 3360000 | D5: META NAT (utilidad neta): | E5: 1000000
A6: GP comprometido (último): | B6: =IFERROR(LOOKUP(2,1/($B$12:$B$40<>""),$B$12:$B$40),0) -> 0 | D6: % cobertura: | E6: =IFERROR(B6/B5,0) -> 0
A7: Brecha (falta vender): | B7: =B5-B6 -> 3360000 | D7: Margen NAT (NAT / Ingreso): | E7: 0.047619048
A9: Backlog comprometido por semana (2027)
A11: Semana | B11: GP comprometido (acum.) | C11: GP meta | D11: Brecha | E11: % cobertura
A12: 46188 | C12: =$B$5 -> 3360000 | D12: =IF(B12="","",C12-B12) | E12: =IF(B12="","",B12/C12)
A13: 46195 | C13: =$B$5 -> 3360000 | D13: =IF(B13="","",C13-B13) | E13: =IF(B13="","",B13/C13)
A14: 46202 | C14: =$B$5 -> 3360000 | D14: =IF(B14="","",C14-B14) | E14: =IF(B14="","",B14/C14)
A15: 46209 | C15: =$B$5 -> 3360000 | D15: =IF(B15="","",C15-B15) | E15: =IF(B15="","",B15/C15)
A16: 46216 | C16: =$B$5 -> 3360000 | D16: =IF(B16="","",C16-B16) | E16: =IF(B16="","",B16/C16)
A17: 46223 | C17: =$B$5 -> 3360000 | D17: =IF(B17="","",C17-B17) | E17: =IF(B17="","",B17/C17)
A18: 46230 | C18: =$B$5 -> 3360000 | D18: =IF(B18="","",C18-B18) | E18: =IF(B18="","",B18/C18)
A19: 46237 | C19: =$B$5 -> 3360000 | D19: =IF(B19="","",C19-B19) | E19: =IF(B19="","",B19/C19)
A20: 46244 | C20: =$B$5 -> 3360000 | D20: =IF(B20="","",C20-B20) | E20: =IF(B20="","",B20/C20)
A21: 46251 | C21: =$B$5 -> 3360000 | D21: =IF(B21="","",C21-B21) | E21: =IF(B21="","",B21/C21)
A22: 46258 | C22: =$B$5 -> 3360000 | D22: =IF(B22="","",C22-B22) | E22: =IF(B22="","",B22/C22)
A23: 46265 | C23: =$B$5 -> 3360000 | D23: =IF(B23="","",C23-B23) | E23: =IF(B23="","",B23/C23)
... A40: 46384 | C40: =$B$5 -> 3360000 | D40: =IF(B40="","",C40-B40) | E40: =IF(B40="","",B40/C40)

Sheet 2028
A1: 2028 — Meta de Utilidad Neta (NAT)
A2: Meta de utilidad neta después de impuestos para 2028. Debajo: el camino de GP y la cobertura de backlog — cuánto GP ya está comprometido por contratos conocidos y cuánto falta vender. Se actualiza cada semana de 2026.
A4: Ingreso meta: | B4: 28571000 | D4: GP meta %: | E4: 0.164
A5: GP meta (Ingreso × GP%): | B5: =B4*E4 -> 4685644 | D5: META NAT (utilidad neta): | E5: 2000000
A6: GP comprometido (último): | B6: =IFERROR(LOOKUP(2,1/($B$12:$B$40<>""),$B$12:$B$40),0) -> 0 | D6: % cobertura: | E6: =IFERROR(B6/B5,0) -> 0
A7: Brecha (falta vender): | B7: =B5-B6 -> 4685644 | D7: Margen NAT (NAT / Ingreso): | E7: 0.07000105
A9: Backlog comprometido por semana (2028)
A11: Semana | B11: GP comprometido (acum.) | C11: GP meta | D11: Brecha | E11: % cobertura
A12: 46188 | C12: =$B$5 -> 4685644 | D12: =IF(B12="","",C12-B12) | E12: =IF(B12="","",B12/C12)
A13: 46195 | C13: =$B$5 -> 4685644 | D13: =IF(B13="","",C13-B13) | E13: =IF(B13="","",B13/C13)
A14: 46202 | C14: =$B$5 -> 4685644 | D14: =IF(B14="","",C14-B14) | E14: =IF(B14="","",B14/C14)
A15: 46209 | C15: =$B$5 -> 4685644 | D15: =IF(B15="","",C15-B15) | E15: =IF(B15="","",B15/C15)
A16: 46216 | C16: =$B$5 -> 4685644 | D16: =IF(B16="","",C16-B16) | E16: =IF(B16="","",B16/C16)
A17: 46223 | C17: =$B$5 -> 4685644 | D17: =IF(B17="","",C17-B17) | E17: =IF(B17="","",B17/C17)
A18: 46230 | C18: =$B$5 -> 4685644 | D18: =IF(B18="","",C18-B18) | E18: =IF(B18="","",B18/C18)
A19: 46237 | C19: =$B$5 -> 4685644 | D19: =IF(B19="","",C19-B19) | E19: =IF(B19="","",B19/C19)
A20: 46244 | C20: =$B$5 -> 4685644 | D20: =IF(B20="","",C20-B20) | E20: =IF(B20="","",B20/C20)
A21: 46251 | C21: =$B$5 -> 4685644 | D21: =IF(B21="","",C21-B21) | E21: =IF(B21="","",B21/C21)
A22: 46258 | C22: =$B$5 -> 4685644 | D22: =IF(B22="","",C22-B22) | E22: =IF(B22="","",B22/C22)
A23: 46265 | C23: =$B$5 -> 4685644 | D23: =IF(B23="","",C23-B23) | E23: =IF(B23="","",B23/C23)
... A40: 46384 | C40: =$B$5 -> 4685644 | D40: =IF(B40="","",C40-B40) | E40: =IF(B40="","",B40/C40)

Sheet 2029
A1: 2029 — Meta de Utilidad Neta (NAT)
A2: Meta de utilidad neta después de impuestos para 2029. Debajo: el camino de GP y la cobertura de backlog — cuánto GP ya está comprometido por contratos conocidos y cuánto falta vender. Se actualiza cada semana de 2026.
A4: Ingreso meta: | B4: 30571000 | D4: GP meta %: | E4: 0.165
A5: GP meta (Ingreso × GP%): | B5: =B4*E4 -> 5044215 | D5: META NAT (utilidad neta): | E5: 2445680
A6: GP comprometido (último): | B6: =IFERROR(LOOKUP(2,1/($B$12:$B$40<>""),$B$12:$B$40),0) -> 0 | D6: % cobertura: | E6: =IFERROR(B6/B5,0) -> 0
A7: Brecha (falta vender): | B7: =B5-B6 -> 5044215 | D7: Margen NAT (NAT / Ingreso): | E7: 0.08
A9: Backlog comprometido por semana (2029)
A11: Semana | B11: GP comprometido (acum.) | C11: GP meta | D11: Brecha | E11: % cobertura
A12: 46188 | C12: =$B$5 -> 5044215 | D12: =IF(B12="","",C12-B12) | E12: =IF(B12="","",B12/C12)
A13: 46195 | C13: =$B$5 -> 5044215 | D13: =IF(B13="","",C13-B13) | E13: =IF(B13="","",B13/C13)
A14: 46202 | C14: =$B$5 -> 5044215 | D14: =IF(B14="","",C14-B14) | E14: =IF(B14="","",B14/C14)
A15: 46209 | C15: =$B$5 -> 5044215 | D15: =IF(B15="","",C15-B15) | E15: =IF(B15="","",B15/C15)
A16: 46216 | C16: =$B$5 -> 5044215 | D16: =IF(B16="","",C16-B16) | E16: =IF(B16="","",B16/C16)
A17: 46223 | C17: =$B$5 -> 5044215 | D17: =IF(B17="","",C17-B17) | E17: =IF(B17="","",B17/C17)
A18: 46230 | C18: =$B$5 -> 5044215 | D18: =IF(B18="","",C18-B18) | E18: =IF(B18="","",B18/C18)
A19: 46237 | C19: =$B$5 -> 5044215 | D19: =IF(B19="","",C19-B19) | E19: =IF(B19="","",B19/C19)
A20: 46244 | C20: =$B$5 -> 5044215 | D20: =IF(B20="","",C20-B20) | E20: =IF(B20="","",B20/C20)
A21: 46251 | C21: =$B$5 -> 5044215 | D21: =IF(B21="","",C21-B21) | E21: =IF(B21="","",B21/C21)
A22: 46258 | C22: =$B$5 -> 5044215 | D22: =IF(B22="","",C22-B22) | E22: =IF(B22="","",B22/C22)
A23: 46265 | C23: =$B$5 -> 5044215 | D23: =IF(B23="","",C23-B23) | E23: =IF(B23="","",B23/C23)
... A40: 46384 | C40: =$B$5 -> 5044215 | D40: =IF(B40="","",C40-B40) | E40: =IF(B40="","",B40/C40)

Sheet Tareas
A1: WIG | B1: Lead | C1: Tarea | D1: Responsable | E1: Estado | G1: Tareas de soporte por lead: cada fila es una acción concreta que sostiene un lead measure. WIG = número de pestaña (1–12), Lead = 1–8. Aparecen en el detalle del lead en el televisor. Estado: Pendiente · En curso · Hecho.
A2: 1 | B2: 3 | C2: Presentar la oferta Smart User a 100 clientes en 2026 | D2: Pre-Sales | E2: En curso
A3: 1 | B3: 1 | C3: Certificarse como Apple Authorized Service Provider para reparar equipos con mayor eficiencia | D3: Del - DEX | E3: Pendiente
A4: 1 | B4: 5 | C4: Mantener siempre 50 equipos en bodega listos para colocar | D4: Del - DEX | E4: En curso

Sheet Instrucciones
A1: Cómo usar este tablero 4DX
A3: RITUAL DEL LUNES (antes de la reunión de WIG):
A4: 1. Cada dueño de WIG abre su pestaña y digita en las celdas AZULES de la semana: el resultado real del lag (columna "Real") y el real de cada lead measure (columnas "Real" bajo cada lead, a la derecha).
A5: 2. Finanzas digita el NAT del mes en el Dashboard (columna "NAT real") cuando cierre el mes.
A6: 3. El Dashboard se actualiza solo, y el marcador del televisor se refresca arrastrando este archivo a la pantalla.
A7: 4. Suban el archivo actualizado a Claude cada lunes y pidan el marcador semanal para la reunión de cadencia.
A9: LEAD MEASURES (hasta 8 por WIG):
A10: • Cada WIG tiene hasta 8 indicadores predictivos en columnas a la derecha: el nombre (fila 8) y la meta semanal/mensual (fila 9) son editables en azul.
A11: • Los leads L1 y L2 son la apuesta principal: ahí el equipo rinde cuentas con compromisos semanales. L3–L8 son indicadores de apoyo que explican el resultado.
A12: • El % de cada lead se calcula automáticamente contra su meta. Dejar la meta vacía desactiva el lead ("(Disponible)").
A13: • Definan todos los leads en positivo (más = mejor) para que el % se lea igual en todos.
A15: TAREAS DE SOPORTE (pestaña «Tareas»):
... A26: Las lead measures son predictivas e influenciables por el equipo; el lag solo se mueve si las leads se cumplen. En la cadencia semanal cada quien rinde cuentas de sus compromisos sobre las leads, no sobre el lag.
